Workbook

Sheet Итоги
B2: "FBO", "FBS", "Гибрид", "Гибрид с Fulllog (3PL)" - Итоговая экономика
B5: Выручка: Гибрид с Fulllog (3PL) | E5: Валовая прибыль: Гибрид с Fulllog (3PL) | H5: Операционная прибыль: Гибрид с Fulllog (3PL) | K5: Операционная маржа: Гибрид с Fulllog (3PL)
B6: =F22 -> 13668020 | E6: =F24 -> 7765680 | H6: =F42 -> 3064646.8 | K6: =F43 -> 0.22422025
B10: КОНФИГУРАЦИЯ СЦЕНАРИЕВ | H10: Рекомендация
B11: Показатель | C11: FBO | D11: FBS | E11: Гибрид | F11: Гибрид с Fulllog (3PL) | H11: =IF(MAX(C42:F42)=F42,"Гибрид с Fulllog (3PL)",IF(MAX(C42:F42)=E42,"Гибрид",IF(MAX(C42:F42)=D42,"FBS","FBO"))) -> Гибрид с Fulllog (3PL)
B12: SKU → FBO, шт. | C12: =COUNTIF(Модель!$S$5:$S$44,"<>Пауза") -> 38 | D12: =0 -> 0 | E12: =COUNTIF(Модель!$S$5:$S$44,"FBO") -> 17 | F12: =E12 -> 17
B13: SKU → FBS, шт. | C13: =0 -> 0 | D13: =COUNTIF(Модель!$S$5:$S$44,"<>Пауза") -> 38 | E13: =COUNTIF(Модель!$S$5:$S$44,"FBS") -> 21 | F13: =E13 -> 21 | H13: При текущих тарифах передача FBS-операций Fulllog экономически выгоднее, чем самостоятельное создание и обслуживание полного FBS-контура Sportmaster
B14: SKU → Пауза, шт. | C14: =COUNTIF(Модель!$S$5:$S$44,"Пауза") -> 2 | D14: =COUNTIF(Модель!$S$5:$S$44,"Пауза") -> 2 | E14: =COUNTIF(Модель!$S$5:$S$44,"Пауза") -> 2 | F14: =COUNTIF(Модель!$S$5:$S$44,"Пауза") -> 2
B15: Рейсы собственного FBS → Ozon, раз/мес. | C15: =0 -> 0 | D15: =MAX(ROUNDUP(SUMPRODUCT((Модель!$S$5:$S$44<>"Пауза")*Модель!$AK$5:$AK$44)/Модель!$C$48/Модель!$C$66,0),ROUNDUP(SUMPRODUCT((Модель!$S$5:$S$44<>"Пауза")*Модель!$AY$5:$AY$44)/Модель!$C$48/Модель!$C$67,0))*Модель!$C$48 -> 30 | E15: =MAX(ROUNDUP(SUM(Модель!$U$5:$U$44)/Модель!$C$48/Модель!$C$66,0),ROUNDUP(SUM(Модель!$V$5:$V$44)/Модель!$C$48/Модель!$C$67,0))*Модель!$C$48 -> 30 | F15: =0 -> 0
B16: SLA FBS: передано ≤24 ч, % | C16: =0 -> 0 | D16: =1-Модель!$C$50 -> 0.9 | E16: =1-Модель!$C$50 -> 0.9 | F16: =1-Модель!$C$50 -> 0.9 | H16: SM-0020 и SM-0037 формируют отрицательный денежный эффект независимо от схемы исполнения — рекомендуем вывести их из активных продаж до пересмотра цены, спроса или себестоимости.
B18: P&L ПО СЦЕНАРИЯМ
B20: ДОХОДЫ И СЕБЕСТОИМОСТЬ
B21: Статья | C21: FBO | D21: FBS | E21: Гибрид | F21: Гибрид с Fulllog (3PL)
B22: Выручка | C22: =SUMIFS(Модель!$Z$5:$Z$44,Модель!$S$5:$S$44,"<>Пауза") -> 14530290 | D22: =SUMIFS(Модель!$AN$5:$AN$44,Модель!$S$5:$S$44,"<>Пауза") -> 12876790 | E22: =SUM(Модель!$BB$5:$BB$44) -> 13668020 | F22: =E22 -> 13668020
B23: Себестоимость выкупов | C23: =SUMIFS(Модель!$AA$5:$AA$44,Модель!$S$5:$S$44,"<>Пауза") -> 6332650 | D23: =SUMIFS(Модель!$AO$5:$AO$44,Модель!$S$5:$S$44,"<>Пауза") -> 5594240 | E23: =SUM(Модель!$BC$5:$BC$44) -> 5902340 | F23: =E23 -> 5902340
B24: Валовая прибыль | C24: =C22-C23 -> 8197640 | D24: =D22-D23 -> 7282550 | E24: =E22-E23 -> 7765680 | F24: =F22-F23 -> 7765680
B25: ОПЕРАЦИОННЫЕ РАСХОДЫ | J25: Сценарий | K25: Операционная прибыль
B26: Статья | C26: FBO | D26: FBS | E26: Гибрид | F26: Гибрид с Fulllog (3PL) | J26: FBO | K26: =C42 -> 2151647.7
B27: Комиссия Ozon | C27: =SUMIFS(Модель!$AB$5:$AB$44,Модель!$S$5:$S$44,"<>Пауза") -> 2246020.2 | D27: =SUMIFS(Модель!$AP$5:$AP$44,Модель!$S$5:$S$44,"<>Пауза") -> 1865684 | E27: =SUM(Модель!$BD$5:$BD$44) -> 2064528.4 | F27: =E27 -> 2064528.4 | J27: FBS | K27: =D42 -> 2608490.2
B28: Эквайринг | C28: =SUMIFS(Модель!$AC$5:$AC$44,Модель!$S$5:$S$44,"<>Пауза") -> 217954.35 | D28: =SUMIFS(Модель!$AQ$5:$AQ$44,Модель!$S$5:$S$44,"<>Пауза") -> 193151.85 | E28: =SUM(Модель!$BE$5:$BE$44) -> 205020.3 | F28: =E28 -> 205020.3 | J28: Гибрид | K28: =E42 -> 2938795.1
B29: Первая миля до первой внешней точки | C29: =SUMPRODUCT((Модель!$S$5:$S$44<>"Пауза")*Модель!$X$5:$X$44*Модель!$J$5:$J$44)*'Затраты продавца'!$B$12 -> 151335.48 | D29: =D15*'Затраты продавца'!$B$8 -> 75000 | E29: =SUM(Модель!$BI$5:$BI$44)+E15*'Затраты продавца'!$B$8 -> 119332.49 | F29: =SUM(Модель!$BI$5:$BI$44)+SUM(Модель!$V$5:$V$44)*1000*'Fulllog 3PL'!$L$7 -> 138580.02 | J29: Гибрид с Fulllog | K29: =F42 -> 3064646.8
B30: Хранение | C30: =SUMIFS(Модель!$AF$5:$AF$44,Модель!$S$5:$S$44,"<>Пауза") -> 2097850.1 | D30: =SUMIFS(Модель!$AT$5:$AT$44,Модель!$S$5:$S$44,"<>Пауза") -> 674342.55 | E30: =SUM(Модель!$BH$5:$BH$44) -> 1044600.1 | F30: =SUMIFS(Модель!$BH$5:$BH$44,Модель!$S$5:$S$44,"FBO")+'Fulllog 3PL'!$D$12 -> 918219.83
B31: Сборка / подбор | C31: =0 -> 0 | D31: =SUMPRODUCT((Модель!$S$5:$S$44<>"Пауза")*Модель!$AK$5:$AK$44)*'Затраты продавца'!$B$6 -> 380880 | E31: =SUM(Модель!$U$5:$U$44)*'Затраты продавца'!$B$6 -> 70500 | F31: =SUM('Fulllog 3PL'!$D$11,'Fulllog 3PL'!$D$13,'Fulllog 3PL'!$D$15,'Fulllog 3PL'!$D$19) -> 21150
B32: Упаковка | C32: =0 -> 0 | D32: =SUMPRODUCT((Модель!$S$5:$S$44<>"Пауза")*Модель!$AK$5:$AK$44)*'Затраты продавца'!$B$7 -> 63480 | E32: =SUM(Модель!$U$5:$U$44)*'Затраты продавца'!$B$7 -> 11750 | F32: ='Fulllog 3PL'!$D$14 -> 28410
B33: Передача FBS-заказов в Ozon | C33: =0 -> 0 | D33: =SUMIFS(Модель!$AV$5:$AV$44,Модель!$S$5:$S$44,"<>Пауза") -> 63480 | E33: =SUM(Модель!$BK$5:$BK$44) -> 11750 | F33: ='Fulllog 3PL'!$D$16 -> 29375
B34: Прямая логистика Ozon | C34: =SUMIFS(Модель!$AD$5:$AD$44,Модель!$S$5:$S$44,"<>Пауза") -> 962020.39 | D34: =SUMIFS(Модель!$AR$5:$AR$44,Модель!$S$5:$S$44,"<>Пауза") -> 856216.43 | E34: =SUM(Модель!$BF$5:$BF$44) -> 906738.53 | F34: =E34 -> 906738.53
B35: Последняя миля Ozon | C35: =SUMIFS(Модель!$AE$5:$AE$44,Модель!$S$5:$S$44,"<>Пауза") -> 176925 | D35: =SUMIFS(Модель!$AS$5:$AS$44,Модель!$S$5:$S$44,"<>Пауза") -> 158700 | E35: =SUM(Модель!$BG$5:$BG$44) -> 173375 | F35: =E35 -> 173375
B36: Возвратная логистика Ozon | C36: =SUMIFS(Модель!$AH$5:$AH$44,Модель!$S$5:$S$44,"<>Пауза") -> 82202.78 | D36: =SUMIFS(Модель!$AW$5:$AW$44,Модель!$S$5:$S$44,"<>Пауза")-SUMPRODUCT((Модель!$S$5:$S$44<>"Пауза")*Модель!$AL$5:$AL$44)*'Затраты продавца'!$B$9-SUMPRODUCT((Модель!$S$5:$S$44<>"Пауза")*Модель!$AL$5:$AL$44*Модель!$I$5:$I$44)*(1-'Затраты продавца'!$B$10)*Модель!$C$55 -> 76085.74 | E36: =SUM(Модель!$BL$5:$BL$44)-SUMPRODUCT((Модель!$S$5:$S$44="FBS")*Модель!$AL$5:$AL$44)*'Затраты продавца'!$B$9-SUMPRODUCT((Модель!$S$5:$S$44="FBS")*Модель!$AL$5:$AL$44*Модель!$I$5:$I$44)*(1-'Затраты продавца'!$B$10)*Модель!$C$55 -> 80483.08 | F36: =E36 -> 80483.08
B37: Обработка возвратов | C37: =0 -> 0 | D37: =SUMPRODUCT((Модель!$S$5:$S$44<>"Пауза")*Модель!$AL$5:$AL$44)*'Затраты продавца'!$B$9 -> 54700 | E37: =SUMPRODUCT((Модель!$S$5:$S$44="FBS")*Модель!$AL$5:$AL$44)*'Затраты продавца'!$B$9 -> 8700 | F37: ='Fulllog 3PL'!$D$17 -> 5046
B38: Штрафы, списания и прочее | C38: =SUMIFS(Модель!$BN$5:$BN$44,Модель!$S$5:$S$44,"<>Пауза") -> 111684 | D38: =SUMIFS(Модель!$AX$5:$AX$44,Модель!$S$5:$S$44,"<>Пауза")+SUMPRODUCT((Модель!$S$5:$S$44<>"Пауза")*Модель!$AL$5:$AL$44*Модель!$I$5:$I$44)*(1-'Затраты продавца'!$B$10)*Модель!$C$55 -> 212339.25 | E38: =SUM(Модель!$BM$5:$BM$44)+SUMIFS(Модель!$BN$5:$BN$44,Модель!$S$5:$S$44,"FBO")+SUMPRODUCT((Модель!$S$5:$S$44="FBS")*Модель!$AL$5:$AL$44*Модель!$I$5:$I$44)*(1-'Затраты продавца'!$B$10)*Модель!$C$55 -> 130107 | F38: =E38 -> 130107
B39: Итого операционные расходы | C39: =SUM(C27:C38) -> 6045992.3 | D39: =SUM(D27:D38) -> 4674059.8 | E39: =SUM(E27:E38) -> 4826884.9 | F39: =SUM(F27:F38) -> 4701033.2
B40: ФИНАНСОВЫЙ РЕЗУЛЬТАТ
B41: Статья | C41: FBO | D41: FBS | E41: Гибрид | F41: Гибрид с Fulllog (3PL)
B42: Операционная прибыль | C42: =C24-C39 -> 2151647.7 | D42: =D24-D39 -> 2608490.2 | E42: =E24-E39 -> 2938795.1 | F42: =F24-F39 -> 3064646.8
B43: Операционная маржа | C43: =C42/C22 -> 0.14808016 | D43: =D42/D22 -> 0.20257302 | E43: =E42/E22 -> 0.2150125 | F43: =F42/F22 -> 0.22422025
B44: Разница к FBO | C44: =0 -> 0 | D44: =D42-$C$42 -> 456842.47 | E44: =E42-$C$42 -> 787147.43 | F44: =F42-$C$42 -> 912999.13

Sheet Модель
B2: Расчёт экономики по SKU
B4: Источник | C4: Артикул | D4: Товар | E4: Категория | F4: Текущая схема | G4: Выкупы в модели | H4: Цена | I4: Себестоимость | J4: Объём, л | K4: Возвраты | L4: Оборачиваемость, дн. | M4: Комиссия FBO | N4: Комиссия FBS | O4: Прибыль FBO без первой мили | P4: Прибыль FBS без первой мили | Q4: Рекомендация | R4: Ручной выбор | S4: Схема в гибриде | T4: Прибыль выбранной схемы | U4: Отправления FBS | V4: Объём FBS, м³ | X4: FBO: отправления | Y4: FBO: возвраты | Z4: FBO: выручка | AA4: FBO: COGS | AB4: FBO: комиссия | AC4: FBO: эквайринг | AD4: FBO: прямая логистика | AE4: FBO: последняя миля | AF4: FBO: хранение | AG4: FBO: входящая логистика | AH4: FBO: возвратная логистика | AI4: FBS: заказы | AJ4: FBS: отмены | AK4: FBS: отправления | AL4: FBS: возвраты | AM4: FBS: выкупы | AN4: FBS: выручка | AO4: FBS: COGS | AP4: FBS: комиссия | AQ4: FBS: эквайринг | AR4: FBS: прямая логистика | AS4: FBS: последняя миля | AT4: FBS: хранение | AU4: FBS: сборка и упаковка | AV4: FBS: drop-off | AW4: FBS: расходы возвратов | AX4: FBS: штрафы | AY4: FBS: объём, м³ | AZ4: Гибрид: выкупы | BA4: Гибрид: отправления | BB4: Гибрид: выручка | BC4: Гибрид: COGS | BD4: Гибрид: комиссия | BE4: Гибрид: эквайринг | BF4: Гибрид: прямая логистика | BG4: Гибрид: последняя миля | BH4: Гибрид: хранение | BI4: Гибрид: входящая FBO | BJ4: Гибрид: сборка и упаковка | BK4: Гибрид: drop-off | BL4: Гибрид: расходы возвратов | BM4: Гибрид: штрафы | BN4: FBO: списания возвратов | BO4: FBO: нормативный запас, шт. | BP4: FBS: нормативный запас, шт. | BQ4: Гибрид: нормативный запас, шт.
B5: =HYPERLINK("#'SKU'!A2","SKU!2") -> SKU!2 | C5: =SKU!A2 -> SM-0001 | D5: =SKU!B2 -> Кроссовки беговые мужские | E5: =SKU!C2 -> Обувь | F5: =SKU!L2 -> FBO | G5: =SKU!K2*IF(SKU!L2="не представлен",$C$52,1) -> 260 | H5: =SKU!D2 -> 3990 | I5: =SKU!E2 -> 1900 | J5: =SKU!I2 -> 8.316 | K5: =SKU!N2 -> 0.14 | L5: =IF(ISNUMBER(SKU!M2),SKU!M2,$C$53) -> 66.679446 | M5: =VLOOKUP(E5,$B$58:$D$63,2,FALSE()) -> 0.16 | N5: =VLOOKUP(E5,$B$58:$D$63,3,FALSE()) -> 0.15 | O5: =Z5-SUM(AA5:AF5)-AH5-BN5 -> 227204.36 | P5: =AN5-SUM(AO5:AX5) -> 224934.26 | Q5: =IF(MAX(O5,P5)<0,"Пауза",IF(P5>O5,"FBS","FBO")) -> FBO | R5: Авто | S5: =IF(R5="Авто",Q5,R5) -> FBO | T5: =IF(S5="FBO",O5,IF(S5="FBS",P5,0)) -> 227204.36 | U5: =IF(S5="FBS",AK5,0) -> 0 | V5: =IF(S5="FBS",AY5,0) -> 0 | X5: =ROUNDUP(G5/(1-K5),0) -> 303 | Y5: =X5-G5 -> 43 | Z5: =G5*H5 -> 1037400 | AA5: =G5*I5 -> 494000 | AB5: =Z5*M5 -> 165984 | AC5: =Z5*Тарифы!$B$32 -> 15561 | AD5: =X5*(Тарифы!$B$18+MAX(0,J5-5)*Тарифы!$B$19) -> 34287.48 | AE5: =X5*Тарифы!$B$20 -> 7575 | AF5: =BO5*J5*$C$48*IF(E5="Крупногабарит",$C$68,Тарифы!$B$21) -> 75667.284 | AG5: =X5*J5*'Затраты продавца'!$B$12 -> 6299.37 | AH5: =Y5*(Тарифы!$B$18+MAX(0,J5-5)*Тарифы!$B$19)*Тарифы!$B$22 -> 4865.88 | AI5: =ROUNDUP(G5/(1-MIN(0.99,MAX(0,K5+$C$51)))*$C$49,0) -> 303 | AJ5: =ROUNDUP(AI5*$C$50,0) -> 31 | AK5: =AI5-AJ5 -> 272 | AL5: =ROUNDUP(AK5*MIN(0.99,MAX(0,K5+$C$51)),0) -> 39 | AM5: =AK5-AL5 -> 233 | AN5: =AM5*H5 -> 929670 | AO5: =AM5*I5 -> 442700 | AP5: =AN5*N5 -> 139450.5 | AQ5: =AN5*Тарифы!$B$32 -> 13945.05 | AR5: =AK5*(Тарифы!$B$25+MAX(0,J5-5)*Тарифы!$B$26) -> 30779.52 | AS5: =AK5*Тарифы!$B$27 -> 6800 | AT5: =BP5*J5*$C$48*'Затраты продавца'!$B$5 -> 25222.428 | AU5: =AK5*('Затраты продавца'!$B$6+'Затраты продавца'!$B$7) -> 19040 | AV5: =AK5*Тарифы!$B$24 -> 2720 | AW5: =AL5*((Тарифы!$B$25+MAX(0,J5-5)*Тарифы!$B$26)*Тарифы!$B$28+'Затраты продавца'!$B$9+(1-'Затраты продавца'!$B$10)*I5*$C$55) -> 19428.24 | AX5: =AJ5*Тарифы!$B$29 -> 4650 | AY5: =AK5*J5/1000 -> 2.261952 | AZ5: =IF(S5="FBO",G5,IF(S5="FBS",AM5,0)) -> 260 | BA5: =IF(S5="FBO",X5,IF(S5="FBS",AK5,0)) -> 303 | BB5: =IF(S5="FBO",Z5,IF(S5="FBS",AN5,0)) -> 1037400 | BC5: =IF(S5="FBO",AA5,IF(S5="FBS",AO5,0)) -> 494000 | BD5: =IF(S5="FBO",AB5,IF(S5="FBS",AP5,0)) -> 165984 | BE5: =IF(S5="FBO",AC5,IF(S5="FBS",AQ5,0)) -> 15561 | BF5: =IF(S5="FBO",AD5,IF(S5="FBS",AR5,0)) -> 34287.48 | BG5: =IF(S5="FBO",AE5,IF(S5="FBS",AS5,0)) -> 7575 | BH5: =IF(S5="FBO",AF5,IF(S5="FBS",AT5,0)) -> 75667.284 | BI5: =IF(S5="FBO",AG5,0) -> 6299.37 | BJ5: =IF(S5="FBS",AU5,0) -> 0 | BK5: =IF(S5="FBS",AV5,0) -> 0 | BL5: =IF(S5="FBO",AH5,IF(S5="FBS",AW5,0)) -> 4865.88 | BM5: =IF(S5="FBS",AX5,0) -> 0 | BN5: =Y5*I5*(1-'Затраты продавца'!$B$10)*$C$55 -> 12255 | BO5: =ROUNDUP(X5*L5/$C$48,0) -> 674 | BP5: =ROUNDUP(AI5*L5*$C$54/$C$48,0) -> 674 | BQ5: =IF(S5="FBO",BO5,IF(S5="FBS",BP5,0)) -> 674
B6: =HYPERLINK("#'SKU'!A3","SKU!3") -> SKU!3 | C6: =SKU!A3 -> SM-0002 | D6: =SKU!B3 -> Кроссовки трейловые | E6: =SKU!C3 -> Обувь | F6: =SKU!L3 -> FBO | G6: =SKU!K3*IF(SKU!L3="не представлен",$C$52,1) -> 180 | H6: =SKU!D3 -> 5490 | I6: =SKU!E3 -> 2600 | J6: =SKU!I3 -> 9.724 | K6: =SKU!N3 -> 0.15 | L6: =IF(ISNUMBER(SKU!M3),SKU!M3,$C$53) -> 67.064723 | M6: =VLOOKUP(E6,$B$58:$D$63,2,FALSE()) -> 0.16 | N6: =VLOOKUP(E6,$B$58:$D$63,3,FALSE()) -> 0.15 | O6: =Z6-SUM(AA6:AF6)-AH6-BN6 -> 236214.56 | P6: =AN6-SUM(AO6:AX6) -> 233381.3 | Q6: =IF(MAX(O6,P6)<0,"Пауза",IF(P6>O6,"FBS","FBO")) -> FBO | R6: Авто | S6: =IF(R6="Авто",Q6,R6) -> FBO | T6: =IF(S6="FBO",O6,IF(S6="FBS",P6,0)) -> 236214.56 | U6: =IF(S6="FBS",AK6,0) -> 0 | V6: =IF(S6="FBS",AY6,0) -> 0 | X6: =ROUNDUP(G6/(1-K6),0) -> 212 | Y6: =X6-G6 -> 32 | Z6: =G6*H6 -> 988200 | AA6: =G6*I6 -> 468000 | AB6: =Z6*M6 -> 158112 | AC6: =Z6*Тарифы!$B$32 -> 14823 | AD6: =X6*(Тарифы!$B$18+MAX(0,J6-5)*Тарифы!$B$19) -> 26974.88 | AE6: =X6*Тарифы!$B$20 -> 5300 | AF6: =BO6*J6*$C$48*IF(E6="Крупногабарит",$C$68,Тарифы!$B$21) -> 62223.876 | AG6: =X6*J6*'Затраты продавца'!$B$12 -> 5153.72 | AH6: =Y6*(Тарифы!$B$18+MAX(0,J6-5)*Тарифы!$B$19)*Тарифы!$B$22 -> 4071.68 | AI6: =ROUNDUP(G6/(1-MIN(0.99,MAX(0,K6+$C$51)))*$C$49,0) -> 212 | AJ6: =ROUNDUP(AI6*$C$50,0) -> 22 | AK6: =AI6-AJ6 -> 190 | AL6: =ROUNDUP(AK6*MIN(0.99,MAX(0,K6+$C$51)),0) -> 29 | AM6: =AK6-AL6 -> 161 | AN6: =AM6*H6 -> 883890 | AO6: =AM6*I6 -> 418600 | AP6: =AN6*N6 -> 132583.5 | AQ6: =AN6*Тарифы!$B$32 -> 13258.35 | AR6: =AK6*(Тарифы!$B$25+MAX(0,J6-5)*Тарифы!$B$26) -> 24175.6 | AS6: =AK6*Тарифы!$B$27 -> 4750 | AT6: =BP6*J6*$C$48*'Затраты продавца'!$B$5 -> 20741.292 | AU6: =AK6*('Затраты продавца'!$B$6+'Затраты продавца'!$B$7) -> 13300 | AV6: =AK6*Тарифы!$B$24 -> 1900 | AW6: =AL6*((Тарифы!$B$25+MAX(0,J6-5)*Тарифы!$B$26)*Тарифы!$B$28+'Затраты продавца'!$B$9+(1-'Затраты продавца'!$B$10)*I6*$C$55) -> 17899.96 | AX6: =AJ6*Тарифы!$B$29 -> 3300 | AY6: =AK6*J6/1000 -> 1.84756 | AZ6: =IF(S6="FBO",G6,IF(S6="FBS",AM6,0)) -> 180 | BA6: =IF(S6="FBO",X6,IF(S6="FBS",AK6,0)) -> 212 | BB6: =IF(S6="FBO",Z6,IF(S6="FBS",AN6,0)) -> 988200 | BC6: =IF(S6="FBO",AA6,IF(S6="FBS",AO6,0)) -> 468000 | BD6: =IF(S6="FBO",AB6,IF(S6="FBS",AP6,0)) -> 158112 | BE6: =IF(S6="FBO",AC6,IF(S6="FBS",AQ6,0)) -> 14823 | BF6: =IF(S6="FBO",AD6,IF(S6="FBS",AR6,0)) -> 26974.88 | BG6: =IF(S6="FBO",AE6,IF(S6="FBS",AS6,0)) -> 5300 | BH6: =IF(S6="FBO",AF6,IF(S6="FBS",AT6,0)) -> 62223.876 | BI6: =IF(S6="FBO",AG6,0) -> 5153.72 | BJ6: =IF(S6="FBS",AU6,0) -> 0 | BK6: =IF(S6="FBS",AV6,0) -> 0 | BL6: =IF(S6="FBO",AH6,IF(S6="FBS",AW6,0)) -> 4071.68 | BM6: =IF(S6="FBS",AX6,0) -> 0 | BN6: =Y6*I6*(1-'Затраты продавца'!$B$10)*$C$55 -> 12480 | BO6: =ROUNDUP(X6*L6/$C$48,0) -> 474 | BP6: =ROUNDUP(AI6*L6*$C$54/$C$48,0) -> 474 | BQ6: =IF(S6="FBO",BO6,IF(S6="FBS",BP6,0)) -> 474
B7: =HYPERLINK("#'SKU'!A4","SKU!4") -> SKU!4 | C7: =SKU!A4 -> SM-0003 | D7: =SKU!B4 -> Кеды классические | E7: =SKU!C4 -> Обувь | F7: =SKU!L4 -> FBO | G7: =SKU!K4*IF(SKU!L4="не представлен",$C$52,1) -> 340 | H7: =SKU!D4 -> 2490 | I7: =SKU!E4 -> 1050 | J7: =SKU!I4 -> 7.04 | K7: =SKU!N4 -> 0.12 | L7: =IF(ISNUMBER(SKU!M4),SKU!M4,$C$53) -> 48.031221 | M7: =VLOOKUP(E7,$B$58:$D$63,2,FALSE()) -> 0.16 | N7: =VLOOKUP(E7,$B$58:$D$63,3,FALSE()) -> 0.15 | O7: =Z7-SUM(AA7:AF7)-AH7-BN7 -> 221869.1 | P7: =AN7-SUM(AO7:AX7) -> 202917.3 | Q7: =IF(MAX(O7,P7)<0,"Пауза",IF(P7>O7,"FBS","FBO")) -> FBO | R7: Авто | S7: =IF(R7="Авто",Q7,R7) -> FBO | T7: =IF(S7="FBO",O7,IF(S7="FBS",P7,0)) -> 221869.1 | U7: =IF(S7="FBS",AK7,0) -> 0 | V7: =IF(S7="FBS",AY7,0) -> 0 | X7: =ROUNDUP(G7/(1-K7),0) -> 387 | Y7: =X7-G7 -> 47 | Z7: =G7*H7 -> 846600 | AA7: =G7*I7 -> 357000 | AB7: =Z7*M7 -> 135456 | AC7: =Z7*Тарифы!$B$32 -> 12699 | AD7: =X7*(Тарифы!$B$18+MAX(0,J7-5)*Тарифы!$B$19) -> 38854.8 | AE7: =X7*Тарифы!$B$20 -> 9675 | AF7: =BO7*J7*$C$48*IF(E7="Крупногабарит",$C$68,Тарифы!$B$21) -> 58924.8 | AG7: =X7*J7*'Затраты продавца'!$B$12 -> 6811.2 | AH7: =Y7*(Тарифы!$B$18+MAX(0,J7-5)*Тарифы!$B$19)*Тарифы!$B$22 -> 4718.8 | AI7: =ROUNDUP(G7/(1-MIN(0.99,MAX(0,K7+$C$51)))*$C$49,0) -> 387 | AJ7: =ROUNDUP(AI7*$C$50,0) -> 39 | AK7: =AI7-AJ7 -> 348 | AL7: =ROUNDUP(AK7*MIN(0.99,MAX(0,K7+$C$51)),0) -> 42 | AM7: =AK7-AL7 -> 306 | AN7: =AM7*H7 -> 761940 | AO7: =AM7*I7 -> 321300 | AP7: =AN7*N7 -> 114291 | AQ7: =AN7*Тарифы!$B$32 -> 11429.1 | AR7: =AK7*(Тарифы!$B$25+MAX(0,J7-5)*Тарифы!$B$26) -> 34939.2 | AS7: =AK7*Тарифы!$B$27 -> 8700 | AT7: =BP7*J7*$C$48*'Затраты продавца'!$B$5 -> 19641.6 | AU7: =AK7*('Затраты продавца'!$B$6+'Затраты продавца'!$B$7) -> 24360 | AV7: =AK7*Тарифы!$B$24 -> 3480 | AW7: =AL7*((Тарифы!$B$25+MAX(0,J7-5)*Тарифы!$B$26)*Тарифы!$B$28+'Затраты продавца'!$B$9+(1-'Затраты продавца'!$B$10)*I7*$C$55) -> 15031.8 | AX7: =AJ7*Тарифы!$B$29 -> 5850 | AY7: =AK7*J7/1000 -> 2.44992 | AZ7: =IF(S7="FBO",G7,IF(S7="FBS",AM7,0)) -> 340 | BA7: =IF(S7="FBO",X7,IF(S7="FBS",AK7,0)) -> 387 | BB7: =IF(S7="FBO",Z7,IF(S7="FBS",AN7,0)) -> 846600 | BC7: =IF(S7="FBO",AA7,IF(S7="FBS",AO7,0)) -> 357000 | BD7: =IF(S7="FBO",AB7,IF(S7="FBS",AP7,0)) -> 135456 | BE7: =IF(S7="FBO",AC7,IF(S7="FBS",AQ7,0)) -> 12699 | BF7: =IF(S7="FBO",AD7,IF(S7="FBS",AR7,0)) -> 38854.8 | BG7: =IF(S7="FBO",AE7,IF(S7="FBS",AS7,0)) -> 9675 | BH7: =IF(S7="FBO",AF7,IF(S7="FBS",AT7,0)) -> 58924.8 | BI7: =IF(S7="FBO",AG7,0) -> 6811.2 | BJ7: =IF(S7="FBS",AU7,0) -> 0 | BK7: =IF(S7="FBS",AV7,0) -> 0 | BL7: =IF(S7="FBO",AH7,IF(S7="FBS",AW7,0)) -> 4718.8 | BM7: =IF(S7="FBS",AX7,0) -> 0 | BN7: =Y7*I7*(1-'Затраты продавца'!$B$10)*$C$55 -> 7402.5 | BO7: =ROUNDUP(X7*L7/$C$48,0) -> 620 | BP7: =ROUNDUP(AI7*L7*$C$54/$C$48,0) -> 620 | BQ7: =IF(S7="FBO",BO7,IF(S7="FBS",BP7,0)) -> 620
B8: =HYPERLINK("#'SKU'!A5","SKU!5") -> SKU!5 | C8: =SKU!A5 -> SM-0004 | D8: =SKU!B5 -> Ботинки треккинговые | E8: =SKU!C5 -> Обувь | F8: =SKU!L5 -> FBO | G8: =SKU!K5*IF(SKU!L5="не представлен",$C$52,1) -> 85 | H8: =SKU!D5 -> 7990 | I8: =SKU!E5 -> 3800 | J8: =SKU!I5 -> 11.76 | K8: =SKU!N5 -> 0.16 | L8: =IF(ISNUMBER(SKU!M5),SKU!M5,$C$53) -> 73.154068 | M8: =VLOOKUP(E8,$B$58:$D$63,2,FALSE()) -> 0.16 | N8: =VLOOKUP(E8,$B$58:$D$63,3,FALSE()) -> 0.15 | O8: =Z8-SUM(AA8:AF8)-AH8-BN8 -> 167963.11 | P8: =AN8-SUM(AO8:AX8) -> 168167.72 | Q8: =IF(MAX(O8,P8)<0,"Пауза",IF(P8>O8,"FBS","FBO")) -> FBS | R8: Авто | S8: =IF(R8="Авто",Q8,R8) -> FBS | T8: =IF(S8="FBO",O8,IF(S8="FBS",P8,0)) -> 168167.72 | U8: =IF(S8="FBS",AK8,0) -> 91 | V8: =IF(S8="FBS",AY8,0) -> 1.07016 | X8: =ROUNDUP(G8/(1-K8),0) -> 102 | Y8: =X8-G8 -> 17 | Z8: =G8*H8 -> 679150 | AA8: =G8*I8 -> 323000 | AB8: =Z8*M8 -> 108664 | AC8: =Z8*Тарифы!$B$32 -> 10187.25 | AD8: =X8*(Тарифы!$B$18+MAX(0,J8-5)*Тарифы!$B$19) -> 15055.2 | AE8: =X8*Тарифы!$B$20 -> 2550 | AF8: =BO8*J8*$C$48*IF(E8="Крупногабарит",$C$68,Тарифы!$B$21) -> 39531.24 | AG8: =X8*J8*'Затраты продавца'!$B$12 -> 2998.8 | AH8: =Y8*(Тарифы!$B$18+MAX(0,J8-5)*Тарифы!$B$19)*Тарифы!$B$22 -> 2509.2 | AI8: =ROUNDUP(G8/(1-MIN(0.99,MAX(0,K8+$C$51)))*$C$49,0) -> 102 | AJ8: =ROUNDUP(AI8*$C$50,0) -> 11 | AK8: =AI8-AJ8 -> 91 | AL8: =ROUNDUP(AK8*MIN(0.99,MAX(0,K8+$C$51)),0) -> 15 | AM8: =AK8-AL8 -> 76 | AN8: =AM8*H8 -> 607240 | AO8: =AM8*I8 -> 288800 | AP8: =AN8*N8 -> 91086 | AQ8: =AN8*Тарифы!$B$32 -> 9108.6 | AR8: =AK8*(Тарифы!$B$25+MAX(0,J8-5)*Тарифы!$B$26) -> 13431.6 | AS8: =AK8*Тарифы!$B$27 -> 2275 | AT8: =BP8*J8*$C$48*'Затраты продавца'!$B$5 -> 13177.08 | AU8: =AK8*('Затраты продавца'!$B$6+'Затраты продавца'!$B$7) -> 6370 | AV8: =AK8*Тарифы!$B$24 -> 910 | AW8: =AL8*((Тарифы!$B$25+MAX(0,J8-5)*Тарифы!$B$26)*Тарифы!$B$28+'Затраты продавца'!$B$9+(1-'Затраты продавца'!$B$10)*I8*$C$55) -> 12264 | AX8: =AJ8*Тарифы!$B$29 -> 1650 | AY8: =AK8*J8/1000 -> 1.07016 | AZ8: =IF(S8="FBO",G8,IF(S8="FBS",AM8,0)) -> 76 | BA8: =IF(S8="FBO",X8,IF(S8="FBS",AK8,0)) -> 91 | BB8: =IF(S8="FBO",Z8,IF(S8="FBS",AN8,0)) -> 607240 | BC8: =IF(S8="FBO",AA8,IF(S8="FBS",AO8,0)) -> 288800 | BD8: =IF(S8="FBO",AB8,IF(S8="FBS",AP8,0)) -> 91086 | BE8: =IF(S8="FBO",AC8,IF(S8="FBS",AQ8,0)) -> 9108.6 | BF8: =IF(S8="FBO",AD8,IF(S8="FBS",AR8,0)) -> 13431.6 | BG8: =IF(S8="FBO",AE8,IF(S8="FBS",AS8,0)) -> 2275 | BH8: =IF(S8="FBO",AF8,IF(S8="FBS",AT8,0)) -> 13177.08 | BI8: =IF(S8="FBO",AG8,0) -> 0 | BJ8: =IF(S8="FBS",AU8,0) -> 6370 | BK8: =IF(S8="FBS",AV8,0) -> 910 | BL8: =IF(S8="FBO",AH8,IF(S8="FBS",AW8,0)) -> 12264 | BM8: =IF(S8="FBS",AX8,0) -> 1650 | BN8: =Y8*I8*(1-'Затраты продавца'!$B$10)*$C$55 -> 9690 | BO8: =ROUNDUP(X8*L8/$C$48,0) -> 249 | BP8: =ROUNDUP(AI8*L8*$C$54/$C$48,0) -> 249 | BQ8: =IF(S8="FBO",BO8,IF(S8="FBS",BP8,0)) -> 249
B9: =HYPERLINK("#'SKU'!A6","SKU!6") -> SKU!6 | C9: =SKU!A6 -> SM-0005 | D9: =SKU!B6 -> Сланцы пляжные | E9: =SKU!C6 -> Обувь | F9: =SKU!L6 -> FBO | G9: =SKU!K6*IF(SKU!L6="не представлен",$C$52,1) -> 480 | H9: =SKU!D6 -> 890 | I9: =SKU!E6 -> 290 | J9: =SKU!I6 -> 3.36 | K9: =SKU!N6 -> 0.06 | L9: =IF(ISNUMBER(SKU!M6),SKU!M6,$C$53) -> 79.611473 | M9: =VLOOKUP(E9,$B$58:$D$63,2,FALSE()) -> 0.16 | N9: =VLOOKUP(E9,$B$58:$D$63,3,FALSE()) -> 0.15 | O9: =Z9-SUM(AA9:AF9)-AH9-BN9 -> 94202.98 | P9: =AN9-SUM(AO9:AX9) -> 75816.81 | Q9: =IF(MAX(O9,P9)<0,"Пауза",IF(P9>O9,"FBS","FBO")) -> FBO | R9: Авто | S9: =IF(R9="Авто",Q9,R9) -> FBO | T9: =IF(S9="FBO",O9,IF(S9="FBS",P9,0)) -> 94202.98 | U9: =IF(S9="FBS",AK9,0) -> 0 | V9: =IF(S9="FBS",AY9,0) -> 0 | X9: =ROUNDUP(G9/(1-K9),0) -> 511 | Y9: =X9-G9 -> 31 | Z9: =G9*H9 -> 427200 | AA9: =G9*I9 -> 139200 | AB9: =Z9*M9 -> 68352 | AC9: =Z9*Тарифы!$B$32 -> 6408 | AD9: =X9*(Тарифы!$B$18+MAX(0,J9-5)*Тарифы!$B$19) -> 40880 | AE9: =X9*Тарифы!$B$20 -> 12775 | AF9: =BO9*J9*$C$48*IF(E9="Крупногабарит",$C$68,Тарифы!$B$21) -> 61553.52 | AG9: =X9*J9*'Затраты продавца'!$B$12 -> 4292.4 | AH9: =Y9*(Тарифы!$B$18+MAX(0,J9-5)*Тарифы!$B$19)*Тарифы!$B$22 -> 2480 | AI9: =ROUNDUP(G9/(1-MIN(0.99,MAX(0,K9+$C$51)))*$C$49,0) -> 511 | AJ9: =ROUNDUP(AI9*$C$50,0) -> 52 | AK9: =AI9-AJ9 -> 459 | AL9: =ROUNDUP(AK9*MIN(0.99,MAX(0,K9+$C$51)),0) -> 28 | AM9: =AK9-AL9 -> 431 | AN9: =AM9*H9 -> 383590 | AO9: =AM9*I9 -> 124990 | AP9: =AN9*N9 -> 57538.5 | AQ9: =AN9*Тарифы!$B$32 -> 5753.85 | AR9: =AK9*(Тарифы!$B$25+MAX(0,J9-5)*Тарифы!$B$26) -> 36720 | AS9: =AK9*Тарифы!$B$27 -> 11475 | AT9: =BP9*J9*$C$48*'Затраты продавца'!$B$5 -> 20517.84 | AU9: =AK9*('Затраты продавца'!$B$6+'Затраты продавца'!$B$7) -> 32130 | AV9: =AK9*Тарифы!$B$24 -> 4590 | AW9: =AL9*((Тарифы!$B$25+MAX(0,J9-5)*Тарифы!$B$26)*Тарифы!$B$28+'Затраты продавца'!$B$9+(1-'Затраты продавца'!$B$10)*I9*$C$55) -> 6258 | AX9: =AJ9*Тарифы!$B$29 -> 7800 | AY9: =AK9*J9/1000 -> 1.54224 | AZ9: =IF(S9="FBO",G9,IF(S9="FBS",AM9,0)) -> 480 | BA9: =IF(S9="FBO",X9,IF(S9="FBS",AK9,0)) -> 511 | BB9: =IF(S9="FBO",Z9,IF(S9="FBS",AN9,0)) -> 427200 | BC9: =IF(S9="FBO",AA9,IF(S9="FBS",AO9,0)) -> 139200 | BD9: =IF(S9="FBO",AB9,IF(S9="FBS",AP9,0)) -> 68352 | BE9: =IF(S9="FBO",AC9,IF(S9="FBS",AQ9,0)) -> 6408 | BF9: =IF(S9="FBO",AD9,IF(S9="FBS",AR9,0)) -> 40880 | BG9: =IF(S9="FBO",AE9,IF(S9="FBS",AS9,0)) -> 12775 | BH9: =IF(S9="FBO",AF9,IF(S9="FBS",AT9,0)) -> 61553.52 | BI9: =IF(S9="FBO",AG9,0) -> 4292.4 | BJ9: =IF(S9="FBS",AU9,0) -> 0 | BK9: =IF(S9="FBS",AV9,0) -> 0 | BL9: =IF(S9="FBO",AH9,IF(S9="FBS",AW9,0)) -> 2480 | BM9: =IF(S9="FBS",AX9,0) -> 0 | BN9: =Y9*I9*(1-'Затраты продавца'!$B$10)*$C$55 -> 1348.5 | BO9: =ROUNDUP(X9*L9/$C$48,0) -> 1357 | BP9: =ROUNDUP(AI9*L9*$C$54/$C$48,0) -> 1357 | BQ9: =IF(S9="FBO",BO9,IF(S9="FBS",BP9,0)) -> 1357
B10: =HYPERLINK("#'SKU'!A7","SKU!7") -> SKU!7 | C10: =SKU!A7 -> SM-0006 | D10: =SKU!B7 -> Футболка тренировочная | E10: =SKU!C7 -> Одежда | F10: =SKU!L7 -> FBO | G10: =SKU!K7*IF(SKU!L7="не представлен",$C$52,1) -> 620 | H10: =SKU!D7 -> 990 | I10: =SKU!E7 -> 340 | J10: =SKU!I7 -> 1.98 | K10: =SKU!N7 -> 0.15 | L10: =IF(ISNUMBER(SKU!M7),SKU!M7,$C$53) -> 77.881051 | M10: =VLOOKUP(E10,$B$58:$D$63,2,FALSE()) -> 0.17 | N10: =VLOOKUP(E10,$B$58:$D$63,3,FALSE()) -> 0.16 | O10: =Z10-SUM(AA10:AF10)-AH10-BN10 -> 147706.92 | P10: =AN10-SUM(AO10:AX10) -> 93769.14 | Q10: =IF(MAX(O10,P10)<0,"Пауза",IF(P10>O10,"FBS","FBO")) -> FBO | R10: Авто | S10: =IF(R10="Авто",Q10,R10) -> FBO | T10: =IF(S10="FBO",O10,IF(S10="FBS",P10,0)) -> 147706.92 | U10: =IF(S10="FBS",AK10,0) -> 0 | V10: =IF(S10="FBS",AY10,0) -> 0 | X10: =ROUNDUP(G10/(1-K10),0) -> 730 | Y10: =X10-G10 -> 110 | Z10: =G10*H10 -> 613800 | AA10: =G10*I10 -> 210800 | AB10: =Z10*M10 -> 104346 | AC10: =Z10*Тарифы!$B$32 -> 9207 | AD10: =X10*(Тарифы!$B$18+MAX(0,J10-5)*Тарифы!$B$19) -> 58400 | AE10: =X10*Тарифы!$B$20 -> 18250 | AF10: =BO10*J10*$C$48*IF(E10="Крупногабарит",$C$68,Тарифы!$B$21) -> 50680.08 | AG10: =X10*J10*'Затраты продавца'!$B$12 -> 3613.5 | AH10: =Y10*(Тарифы!$B$18+MAX(0,J10-5)*Тарифы!$B$19)*Тарифы!$B$22 -> 8800 | AI10: =ROUNDUP(G10/(1-MIN(0.99,MAX(0,K10+$C$51)))*$C$49,0) -> 730 | AJ10: =ROUNDUP(AI10*$C$50,0) -> 73 | AK10: =AI10-AJ10 -> 657 | AL10: =ROUNDUP(AK10*MIN(0.99,MAX(0,K10+$C$51)),0) -> 99 | AM10: =AK10-AL10 -> 558 | AN10: =AM10*H10 -> 552420 | AO10: =AM10*I10 -> 189720 | AP10: =AN10*N10 -> 88387.2 | AQ10: =AN10*Тарифы!$B$32 -> 8286.3 | AR10: =AK10*(Тарифы!$B$25+MAX(0,J10-5)*Тарифы!$B$26) -> 52560 | AS10: =AK10*Тарифы!$B$27 -> 16425 | AT10: =BP10*J10*$C$48*'Затраты продавца'!$B$5 -> 16893.36 | AU10: =AK10*('Затраты продавца'!$B$6+'Затраты продавца'!$B$7) -> 45990 | AV10: =AK10*Тарифы!$B$24 -> 6570 | AW10: =AL10*((Тарифы!$B$25+MAX(0,J10-5)*Тарифы!$B$26)*Тарифы!$B$28+'Затраты продавца'!$B$9+(1-'Затраты продавца'!$B$10)*I10*$C$55) -> 22869 | AX10: =AJ10*Тарифы!$B$29 -> 10950 | AY10: =AK10*J10/1000 -> 1.30086 | AZ10: =IF(S10="FBO",G10,IF(S10="FBS",AM10,0)) -> 620 | BA10: =IF(S10="FBO",X10,IF(S10="FBS",AK10,0)) -> 730 | BB10: =IF(S10="FBO",Z10,IF(S10="FBS",AN10,0)) -> 613800 | BC10: =IF(S10="FBO",AA10,IF(S10="FBS",AO10,0)) -> 210800 | BD10: =IF(S10="FBO",AB10,IF(S10="FBS",AP10,0)) -> 104346 | BE10: =IF(S10="FBO",AC10,IF(S10="FBS",AQ10,0)) -> 9207 | BF10: =IF(S10="FBO",AD10,IF(S10="FBS",AR10,0)) -> 58400 | BG10: =IF(S10="FBO",AE10,IF(S10="FBS",AS10,0)) -> 18250 | BH10: =IF(S10="FBO",AF10,IF(S10="FBS",AT10,0)) -> 50680.08 | BI10: =IF(S10="FBO",AG10,0) -> 3613.5 | BJ10: =IF(S10="FBS",AU10,0) -> 0 | BK10: =IF(S10="FBS",AV10,0) -> 0 | BL10: =IF(S10="FBO",AH10,IF(S10="FBS",AW10,0)) -> 8800 | BM10: =IF(S10="FBS",AX10,0) -> 0 | BN10: =Y10*I10*(1-'Затраты продавца'!$B$10)*$C$55 -> 5610 | BO10: =ROUNDUP(X10*L10/$C$48,0) -> 1896 | BP10: =ROUNDUP(AI10*L10*$C$54/$C$48,0) -> 1896 | BQ10: =IF(S10="FBO",BO10,IF(S10="FBS",BP10,0)) -> 1896
B11: =HYPERLINK("#'SKU'!A8","SKU!8") -> SKU!8 | C11: =SKU!A8 -> SM-0007 | D11: =SKU!B8 -> Шорты беговые | E11: =SKU!C8 -> Одежда | F11: =SKU!L8 -> FBO | G11: =SKU!K8*IF(SKU!L8="не представлен",$C$52,1) -> 380 | H11: =SKU!D8 -> 1290 | I11: =SKU!E8 -> 430 | J11: =SKU!I8 -> 2.24 | K11: =SKU!N8 -> 0.14 | L11: =IF(ISNUMBER(SKU!M8),SKU!M8,$C$53) -> 82.191663 | M11: =VLOOKUP(E11,$B$58:$D$63,2,FALSE()) -> 0.17 | N11: =VLOOKUP(E11,$B$58:$D$63,3,FALSE()) -> 0.16 | O11: =Z11-SUM(AA11:AF11)-AH11-BN11 -> 144123.36 | P11: =AN11-SUM(AO11:AX11) -> 110185.37 | Q11: =IF(MAX(O11,P11)<0,"Пауза",IF(P11>O11,"FBS","FBO")) -> FBO | R11: Авто | S11: =IF(R11="Авто",Q11,R11) -> FBO | T11: =IF(S11="FBO",O11,IF(S11="FBS",P11,0)) -> 144123.36 | U11: =IF(S11="FBS",AK11,0) -> 0 | V11: =IF(S11="FBS",AY11,0) -> 0 | X11: =ROUNDUP(G11/(1-K11),0) -> 442 | Y11: =X11-G11 -> 62 | Z11: =G11*H11 -> 490200 | AA11: =G11*I11 -> 163400 | AB11: =Z11*M11 -> 83334 | AC11: =Z11*Тарифы!$B$32 -> 7353 | AD11: =X11*(Тарифы!$B$18+MAX(0,J11-5)*Тарифы!$B$19) -> 35360 | AE11: =X11*Тарифы!$B$20 -> 11050 | AF11: =BO11*J11*$C$48*IF(E11="Крупногабарит",$C$68,Тарифы!$B$21) -> 36620.64 | AG11: =X11*J11*'Затраты продавца'!$B$12 -> 2475.2 | AH11: =Y11*(Тарифы!$B$18+MAX(0,J11-5)*Тарифы!$B$19)*Тарифы!$B$22 -> 4960 | AI11: =ROUNDUP(G11/(1-MIN(0.99,MAX(0,K11+$C$51)))*$C$49,0) -> 442 | AJ11: =ROUNDUP(AI11*$C$50,0) -> 45 | AK11: =AI11-AJ11 -> 397 | AL11: =ROUNDUP(AK11*MIN(0.99,MAX(0,K11+$C$51)),0) -> 56 | AM11: =AK11-AL11 -> 341 | AN11: =AM11*H11 -> 439890 | AO11: =AM11*I11 -> 146630 | AP11: =AN11*N11 -> 70382.4 | AQ11: =AN11*Тарифы!$B$32 -> 6598.35 | AR11: =AK11*(Тарифы!$B$25+MAX(0,J11-5)*Тарифы!$B$26) -> 31760 | AS11: =AK11*Тарифы!$B$27 -> 9925 | AT11: =BP11*J11*$C$48*'Затраты продавца'!$B$5 -> 12206.88 | AU11: =AK11*('Затраты продавца'!$B$6+'Затраты продавца'!$B$7) -> 27790 | AV11: =AK11*Тарифы!$B$24 -> 3970 | AW11: =AL11*((Тарифы!$B$25+MAX(0,J11-5)*Тарифы!$B$26)*Тарифы!$B$28+'Затраты продавца'!$B$9+(1-'Затраты продавца'!$B$10)*I11*$C$55) -> 13692 | AX11: =AJ11*Тарифы!$B$29 -> 6750 | AY11: =AK11*J11/1000 -> 0.88928 | AZ11: =IF(S11="FBO",G11,IF(S11="FBS",AM11,0)) -> 380 | BA11: =IF(S11="FBO",X11,IF(S11="FBS",AK11,0)) -> 442 | BB11: =IF(S11="FBO",Z11,IF(S11="FBS",AN11,0)) -> 490200 | BC11: =IF(S11="FBO",AA11,IF(S11="FBS",AO11,0)) -> 163400 | BD11: =IF(S11="FBO",AB11,IF(S11="FBS",AP11,0)) -> 83334 | BE11: =IF(S11="FBO",AC11,IF(S11="FBS",AQ11,0)) -> 7353 | BF11: =IF(S11="FBO",AD11,IF(S11="FBS",AR11,0)) -> 35360 | BG11: =IF(S11="FBO",AE11,IF(S11="FBS",AS11,0)) -> 11050 | BH11: =IF(S11="FBO",AF11,IF(S11="FBS",AT11,0)) -> 36620.64 | BI11: =IF(S11="FBO",AG11,0) -> 2475.2 | BJ11: =IF(S11="FBS",AU11,0) -> 0 | BK11: =IF(S11="FBS",AV11,0) -> 0 | BL11: =IF(S11="FBO",AH11,IF(S11="FBS",AW11,0)) -> 4960 | BM11: =IF(S11="FBS",AX11,0) -> 0 | BN11: =Y11*I11*(1-'Затраты продавца'!$B$10)*$C$55 -> 3999 | BO11: =ROUNDUP(X11*L11/$C$48,0) -> 1211 | BP11: =ROUNDUP(AI11*L11*$C$54/$C$48,0) -> 1211 | BQ11: =IF(S11="FBO",BO11,IF(S11="FBS",BP11,0)) -> 1211
B12: =HYPERLINK("#'SKU'!A9","SKU!9") -> SKU!9 | C12: =SKU!A9 -> SM-0008 | D12: =SKU!B9 -> Ветровка для бега | E12: =SKU!C9 -> Одежда | F12: =SKU!L9 -> FBO | G12: =SKU!K9*IF(SKU!L9="не представлен",$C$52,1) -> 150 | H12: =SKU!D9 -> 3490 | I12: =SKU!E9 -> 1400 | J12: =SKU!I9 -> 5.25 | K12: =SKU!N9 -> 0.17 | L12: =IF(ISNUMBER(SKU!M9),SKU!M9,$C$53) -> 79.712035 | M12: =VLOOKUP(E12,$B$58:$D$63,2,FALSE()) -> 0.17 | N12: =VLOOKUP(E12,$B$58:$D$63,3,FALSE()) -> 0.16 | O12: =Z12-SUM(AA12:AF12)-AH12-BN12 -> 154036.62 | P12: =AN12-SUM(AO12:AX12) -> 142640.88 | Q12: =IF(MAX(O12,P12)<0,"Пауза",IF(P12>O12,"FBS","FBO")) -> FBO | R12: Авто | S12: =IF(R12="Авто",Q12,R12) -> FBO | T12: =IF(S12="FBO",O12,IF(S12="FBS",P12,0)) -> 154036.62 | U12: =IF(S12="FBS",AK12,0) -> 0 | V12: =IF(S12="FBS",AY12,0) -> 0 | X12: =ROUNDUP(G12/(1-K12),0) -> 181 | Y12: =X12-G12 -> 31 | Z12: =G12*H12 -> 523500 | AA12: =G12*I12 -> 210000 | AB12: =Z12*M12 -> 88995 | AC12: =Z12*Тарифы!$B$32 -> 7852.5 | AD12: =X12*(Тарифы!$B$18+MAX(0,J12-5)*Тарифы!$B$19) -> 14932.5 | AE12: =X12*Тарифы!$B$20 -> 4525 | AF12: =BO12*J12*$C$48*IF(E12="Крупногабарит",$C$68,Тарифы!$B$21) -> 34090.875 | AG12: =X12*J12*'Затраты продавца'!$B$12 -> 2375.625 | AH12: =Y12*(Тарифы!$B$18+MAX(0,J12-5)*Тарифы!$B$19)*Тарифы!$B$22 -> 2557.5 | AI12: =ROUNDUP(G12/(1-MIN(0.99,MAX(0,K12+$C$51)))*$C$49,0) -> 181 | AJ12: =ROUNDUP(AI12*$C$50,0) -> 19 | AK12: =AI12-AJ12 -> 162 | AL12: =ROUNDUP(AK12*MIN(0.99,MAX(0,K12+$C$51)),0) -> 28 | AM12: =AK12-AL12 -> 134 | AN12: =AM12*H12 -> 467660 | AO12: =AM12*I12 -> 187600 | AP12: =AN12*N12 -> 74825.6 | AQ12: =AN12*Тарифы!$B$32 -> 7014.9 | AR12: =AK12*(Тарифы!$B$25+MAX(0,J12-5)*Тарифы!$B$26) -> 13365 | AS12: =AK12*Тарифы!$B$27 -> 4050 | AT12: =BP12*J12*$C$48*'Затраты продавца'!$B$5 -> 11363.625 | AU12: =AK12*('Затраты продавца'!$B$6+'Затраты продавца'!$B$7) -> 11340 | AV12: =AK12*Тарифы!$B$24 -> 1620 | AW12: =AL12*((Тарифы!$B$25+MAX(0,J12-5)*Тарифы!$B$26)*Тарифы!$B$28+'Затраты продавца'!$B$9+(1-'Затраты продавца'!$B$10)*I12*$C$55) -> 10990 | AX12: =AJ12*Тарифы!$B$29 -> 2850 | AY12: =AK12*J12/1000 -> 0.8505 | AZ12: =IF(S12="FBO",G12,IF(S12="FBS",AM12,0)) -> 150 | BA12: =IF(S12="FBO",X12,IF(S12="FBS",AK12,0)) -> 181 | BB12: =IF(S12="FBO",Z12,IF(S12="FBS",AN12,0)) -> 523500 | BC12: =IF(S12="FBO",AA12,IF(S12="FBS",AO12,0)) -> 210000 | BD12: =IF(S12="FBO",AB12,IF(S12="FBS",AP12,0)) -> 88995 | BE12: =IF(S12="FBO",AC12,IF(S12="FBS",AQ12,0)) -> 7852.5 | BF12: =IF(S12="FBO",AD12,IF(S12="FBS",AR12,0)) -> 14932.5 | BG12: =IF(S12="FBO",AE12,IF(S12="FBS",AS12,0)) -> 4525 | BH12: =IF(S12="FBO",AF12,IF(S12="FBS",AT12,0)) -> 34090.875 | BI12: =IF(S12="FBO",AG12,0) -> 2375.625 | BJ12: =IF(S12="FBS",AU12,0) -> 0 | BK12: =IF(S12="FBS",AV12,0) -> 0 | BL12: =IF(S12="FBO",AH12,IF(S12="FBS",AW12,0)) -> 2557.5 | BM12: =IF(S12="FBS",AX12,0) -> 0 | BN12: =Y12*I12*(1-'Затраты продавца'!$B$10)*$C$55 -> 6510 | BO12: =ROUNDUP(X12*L12/$C$48,0) -> 481 | BP12: =ROUNDUP(AI12*L12*$C$54/$C$48,0) -> 481 | BQ12: =IF(S12="FBO",BO12,IF(S12="FBS",BP12,0)) -> 481
B13: =HYPERLINK("#'SKU'!A10","SKU!10") -> SKU!10 | C13: =SKU!A10 -> SM-0009 | D13: =SKU!B10 -> Куртка зимняя утеплённая | E13: =SKU!C10 -> Одежда | F13: =SKU!L10 -> FBO | G13: =SKU!K10*IF(SKU!L10="не представлен",$C$52,1) -> 18 | H13: =SKU!D10 -> 8990 | I13: =SKU!E10 -> 4100 | J13: =SKU!I10 -> 23.625 | K13: =SKU!N10 -> 0.2 | L13: =IF(ISNUMBER(SKU!M10),SKU!M10,$C$53) -> 140 | M13: =VLOOKUP(E13,$B$58:$D$63,2,FALSE()) -> 0.17 | N13: =VLOOKUP(E13,$B$58:$D$63,3,FALSE()) -> 0.16 | O13: =Z13-SUM(AA13:AF13)-AH13-BN13 -> 12533.05 | P13: =AN13-SUM(AO13:AX13) -> 29786.25 | Q13: =IF(MAX(O13,P13)<0,"Пауза",IF(P13>O13,"FBS","FBO")) -> FBS | R13: Авто | S13: =IF(R13="Авто",Q13,R13) -> FBS | T13: =IF(S13="FBO",O13,IF(S13="FBS",P13,0)) -> 29786.25 | U13: =IF(S13="FBS",AK13,0) -> 20 | V13: =IF(S13="FBS",AY13,0) -> 0.4725 | X13: =ROUNDUP(G13/(1-K13),0) -> 23 | Y13: =X13-G13 -> 5 | Z13: =G13*H13 -> 161820 | AA13: =G13*I13 -> 73800 | AB13: =Z13*M13 -> 27509.4 | AC13: =Z13*Тарифы!$B$32 -> 2427.3 | AD13: =X13*(Тарифы!$B$18+MAX(0,J13-5)*Тарифы!$B$19) -> 6123.75 | AE13: =X13*Тарифы!$B$20 -> 575 | AF13: =BO13*J13*$C$48*IF(E13="Крупногабарит",$C$68,Тарифы!$B$21) -> 34445.25 | AG13: =X13*J13*'Затраты продавца'!$B$12 -> 1358.4375 | AH13: =Y13*(Тарифы!$B$18+MAX(0,J13-5)*Тарифы!$B$19)*Тарифы!$B$22 -> 1331.25 | AI13: =ROUNDUP(G13/(1-MIN(0.99,MAX(0,K13+$C$51)))*$C$49,0) -> 23 | AJ13: =ROUNDUP(AI13*$C$50,0) -> 3 | AK13: =AI13-AJ13 -> 20 | AL13: =ROUNDUP(AK13*MIN(0.99,MAX(0,K13+$C$51)),0) -> 4 | AM13: =AK13-AL13 -> 16 | AN13: =AM13*H13 -> 143840 | AO13: =AM13*I13 -> 65600 | AP13: =AN13*N13 -> 23014.4 | AQ13: =AN13*Тарифы!$B$32 -> 2157.6 | AR13: =AK13*(Тарифы!$B$25+MAX(0,J13-5)*Тарифы!$B$26) -> 5325 | AS13: =AK13*Тарифы!$B$27 -> 500 | AT13: =BP13*J13*$C$48*'Затраты продавца'!$B$5 -> 11481.75 | AU13: =AK13*('Затраты продавца'!$B$6+'Затраты продавца'!$B$7) -> 1400 | AV13: =AK13*Тарифы!$B$24 -> 200 | AW13: =AL13*((Тарифы!$B$25+MAX(0,J13-5)*Тарифы!$B$26)*Тарифы!$B$28+'Затраты продавца'!$B$9+(1-'Затраты продавца'!$B$10)*I13*$C$55) -> 3925 | AX13: =AJ13*Тарифы!$B$29 -> 450 | AY13: =AK13*J13/1000 -> 0.4725 | AZ13: =IF(S13="FBO",G13,IF(S13="FBS",AM13,0)) -> 16 | BA13: =IF(S13="FBO",X13,IF(S13="FBS",AK13,0)) -> 20 | BB13: =IF(S13="FBO",Z13,IF(S13="FBS",AN13,0)) -> 143840 | BC13: =IF(S13="FBO",AA13,IF(S13="FBS",AO13,0)) -> 65600 | BD13: =IF(S13="FBO",AB13,IF(S13="FBS",AP13,0)) -> 23014.4 | BE13: =IF(S13="FBO",AC13,IF(S13="FBS",AQ13,0)) -> 2157.6 | BF13: =IF(S13="FBO",AD13,IF(S13="FBS",AR13,0)) -> 5325 | BG13: =IF(S13="FBO",AE13,IF(S13="FBS",AS13,0)) -> 500 | BH13: =IF(S13="FBO",AF13,IF(S13="FBS",AT13,0)) -> 11481.75 | BI13: =IF(S13="FBO",AG13,0) -> 0 | BJ13: =IF(S13="FBS",AU13,0) -> 1400 | BK13: =IF(S13="FBS",AV13,0) -> 200 | BL13: =IF(S13="FBO",AH13,IF(S13="FBS",AW13,0)) -> 3925 | BM13: =IF(S13="FBS",AX13,0) -> 450 | BN13: =Y13*I13*(1-'Затраты продавца'!$B$10)*$C$55 -> 3075 | BO13: =ROUNDUP(X13*L13/$C$48,0) -> 108 | BP13: =ROUNDUP(AI13*L13*$C$54/$C$48,0) -> 108 | BQ13: =IF(S13="FBO",BO13,IF(S13="FBS",BP13,0)) -> 108
B14: =HYPERLINK("#'SKU'!A11","SKU!11") -> SKU!11 | C14: =SKU!A11 -> SM-0010 | D14: =SKU!B11 -> Леггинсы женские | E14: =SKU!C11 -> Одежда | F14: =SKU!L11 -> FBO | G14: =SKU!K11*IF(SKU!L11="не представлен",$C$52,1) -> 290 | H14: =SKU!D11 -> 1790 | I14: =SKU!E11 -> 620 | J14: =SKU!I11 -> 2.24 | K14: =SKU!N11 -> 0.18 | L14: =IF(ISNUMBER(SKU!M11),SKU!M11,$C$53) -> 77.397201 | M14: =VLOOKUP(E14,$B$58:$D$63,2,FALSE()) -> 0.17 | N14: =VLOOKUP(E14,$B$58:$D$63,3,FALSE()) -> 0.16 | O14: =Z14-SUM(AA14:AF14)-AH14-BN14 -> 167385.14 | P14: =AN14-SUM(AO14:AX14) -> 133477.88 | Q14: =IF(MAX(O14,P14)<0,"Пауза",IF(P14>O14,"FBS","FBO")) -> FBO | R14: Авто | S14: =IF(R14="Авто",Q14,R14) -> FBO | T14: =IF(S14="FBO",O14,IF(S14="FBS",P14,0)) -> 167385.14 | U14: =IF(S14="FBS",AK14,0) -> 0 | V14: =IF(S14="FBS",AY14,0) -> 0 | X14: =ROUNDUP(G14/(1-K14),0) -> 354 | Y14: =X14-G14 -> 64 | Z14: =G14*H14 -> 519100 | AA14: =G14*I14 -> 179800 | AB14: =Z14*M14 -> 88247 | AC14: =Z14*Тарифы!$B$32 -> 7786.5 | AD14: =X14*(Тарифы!$B$18+MAX(0,J14-5)*Тарифы!$B$19) -> 28320 | AE14: =X14*Тарифы!$B$20 -> 8850 | AF14: =BO14*J14*$C$48*IF(E14="Крупногабарит",$C$68,Тарифы!$B$21) -> 27639.36 | AG14: =X14*J14*'Затраты продавца'!$B$12 -> 1982.4 | AH14: =Y14*(Тарифы!$B$18+MAX(0,J14-5)*Тарифы!$B$19)*Тарифы!$B$22 -> 5120 | AI14: =ROUNDUP(G14/(1-MIN(0.99,MAX(0,K14+$C$51)))*$C$49,0) -> 354 | AJ14: =ROUNDUP(AI14*$C$50,0) -> 36 | AK14: =AI14-AJ14 -> 318 | AL14: =ROUNDUP(AK14*MIN(0.99,MAX(0,K14+$C$51)),0) -> 58 | AM14: =AK14-AL14 -> 260 | AN14: =AM14*H14 -> 465400 | AO14: =AM14*I14 -> 161200 | AP14: =AN14*N14 -> 74464 | AQ14: =AN14*Тарифы!$B$32 -> 6981 | AR14: =AK14*(Тарифы!$B$25+MAX(0,J14-5)*Тарифы!$B$26) -> 25440 | AS14: =AK14*Тарифы!$B$27 -> 7950 | AT14: =BP14*J14*$C$48*'Затраты продавца'!$B$5 -> 9213.12 | AU14: =AK14*('Затраты продавца'!$B$6+'Затраты продавца'!$B$7) -> 22260 | AV14: =AK14*Тарифы!$B$24 -> 3180 | AW14: =AL14*((Тарифы!$B$25+MAX(0,J14-5)*Тарифы!$B$26)*Тарифы!$B$28+'Затраты продавца'!$B$9+(1-'Затраты продавца'!$B$10)*I14*$C$55) -> 15834 | AX14: =AJ14*Тарифы!$B$29 -> 5400 | AY14: =AK14*J14/1000 -> 0.71232 | AZ14: =IF(S14="FBO",G14,IF(S14="FBS",AM14,0)) -> 290 | BA14: =IF(S14="FBO",X14,IF(S14="FBS",AK14,0)) -> 354 | BB14: =IF(S14="FBO",Z14,IF(S14="FBS",AN14,0)) -> 519100 | BC14: =IF(S14="FBO",AA14,IF(S14="FBS",AO14,0)) -> 179800 | BD14: =IF(S14="FBO",AB14,IF(S14="FBS",AP14,0)) -> 88247 | BE14: =IF(S14="FBO",AC14,IF(S14="FBS",AQ14,0)) -> 7786.5 | BF14: =IF(S14="FBO",AD14,IF(S14="FBS",AR14,0)) -> 28320 | BG14: =IF(S14="FBO",AE14,IF(S14="FBS",AS14,0)) -> 8850 | BH14: =IF(S14="FBO",AF14,IF(S14="FBS",AT14,0)) -> 27639.36 | BI14: =IF(S14="FBO",AG14,0) -> 1982.4 | BJ14: =IF(S14="FBS",AU14,0) -> 0 | BK14: =IF(S14="FBS",AV14,0) -> 0 | BL14: =IF(S14="FBO",AH14,IF(S14="FBS",AW14,0)) -> 5120 | BM14: =IF(S14="FBS",AX14,0) -> 0 | BN14: =Y14*I14*(1-'Затраты продавца'!$B$10)*$C$55 -> 5952 | BO14: =ROUNDUP(X14*L14/$C$48,0) -> 914 | BP14: =ROUNDUP(AI14*L14*$C$54/$C$48,0) -> 914 | BQ14: =IF(S14="FBO",BO14,IF(S14="FBS",BP14,0)) -> 914
B15: =HYPERLINK("#'SKU'!A12","SKU!12") -> SKU!12 | C15: =SKU!A12 -> SM-0011 | D15: =SKU!B12 -> Гантели разборные 2×10 кг | E15: =SKU!C12 -> Фитнес | F15: =SKU!L12 -> FBO | G15: =SKU!K12*IF(SKU!L12="не представлен",$C$52,1) -> 60 | H15: =SKU!D12 -> 4990 | I15: =SKU!E12 -> 2750 | J15: =SKU!I12 -> 16.875 | K15: =SKU!N12 -> 0.03 | L15: =IF(ISNUMBER(SKU!M12),SKU!M12,$C$53) -> 81.658982 | M15: =VLOOKUP(E15,$B$58:$D$63,2,FALSE()) -> 0.15 | N15: =VLOOKUP(E15,$B$58:$D$63,3,FALSE()) -> 0.14 | O15: =Z15-SUM(AA15:AF15)-AH15-BN15 -> 31403.688 | P15: =AN15-SUM(AO15:AX15) -> 45714.963 | Q15: =IF(MAX(O15,P15)<0,"Пауза",IF(P15>O15,"FBS","FBO")) -> FBS | R15: Авто | S15: =IF(R15="Авто",Q15,R15) -> FBS | T15: =IF(S15="FBO",O15,IF(S15="FBS",P15,0)) -> 45714.963 | U15: =IF(S15="FBS",AK15,0) -> 55 | V15: =IF(S15="FBS",AY15,0) -> 0.928125 | X15: =ROUNDUP(G15/(1-K15),0) -> 62 | Y15: =X15-G15 -> 2 | Z15: =G15*H15 -> 299400 | AA15: =G15*I15 -> 165000 | AB15: =Z15*M15 -> 44910 | AC15: =Z15*Тарифы!$B$32 -> 4491 | AD15: =X15*(Тарифы!$B$18+MAX(0,J15-5)*Тарифы!$B$19) -> 12322.5 | AE15: =X15*Тарифы!$B$20 -> 1550 | AF15: =BO15*J15*$C$48*IF(E15="Крупногабарит",$C$68,Тарифы!$B$21) -> 38500.312 | AG15: =X15*J15*'Затраты продавца'!$B$12 -> 2615.625 | AH15: =Y15*(Тарифы!$B$18+MAX(0,J15-5)*Тарифы!$B$19)*Тарифы!$B$22 -> 397.5 | AI15: =ROUNDUP(G15/(1-MIN(0.99,MAX(0,K15+$C$51)))*$C$49,0) -> 62 | AJ15: =ROUNDUP(AI15*$C$50,0) -> 7 | AK15: =AI15-AJ15 -> 55 | AL15: =ROUNDUP(AK15*MIN(0.99,MAX(0,K15+$C$51)),0) -> 2 | AM15: =AK15-AL15 -> 53 | AN15: =AM15*H15 -> 264470 | AO15: =AM15*I15 -> 145750 | AP15: =AN15*N15 -> 37025.8 | AQ15: =AN15*Тарифы!$B$32 -> 3967.05 | AR15: =AK15*(Тарифы!$B$25+MAX(0,J15-5)*Тарифы!$B$26) -> 10931.25 | AS15: =AK15*Тарифы!$B$27 -> 1375 | AT15: =BP15*J15*$C$48*'Затраты продавца'!$B$5 -> 12833.438 | AU15: =AK15*('Затраты продавца'!$B$6+'Затраты продавца'!$B$7) -> 3850 | AV15: =AK15*Тарифы!$B$24 -> 550 | AW15: =AL15*((Тарифы!$B$25+MAX(0,J15-5)*Тарифы!$B$26)*Тарифы!$B$28+'Затраты продавца'!$B$9+(1-'Затраты продавца'!$B$10)*I15*$C$55) -> 1422.5 | AX15: =AJ15*Тарифы!$B$29 -> 1050 | AY15: =AK15*J15/1000 -> 0.928125 | AZ15: =IF(S15="FBO",G15,IF(S15="FBS",AM15,0)) -> 53 | BA15: =IF(S15="FBO",X15,IF(S15="FBS",AK15,0)) -> 55 | BB15: =IF(S15="FBO",Z15,IF(S15="FBS",AN15,0)) -> 264470 | BC15: =IF(S15="FBO",AA15,IF(S15="FBS",AO15,0)) -> 145750 | BD15: =IF(S15="FBO",AB15,IF(S15="FBS",AP15,0)) -> 37025.8 | BE15: =IF(S15="FBO",AC15,IF(S15="FBS",AQ15,0)) -> 3967.05 | BF15: =IF(S15="FBO",AD15,IF(S15="FBS",AR15,0)) -> 10931.25 | BG15: =IF(S15="FBO",AE15,IF(S15="FBS",AS15,0)) -> 1375 | BH15: =IF(S15="FBO",AF15,IF(S15="FBS",AT15,0)) -> 12833.438 | BI15: =IF(S15="FBO",AG15,0) -> 0 | BJ15: =IF(S15="FBS",AU15,0) -> 3850 | BK15: =IF(S15="FBS",AV15,0) -> 550 | BL15: =IF(S15="FBO",AH15,IF(S15="FBS",AW15,0)) -> 1422.5 | BM15: =IF(S15="FBS",AX15,0) -> 1050 | BN15: =Y15*I15*(1-'Затраты продавца'!$B$10)*$C$55 -> 825 | BO15: =ROUNDUP(X15*L15/$C$48,0) -> 169 | BP15: =ROUNDUP(AI15*L15*$C$54/$C$48,0) -> 169 | BQ15: =IF(S15="FBO",BO15,IF(S15="FBS",BP15,0)) -> 169
B16: =HYPERLINK("#'SKU'!A13","SKU!13") -> SKU!13 | C16: =SKU!A13 -> SM-0012 | D16: =SKU!B13 -> Гиря чугунная 16 кг | E16: =SKU!C13 -> Фитнес | F16: =SKU!L13 -> FBO | G16: =SKU!K13*IF(SKU!L13="не представлен",$C$52,1) -> 45 | H16: =SKU!D13 -> 2990 | I16: =SKU!E13 -> 1750 | J16: =SKU!I13 -> 11 | K16: =SKU!N13 -> 0.02 | L16: =IF(ISNUMBER(SKU!M13),SKU!M13,$C$53) -> 60.716212 | M16: =VLOOKUP(E16,$B$58:$D$63,2,FALSE()) -> 0.15 | N16: =VLOOKUP(E16,$B$58:$D$63,3,FALSE()) -> 0.14 | O16: =Z16-SUM(AA16:AF16)-AH16-BN16 -> 11647.75 | P16: =AN16-SUM(AO16:AX16) -> 15111.5 | Q16: =IF(MAX(O16,P16)<0,"Пауза",IF(P16>O16,"FBS","FBO")) -> FBS | R16: Авто | S16: =IF(R16="Авто",Q16,R16) -> FBS | T16: =IF(S16="FBO",O16,IF(S16="FBS",P16,0)) -> 15111.5 | U16: =IF(S16="FBS",AK16,0) -> 41 | V16: =IF(S16="FBS",AY16,0) -> 0.451 | X16: =ROUNDUP(G16/(1-K16),0) -> 46 | Y16: =X16-G16 -> 1 | Z16: =G16*H16 -> 134550 | AA16: =G16*I16 -> 78750 | AB16: =Z16*M16 -> 20182.5 | AC16: =Z16*Тарифы!$B$32 -> 2018.25 | AD16: =X16*(Тарифы!$B$18+MAX(0,J16-5)*Тарифы!$B$19) -> 6440 | AE16: =X16*Тарифы!$B$20 -> 1150 | AF16: =BO16*J16*$C$48*IF(E16="Крупногабарит",$C$68,Тарифы!$B$21) -> 13959 | AG16: =X16*J16*'Затраты продавца'!$B$12 -> 1265 | AH16: =Y16*(Тарифы!$B$18+MAX(0,J16-5)*Тарифы!$B$19)*Тарифы!$B$22 -> 140 | AI16: =ROUNDUP(G16/(1-MIN(0.99,MAX(0,K16+$C$51)))*$C$49,0) -> 46 | AJ16: =ROUNDUP(AI16*$C$50,0) -> 5 | AK16: =AI16-AJ16 -> 41 | AL16: =ROUNDUP(AK16*MIN(0.99,MAX(0,K16+$C$51)),0) -> 1 | AM16: =AK16-AL16 -> 40 | AN16: =AM16*H16 -> 119600 | AO16: =AM16*I16 -> 70000 | AP16: =AN16*N16 -> 16744 | AQ16: =AN16*Тарифы!$B$32 -> 1794 | AR16: =AK16*(Тарифы!$B$25+MAX(0,J16-5)*Тарифы!$B$26) -> 5740 | AS16: =AK16*Тарифы!$B$27 -> 1025 | AT16: =BP16*J16*$C$48*'Затраты продавца'!$B$5 -> 4653 | AU16: =AK16*('Затраты продавца'!$B$6+'Затраты продавца'!$B$7) -> 2870 | AV16: =AK16*Тарифы!$B$24 -> 410 | AW16: =AL16*((Тарифы!$B$25+MAX(0,J16-5)*Тарифы!$B$26)*Тарифы!$B$28+'Затраты продавца'!$B$9+(1-'Затраты продавца'!$B$10)*I16*$C$55) -> 502.5 | AX16: =AJ16*Тарифы!$B$29 -> 750 | AY16: =AK16*J16/1000 -> 0.451 | AZ16: =IF(S16="FBO",G16,IF(S16="FBS",AM16,0)) -> 40 | BA16: =IF(S16="FBO",X16,IF(S16="FBS",AK16,0)) -> 41 | BB16: =IF(S16="FBO",Z16,IF(S16="FBS",AN16,0)) -> 119600 | BC16: =IF(S16="FBO",AA16,IF(S16="FBS",AO16,0)) -> 70000 | BD16: =IF(S16="FBO",AB16,IF(S16="FBS",AP16,0)) -> 16744 | BE16: =IF(S16="FBO",AC16,IF(S16="FBS",AQ16,0)) -> 1794 | BF16: =IF(S16="FBO",AD16,IF(S16="FBS",AR16,0)) -> 5740 | BG16: =IF(S16="FBO",AE16,IF(S16="FBS",AS16,0)) -> 1025 | BH16: =IF(S16="FBO",AF16,IF(S16="FBS",AT16,0)) -> 4653 | BI16: =IF(S16="FBO",AG16,0) -> 0 | BJ16: =IF(S16="FBS",AU16,0) -> 2870 | BK16: =IF(S16="FBS",AV16,0) -> 410 | BL16: =IF(S16="FBO",AH16,IF(S16="FBS",AW16,0)) -> 502.5 | BM16: =IF(S16="FBS",AX16,0) -> 750 | BN16: =Y16*I16*(1-'Затраты продавца'!$B$10)*$C$55 -> 262.5 | BO16: =ROUNDUP(X16*L16/$C$48,0) -> 94 | BP16: =ROUNDUP(AI16*L16*$C$54/$C$48,0) -> 94 | BQ16: =IF(S16="FBO",BO16,IF(S16="FBS",BP16,0)) -> 94
B17: =HYPERLINK("#'SKU'!A14","SKU!14") -> SKU!14 | C17: =SKU!A14 -> SM-0013 | D17: =SKU!B14 -> Коврик для йоги 6 мм | E17: =SKU!C14 -> Фитнес | F17: =SKU!L14 -> FBO | G17: =SKU!K14*IF(SKU!L14="не представлен",$C$52,1) -> 320 | H17: =SKU!D14 -> 1490 | I17: =SKU!E14 -> 520 | J17: =SKU!I14 -> 14.85 | K17: =SKU!N14 -> 0.04 | L17: =IF(ISNUMBER(SKU!M14),SKU!M14,$C$53) -> 88.153619 | M17: =VLOOKUP(E17,$B$58:$D$63,2,FALSE()) -> 0.15 | N17: =VLOOKUP(E17,$B$58:$D$63,3,FALSE()) -> 0.14 | O17: =Z17-SUM(AA17:AF17)-AH17-BN17 -> -36698.45 | P17: =AN17-SUM(AO17:AX17) -> 52796.25 | Q17: =IF(MAX(O17,P17)<0,"Пауза",IF(P17>O17,"FBS","FBO")) -> FBS | R17: Авто | S17: =IF(R17="Авто",Q17,R17) -> FBS | T17: =IF(S17="FBO",O17,IF(S17="FBS",P17,0)) -> 52796.25 | U17: =IF(S17="FBS",AK17,0) -> 300 | V17: =IF(S17="FBS",AY17,0) -> 4.455 | X17: =ROUNDUP(G17/(1-K17),0) -> 334 | Y17: =X17-G17 -> 14 | Z17: =G17*H17 -> 476800 | AA17: =G17*I17 -> 166400 | AB17: =Z17*M17 -> 71520 | AC17: =Z17*Тарифы!$B$32 -> 7152 | AD17: =X17*(Тарифы!$B$18+MAX(0,J17-5)*Тарифы!$B$19) -> 59619 | AE17: =X17*Тарифы!$B$20 -> 8350 | AF17: =BO17*J17*$C$48*IF(E17="Крупногабарит",$C$68,Тарифы!$B$21) -> 196866.45 | AG17: =X17*J17*'Затраты продавца'!$B$12 -> 12399.75 | AH17: =Y17*(Тарифы!$B$18+MAX(0,J17-5)*Тарифы!$B$19)*Тарифы!$B$22 -> 2499 | AI17: =ROUNDUP(G17/(1-MIN(0.99,MAX(0,K17+$C$51)))*$C$49,0) -> 334 | AJ17: =ROUNDUP(AI17*$C$50,0) -> 34 | AK17: =AI17-AJ17 -> 300 | AL17: =ROUNDUP(AK17*MIN(0.99,MAX(0,K17+$C$51)),0) -> 12 | AM17: =AK17-AL17 -> 288 | AN17: =AM17*H17 -> 429120 | AO17: =AM17*I17 -> 149760 | AP17: =AN17*N17 -> 60076.8 | AQ17: =AN17*Тарифы!$B$32 -> 6436.8 | AR17: =AK17*(Тарифы!$B$25+MAX(0,J17-5)*Тарифы!$B$26) -> 53550 | AS17: =AK17*Тарифы!$B$27 -> 7500 | AT17: =BP17*J17*$C$48*'Затраты продавца'!$B$5 -> 65622.15 | AU17: =AK17*('Затраты продавца'!$B$6+'Затраты продавца'!$B$7) -> 21000 | AV17: =AK17*Тарифы!$B$24 -> 3000 | AW17: =AL17*((Тарифы!$B$25+MAX(0,J17-5)*Тарифы!$B$26)*Тарифы!$B$28+'Затраты продавца'!$B$9+(1-'Затраты продавца'!$B$10)*I17*$C$55) -> 4278 | AX17: =AJ17*Тарифы!$B$29 -> 5100 | AY17: =AK17*J17/1000 -> 4.455 | AZ17: =IF(S17="FBO",G17,IF(S17="FBS",AM17,0)) -> 288 | BA17: =IF(S17="FBO",X17,IF(S17="FBS",AK17,0)) -> 300 | BB17: =IF(S17="FBO",Z17,IF(S17="FBS",AN17,0)) -> 429120 | BC17: =IF(S17="FBO",AA17,IF(S17="FBS",AO17,0)) -> 149760 | BD17: =IF(S17="FBO",AB17,IF(S17="FBS",AP17,0)) -> 60076.8 | BE17: =IF(S17="FBO",AC17,IF(S17="FBS",AQ17,0)) -> 6436.8 | BF17: =IF(S17="FBO",AD17,IF(S17="FBS",AR17,0)) -> 53550 | BG17: =IF(S17="FBO",AE17,IF(S17="FBS",AS17,0)) -> 7500 | BH17: =IF(S17="FBO",AF17,IF(S17="FBS",AT17,0)) -> 65622.15 | BI17: =IF(S17="FBO",AG17,0) -> 0 | BJ17: =IF(S17="FBS",AU17,0) -> 21000 | BK17: =IF(S17="FBS",AV17,0) -> 3000 | BL17: =IF(S17="FBO",AH17,IF(S17="FBS",AW17,0)) -> 4278 | BM17: =IF(S17="FBS",AX17,0) -> 5100 | BN17: =Y17*I17*(1-'Затраты продавца'!$B$10)*$C$55 -> 1092 | BO17: =ROUNDUP(X17*L17/$C$48,0) -> 982 | BP17: =ROUNDUP(AI17*L17*$C$54/$C$48,0) -> 982 | BQ17: =IF(S17="FBO",BO17,IF(S17="FBS",BP17,0)) -> 982
B18: =HYPERLINK("#'SKU'!A15","SKU!15") -> SKU!15 | C18: =SKU!A15 -> SM-0014 | D18: =SKU!B15 -> Набор эспандеров | E18: =SKU!C15 -> Фитнес | F18: =SKU!L15 -> FBO | G18: =SKU!K15*IF(SKU!L15="не представлен",$C$52,1) -> 410 | H18: =SKU!D15 -> 790 | I18: =SKU!E15 -> 260 | J18: =SKU!I15 -> 1.296 | K18: =SKU!N15 -> 0.04 | L18: =IF(ISNUMBER(SKU!M15),SKU!M15,$C$53) -> 44.843155 | M18: =VLOOKUP(E18,$B$58:$D$63,2,FALSE()) -> 0.15 | N18: =VLOOKUP(E18,$B$58:$D$63,3,FALSE()) -> 0.14 | O18: =Z18-SUM(AA18:AF18)-AH18-BN18 -> 105577.06 | P18: =AN18-SUM(AO18:AX18) -> 65474.47 | Q18: =IF(MAX(O18,P18)<0,"Пауза",IF(P18>O18,"FBS","FBO")) -> FBO | R18: Авто | S18: =IF(R18="Авто",Q18,R18) -> FBO | T18: =IF(S18="FBO",O18,IF(S18="FBS",P18,0)) -> 105577.06 | U18: =IF(S18="FBS",AK18,0) -> 0 | V18: =IF(S18="FBS",AY18,0) -> 0 | X18: =ROUNDUP(G18/(1-K18),0) -> 428 | Y18: =X18-G18 -> 18 | Z18: =G18*H18 -> 323900 | AA18: =G18*I18 -> 106600 | AB18: =Z18*M18 -> 48585 | AC18: =Z18*Тарифы!$B$32 -> 4858.5 | AD18: =X18*(Тарифы!$B$18+MAX(0,J18-5)*Тарифы!$B$19) -> 34240 | AE18: =X18*Тарифы!$B$20 -> 10700 | AF18: =BO18*J18*$C$48*IF(E18="Крупногабарит",$C$68,Тарифы!$B$21) -> 11197.44 | AG18: =X18*J18*'Затраты продавца'!$B$12 -> 1386.72 | AH18: =Y18*(Тарифы!$B$18+MAX(0,J18-5)*Тарифы!$B$19)*Тарифы!$B$22 -> 1440 | AI18: =ROUNDUP(G18/(1-MIN(0.99,MAX(0,K18+$C$51)))*$C$49,0) -> 428 | AJ18: =ROUNDUP(AI18*$C$50,0) -> 43 | AK18: =AI18-AJ18 -> 385 | AL18: =ROUNDUP(AK18*MIN(0.99,MAX(0,K18+$C$51)),0) -> 16 | AM18: =AK18-AL18 -> 369 | AN18: =AM18*H18 -> 291510 | AO18: =AM18*I18 -> 95940 | AP18: =AN18*N18 -> 40811.4 | AQ18: =AN18*Тарифы!$B$32 -> 4372.65 | AR18: =AK18*(Тарифы!$B$25+MAX(0,J18-5)*Тарифы!$B$26) -> 30800 | AS18: =AK18*Тарифы!$B$27 -> 9625 | AT18: =BP18*J18*$C$48*'Затраты продавца'!$B$5 -> 3732.48 | AU18: =AK18*('Затраты продавца'!$B$6+'Затраты продавца'!$B$7) -> 26950 | AV18: =AK18*Тарифы!$B$24 -> 3850 | AW18: =AL18*((Тарифы!$B$25+MAX(0,J18-5)*Тарифы!$B$26)*Тарифы!$B$28+'Затраты продавца'!$B$9+(1-'Затраты продавца'!$B$10)*I18*$C$55) -> 3504 | AX18: =AJ18*Тарифы!$B$29 -> 6450 | AY18: =AK18*J18/1000 -> 0.49896 | AZ18: =IF(S18="FBO",G18,IF(S18="FBS",AM18,0)) -> 410 | BA18: =IF(S18="FBO",X18,IF(S18="FBS",AK18,0)) -> 428 | BB18: =IF(S18="FBO",Z18,IF(S18="FBS",AN18,0)) -> 323900 | BC18: =IF(S18="FBO",AA18,IF(S18="FBS",AO18,0)) -> 106600 | BD18: =IF(S18="FBO",AB18,IF(S18="FBS",AP18,0)) -> 48585 | BE18: =IF(S18="FBO",AC18,IF(S18="FBS",AQ18,0)) -> 4858.5 | BF18: =IF(S18="FBO",AD18,IF(S18="FBS",AR18,0)) -> 34240 | BG18: =IF(S18="FBO",AE18,IF(S18="FBS",AS18,0)) -> 10700 | BH18: =IF(S18="FBO",AF18,IF(S18="FBS",AT18,0)) -> 11197.44 | BI18: =IF(S18="FBO",AG18,0) -> 1386.72 | BJ18: =IF(S18="FBS",AU18,0) -> 0 | BK18: =IF(S18="FBS",AV18,0) -> 0 | BL18: =IF(S18="FBO",AH18,IF(S18="FBS",AW18,0)) -> 1440 | BM18: =IF(S18="FBS",AX18,0) -> 0 | BN18: =Y18*I18*(1-'Затраты продавца'!$B$10)*$C$55 -> 702 | BO18: =ROUNDUP(X18*L18/$C$48,0) -> 640 | BP18: =ROUNDUP(AI18*L18*$C$54/$C$48,0) -> 640 | BQ18: =IF(S18="FBO",BO18,IF(S18="FBS",BP18,0)) -> 640
B19: =HYPERLINK("#'SKU'!A16","SKU!16") -> SKU!16 | C19: =SKU!A16 -> SM-0015 | D19: =SKU!B16 -> Скакалка скоростная | E19: =SKU!C16 -> Аксессуары | F19: =SKU!L16 -> FBO | G19: =SKU!K16*IF(SKU!L16="не представлен",$C$52,1) -> 370 | H19: =SKU!D16 -> 490 | I19: =SKU!E16 -> 150 | J19: =SKU!I16 -> 0.96 | K19: =SKU!N16 -> 0.03 | L19: =IF(ISNUMBER(SKU!M16),SKU!M16,$C$53) -> 79.62719 | M19: =VLOOKUP(E19,$B$58:$D$63,2,FALSE()) -> 0.18 | N19: =VLOOKUP(E19,$B$58:$D$63,3,FALSE()) -> 0.17 | O19: =Z19-SUM(AA19:AF19)-AH19-BN19 -> 35965.06 | P19: =AN19-SUM(AO19:AX19) -> 6871.22 | Q19: =IF(MAX(O19,P19)<0,"Пауза",IF(P19>O19,"FBS","FBO")) -> FBO | R19: Авто | S19: =IF(R19="Авто",Q19,R19) -> FBO | T19: =IF(S19="FBO",O19,IF(S19="FBS",P19,0)) -> 35965.06 | U19: =IF(S19="FBS",AK19,0) -> 0 | V19: =IF(S19="FBS",AY19,0) -> 0 | X19: =ROUNDUP(G19/(1-K19),0) -> 382 | Y19: =X19-G19 -> 12 | Z19: =G19*H19 -> 181300 | AA19: =G19*I19 -> 55500 | AB19: =Z19*M19 -> 32634 | AC19: =Z19*Тарифы!$B$32 -> 2719.5 | AD19: =X19*(Тарифы!$B$18+MAX(0,J19-5)*Тарифы!$B$19) -> 30560 | AE19: =X19*Тарифы!$B$20 -> 9550 | AF19: =BO19*J19*$C$48*IF(E19="Крупногабарит",$C$68,Тарифы!$B$21) -> 13141.44 | AG19: =X19*J19*'Затраты продавца'!$B$12 -> 916.8 | AH19: =Y19*(Тарифы!$B$18+MAX(0,J19-5)*Тарифы!$B$19)*Тарифы!$B$22 -> 960 | AI19: =ROUNDUP(G19/(1-MIN(0.99,MAX(0,K19+$C$51)))*$C$49,0) -> 382 | AJ19: =ROUNDUP(AI19*$C$50,0) -> 39 | AK19: =AI19-AJ19 -> 343 | AL19: =ROUNDUP(AK19*MIN(0.99,MAX(0,K19+$C$51)),0) -> 11 | AM19: =AK19-AL19 -> 332 | AN19: =AM19*H19 -> 162680 | AO19: =AM19*I19 -> 49800 | AP19: =AN19*N19 -> 27655.6 | AQ19: =AN19*Тарифы!$B$32 -> 2440.2 | AR19: =AK19*(Тарифы!$B$25+MAX(0,J19-5)*Тарифы!$B$26) -> 27440 | AS19: =AK19*Тарифы!$B$27 -> 8575 | AT19: =BP19*J19*$C$48*'Затраты продавца'!$B$5 -> 4380.48 | AU19: =AK19*('Затраты продавца'!$B$6+'Затраты продавца'!$B$7) -> 24010 | AV19: =AK19*Тарифы!$B$24 -> 3430 | AW19: =AL19*((Тарифы!$B$25+MAX(0,J19-5)*Тарифы!$B$26)*Тарифы!$B$28+'Затраты продавца'!$B$9+(1-'Затраты продавца'!$B$10)*I19*$C$55) -> 2227.5 | AX19: =AJ19*Тарифы!$B$29 -> 5850 | AY19: =AK19*J19/1000 -> 0.32928 | AZ19: =IF(S19="FBO",G19,IF(S19="FBS",AM19,0)) -> 370 | BA19: =IF(S19="FBO",X19,IF(S19="FBS",AK19,0)) -> 382 | BB19: =IF(S19="FBO",Z19,IF(S19="FBS",AN19,0)) -> 181300 | BC19: =IF(S19="FBO",AA19,IF(S19="FBS",AO19,0)) -> 55500 | BD19: =IF(S19="FBO",AB19,IF(S19="FBS",AP19,0)) -> 32634 | BE19: =IF(S19="FBO",AC19,IF(S19="FBS",AQ19,0)) -> 2719.5 | BF19: =IF(S19="FBO",AD19,IF(S19="FBS",AR19,0)) -> 30560 | BG19: =IF(S19="FBO",AE19,IF(S19="FBS",AS19,0)) -> 9550 | BH19: =IF(S19="FBO",AF19,IF(S19="FBS",AT19,0)) -> 13141.44 | BI19: =IF(S19="FBO",AG19,0) -> 916.8 | BJ19: =IF(S19="FBS",AU19,0) -> 0 | BK19: =IF(S19="FBS",AV19,0) -> 0 | BL19: =IF(S19="FBO",AH19,IF(S19="FBS",AW19,0)) -> 960 | BM19: =IF(S19="FBS",AX19,0) -> 0 | BN19: =Y19*I19*(1-'Затраты продавца'!$B$10)*$C$55 -> 270 | BO19: =ROUNDUP(X19*L19/$C$48,0) -> 1014 | BP19: =ROUNDUP(AI19*L19*$C$54/$C$48,0) -> 1014 | BQ19: =IF(S19="FBO",BO19,IF(S19="FBS",BP19,0)) -> 1014
B20: =HYPERLINK("#'SKU'!A17","SKU!17") -> SKU!17 | C20: =SKU!A17 -> SM-0016 | D20: =SKU!B17 -> Палатка 2-местная | E20: =SKU!C17 -> Туризм | F20: =SKU!L17 -> FBO | G20: =SKU!K17*IF(SKU!L17="не представлен",$C$52,1) -> 45 | H20: =SKU!D17 -> 6990 | I20: =SKU!E17 -> 3200 | J20: =SKU!I17 -> 23.2 | K20: =SKU!N17 -> 0.06 | L20: =IF(ISNUMBER(SKU!M17),SKU!M17,$C$53) -> 44.53253 | M20: =VLOOKUP(E20,$B$58:$D$63,2,FALSE()) -> 0.15 | N20: =VLOOKUP(E20,$B$58:$D$63,3,FALSE()) -> 0.14 | O20: =Z20-SUM(AA20:AF20)-AH20-BN20 -> 80096.85 | P20: =AN20-SUM(AO20:AX20) -> 81688.2 | Q20: =IF(MAX(O20,P20)<0,"Пауза",IF(P20>O20,"FBS","FBO")) -> FBS | R20: Авто | S20: =IF(R20="Авто",Q20,R20) -> FBS | T20: =IF(S20="FBO",O20,IF(S20="FBS",P20,0)) -> 81688.2 | U20: =IF(S20="FBS",AK20,0) -> 43 | V20: =IF(S20="FBS",AY20,0) -> 0.9976 | X20: =ROUNDUP(G20/(1-K20),0) -> 48 | Y20: =X20-G20 -> 3 | Z20: =G20*H20 -> 314550 | AA20: =G20*I20 -> 144000 | AB20: =Z20*M20 -> 47182.5 | AC20: =Z20*Тарифы!$B$32 -> 4718.25 | AD20: =X20*(Тарифы!$B$18+MAX(0,J20-5)*Тарифы!$B$19) -> 12576 | AE20: =X20*Тарифы!$B$20 -> 1200 | AF20: =BO20*J20*$C$48*IF(E20="Крупногабарит",$C$68,Тарифы!$B$21) -> 22550.4 | AG20: =X20*J20*'Затраты продавца'!$B$12 -> 2784 | AH20: =Y20*(Тарифы!$B$18+MAX(0,J20-5)*Тарифы!$B$19)*Тарифы!$B$22 -> 786 | AI20: =ROUNDUP(G20/(1-MIN(0.99,MAX(0,K20+$C$51)))*$C$49,0) -> 48 | AJ20: =ROUNDUP(AI20*$C$50,0) -> 5 | AK20: =AI20-AJ20 -> 43 | AL20: =ROUNDUP(AK20*MIN(0.99,MAX(0,K20+$C$51)),0) -> 3 | AM20: =AK20-AL20 -> 40 | AN20: =AM20*H20 -> 279600 | AO20: =AM20*I20 -> 128000 | AP20: =AN20*N20 -> 39144 | AQ20: =AN20*Тарифы!$B$32 -> 4194 | AR20: =AK20*(Тарифы!$B$25+MAX(0,J20-5)*Тарифы!$B$26) -> 11266 | AS20: =AK20*Тарифы!$B$27 -> 1075 | AT20: =BP20*J20*$C$48*'Затраты продавца'!$B$5 -> 7516.8 | AU20: =AK20*('Затраты продавца'!$B$6+'Затраты продавца'!$B$7) -> 3010 | AV20: =AK20*Тарифы!$B$24 -> 430 | AW20: =AL20*((Тарифы!$B$25+MAX(0,J20-5)*Тарифы!$B$26)*Тарифы!$B$28+'Затраты продавца'!$B$9+(1-'Затраты продавца'!$B$10)*I20*$C$55) -> 2526 | AX20: =AJ20*Тарифы!$B$29 -> 750 | AY20: =AK20*J20/1000 -> 0.9976 | AZ20: =IF(S20="FBO",G20,IF(S20="FBS",AM20,0)) -> 40 | BA20: =IF(S20="FBO",X20,IF(S20="FBS",AK20,0)) -> 43 | BB20: =IF(S20="FBO",Z20,IF(S20="FBS",AN20,0)) -> 279600 | BC20: =IF(S20="FBO",AA20,IF(S20="FBS",AO20,0)) -> 128000 | BD20: =IF(S20="FBO",AB20,IF(S20="FBS",AP20,0)) -> 39144 | BE20: =IF(S20="FBO",AC20,IF(S20="FBS",AQ20,0)) -> 4194 | BF20: =IF(S20="FBO",AD20,IF(S20="FBS",AR20,0)) -> 11266 | BG20: =IF(S20="FBO",AE20,IF(S20="FBS",AS20,0)) -> 1075 | BH20: =IF(S20="FBO",AF20,IF(S20="FBS",AT20,0)) -> 7516.8 | BI20: =IF(S20="FBO",AG20,0) -> 0 | BJ20: =IF(S20="FBS",AU20,0) -> 3010 | BK20: =IF(S20="FBS",AV20,0) -> 430 | BL20: =IF(S20="FBO",AH20,IF(S20="FBS",AW20,0)) -> 2526 | BM20: =IF(S20="FBS",AX20,0) -> 750 | BN20: =Y20*I20*(1-'Затраты продавца'!$B$10)*$C$55 -> 1440 | BO20: =ROUNDUP(X20*L20/$C$48,0) -> 72 | BP20: =ROUNDUP(AI20*L20*$C$54/$C$48,0) -> 72 | BQ20: =IF(S20="FBO",BO20,IF(S20="FBS",BP20,0)) -> 72
B21: =HYPERLINK("#'SKU'!A18","SKU!18") -> SKU!18 | C21: =SKU!A18 -> SM-0017 | D21: =SKU!B18 -> Палатка 4-местная | E21: =SKU!C18 -> Туризм | F21: =SKU!L18 -> FBO | G21: =SKU!K18*IF(SKU!L18="не представлен",$C$52,1) -> 22 | H21: =SKU!D18 -> 12990 | I21: =SKU!E18 -> 6100 | J21: =SKU!I18 -> 45.968 | K21: =SKU!N18 -> 0.07 | L21: =IF(ISNUMBER(SKU!M18),SKU!M18,$C$53) -> 47.409611 | M21: =VLOOKUP(E21,$B$58:$D$63,2,FALSE()) -> 0.15 | N21: =VLOOKUP(E21,$B$58:$D$63,3,FALSE()) -> 0.14 | O21: =Z21-SUM(AA21:AF21)-AH21-BN21 -> 65683.036 | P21: =AN21-SUM(AO21:AX21) -> 68846.282 | Q21: =IF(MAX(O21,P21)<0,"Пауза",IF(P21>O21,"FBS","FBO")) -> FBS | R21: Авто | S21: =IF(R21="Авто",Q21,R21) -> FBS | T21: =IF(S21="FBO",O21,IF(S21="FBS",P21,0)) -> 68846.282 | U21: =IF(S21="FBS",AK21,0) -> 21 | V21: =IF(S21="FBS",AY21,0) -> 0.965328 | X21: =ROUNDUP(G21/(1-K21),0) -> 24 | Y21: =X21-G21 -> 2 | Z21: =G21*H21 -> 285780 | AA21: =G21*I21 -> 134200 | AB21: =Z21*M21 -> 42867 | AC21: =Z21*Тарифы!$B$32 -> 4286.7 | AD21: =X21*(Тарифы!$B$18+MAX(0,J21-5)*Тарифы!$B$19) -> 11752.32 | AE21: =X21*Тарифы!$B$20 -> 600 | AF21: =BO21*J21*$C$48*IF(E21="Крупногабарит",$C$68,Тарифы!$B$21) -> 23581.584 | AG21: =X21*J21*'Затраты продавца'!$B$12 -> 2758.08 | AH21: =Y21*(Тарифы!$B$18+MAX(0,J21-5)*Тарифы!$B$19)*Тарифы!$B$22 -> 979.36 | AI21: =ROUNDUP(G21/(1-MIN(0.99,MAX(0,K21+$C$51)))*$C$49,0) -> 24 | AJ21: =ROUNDUP(AI21*$C$50,0) -> 3 | AK21: =AI21-AJ21 -> 21 | AL21: =ROUNDUP(AK21*MIN(0.99,MAX(0,K21+$C$51)),0) -> 2 | AM21: =AK21-AL21 -> 19 | AN21: =AM21*H21 -> 246810 | AO21: =AM21*I21 -> 115900 | AP21: =AN21*N21 -> 34553.4 | AQ21: =AN21*Тарифы!$B$32 -> 3702.15 | AR21: =AK21*(Тарифы!$B$25+MAX(0,J21-5)*Тарифы!$B$26) -> 10283.28 | AS21: =AK21*Тарифы!$B$27 -> 525 | AT21: =BP21*J21*$C$48*'Затраты продавца'!$B$5 -> 7860.528 | AU21: =AK21*('Затраты продавца'!$B$6+'Затраты продавца'!$B$7) -> 1470 | AV21: =AK21*Тарифы!$B$24 -> 210 | AW21: =AL21*((Тарифы!$B$25+MAX(0,J21-5)*Тарифы!$B$26)*Тарифы!$B$28+'Затраты продавца'!$B$9+(1-'Затраты продавца'!$B$10)*I21*$C$55) -> 3009.36 | AX21: =AJ21*Тарифы!$B$29 -> 450 | AY21: =AK21*J21/1000 -> 0.965328 | AZ21: =IF(S21="FBO",G21,IF(S21="FBS",AM21,0)) -> 19 | BA21: =IF(S21="FBO",X21,IF(S21="FBS",AK21,0)) -> 21 | BB21: =IF(S21="FBO",Z21,IF(S21="FBS",AN21,0)) -> 246810 | BC21: =IF(S21="FBO",AA21,IF(S21="FBS",AO21,0)) -> 115900 | BD21: =IF(S21="FBO",AB21,IF(S21="FBS",AP21,0)) -> 34553.4 | BE21: =IF(S21="FBO",AC21,IF(S21="FBS",AQ21,0)) -> 3702.15 | BF21: =IF(S21="FBO",AD21,IF(S21="FBS",AR21,0)) -> 10283.28 | BG21: =IF(S21="FBO",AE21,IF(S21="FBS",AS21,0)) -> 525 | BH21: =IF(S21="FBO",AF21,IF(S21="FBS",AT21,0)) -> 7860.528 | BI21: =IF(S21="FBO",AG21,0) -> 0 | BJ21: =IF(S21="FBS",AU21,0) -> 1470 | BK21: =IF(S21="FBS",AV21,0) -> 210 | BL21: =IF(S21="FBO",AH21,IF(S21="FBS",AW21,0)) -> 3009.36 | BM21: =IF(S21="FBS",AX21,0) -> 450 | BN21: =Y21*I21*(1-'Затраты продавца'!$B$10)*$C$55 -> 1830 | BO21: =ROUNDUP(X21*L21/$C$48,0) -> 38 | BP21: =ROUNDUP(AI21*L21*$C$54/$C$48,0) -> 38 | BQ21: =IF(S21="FBO",BO21,IF(S21="FBS",BP21,0)) -> 38
B22: =HYPERLINK("#'SKU'!A19","SKU!19") -> SKU!19 | C22: =SKU!A19 -> SM-0018 | D22: =SKU!B19 -> Спальный мешок −5 °C | E22: =SKU!C19 -> Туризм | F22: =SKU!L19 -> FBO | G22: =SKU!K19*IF(SKU!L19="не представлен",$C$52,1) -> 70 | H22: =SKU!D19 -> 3490 | I22: =SKU!E19 -> 1480 | J22: =SKU!I19 -> 31.36 | K22: =SKU!N19 -> 0.06 | L22: =IF(ISNUMBER(SKU!M19),SKU!M19,$C$53) -> 68.899772 | M22: =VLOOKUP(E22,$B$58:$D$63,2,FALSE()) -> 0.15 | N22: =VLOOKUP(E22,$B$58:$D$63,3,FALSE()) -> 0.14 | O22: =Z22-SUM(AA22:AF22)-AH22-BN22 -> -3323.78 | P22: =AN22-SUM(AO22:AX22) -> 32083.14 | Q22: =IF(MAX(O22,P22)<0,"Пауза",IF(P22>O22,"FBS","FBO")) -> FBS | R22: Авто | S22: =IF(R22="Авто",Q22,R22) -> FBS | T22: =IF(S22="FBO",O22,IF(S22="FBS",P22,0)) -> 32083.14 | U22: =IF(S22="FBS",AK22,0) -> 67 | V22: =IF(S22="FBS",AY22,0) -> 2.10112 | X22: =ROUNDUP(G22/(1-K22),0) -> 75 | Y22: =X22-G22 -> 5 | Z22: =G22*H22 -> 244300 | AA22: =G22*I22 -> 103600 | AB22: =Z22*M22 -> 36645 | AC22: =Z22*Тарифы!$B$32 -> 3664.5 | AD22: =X22*(Тарифы!$B$18+MAX(0,J22-5)*Тарифы!$B$19) -> 25770 | AE22: =X22*Тарифы!$B$20 -> 1875 | AF22: =BO22*J22*$C$48*IF(E22="Крупногабарит",$C$68,Тарифы!$B$21) -> 73241.28 | AG22: =X22*J22*'Затраты продавца'!$B$12 -> 5880 | AH22: =Y22*(Тарифы!$B$18+MAX(0,J22-5)*Тарифы!$B$19)*Тарифы!$B$22 -> 1718 | AI22: =ROUNDUP(G22/(1-MIN(0.99,MAX(0,K22+$C$51)))*$C$49,0) -> 75 | AJ22: =ROUNDUP(AI22*$C$50,0) -> 8 | AK22: =AI22-AJ22 -> 67 | AL22: =ROUNDUP(AK22*MIN(0.99,MAX(0,K22+$C$51)),0) -> 5 | AM22: =AK22-AL22 -> 62 | AN22: =AM22*H22 -> 216380 | AO22: =AM22*I22 -> 91760 | AP22: =AN22*N22 -> 30293.2 | AQ22: =AN22*Тарифы!$B$32 -> 3245.7 | AR22: =AK22*(Тарифы!$B$25+MAX(0,J22-5)*Тарифы!$B$26) -> 23021.2 | AS22: =AK22*Тарифы!$B$27 -> 1675 | AT22: =BP22*J22*$C$48*'Затраты продавца'!$B$5 -> 24413.76 | AU22: =AK22*('Затраты продавца'!$B$6+'Затраты продавца'!$B$7) -> 4690 | AV22: =AK22*Тарифы!$B$24 -> 670 | AW22: =AL22*((Тарифы!$B$25+MAX(0,J22-5)*Тарифы!$B$26)*Тарифы!$B$28+'Затраты продавца'!$B$9+(1-'Затраты продавца'!$B$10)*I22*$C$55) -> 3328 | AX22: =AJ22*Тарифы!$B$29 -> 1200 | AY22: =AK22*J22/1000 -> 2.10112 | AZ22: =IF(S22="FBO",G22,IF(S22="FBS",AM22,0)) -> 62 | BA22: =IF(S22="FBO",X22,IF(S22="FBS",AK22,0)) -> 67 | BB22: =IF(S22="FBO",Z22,IF(S22="FBS",AN22,0)) -> 216380 | BC22: =IF(S22="FBO",AA22,IF(S22="FBS",AO22,0)) -> 91760 | BD22: =IF(S22="FBO",AB22,IF(S22="FBS",AP22,0)) -> 30293.2 | BE22: =IF(S22="FBO",AC22,IF(S22="FBS",AQ22,0)) -> 3245.7 | BF22: =IF(S22="FBO",AD22,IF(S22="FBS",AR22,0)) -> 23021.2 | BG22: =IF(S22="FBO",AE22,IF(S22="FBS",AS22,0)) -> 1675 | BH22: =IF(S22="FBO",AF22,IF(S22="FBS",AT22,0)) -> 24413.76 | BI22: =IF(S22="FBO",AG22,0) -> 0 | BJ22: =IF(S22="FBS",AU22,0) -> 4690 | BK22: =IF(S22="FBS",AV22,0) -> 670 | BL22: =IF(S22="FBO",AH22,IF(S22="FBS",AW22,0)) -> 3328 | BM22: =IF(S22="FBS",AX22,0) -> 1200 | BN22: =Y22*I22*(1-'Затраты продавца'!$B$10)*$C$55 -> 1110 | BO22: =ROUNDUP(X22*L22/$C$48,0) -> 173 | BP22: =ROUNDUP(AI22*L22*$C$54/$C$48,0) -> 173 | BQ22: =IF(S22="FBO",BO22,IF(S22="FBS",BP22,0)) -> 173
B23: =HYPERLINK("#'SKU'!A20","SKU!20") -> SKU!20 | C23: =SKU!A20 -> SM-0019 | D23: =SKU!B20 -> Рюкзак туристический 60 л | E23: =SKU!C20 -> Туризм | F23: =SKU!L20 -> FBO | G23: =SKU!K20*IF(SKU!L20="не представлен",$C$52,1) -> 55 | H23: =SKU!D20 -> 5990 | I23: =SKU!E20 -> 2550 | J23: =SKU!I20 -> 56.875 | K23: =SKU!N20 -> 0.08 | L23: =IF(ISNUMBER(SKU!M20),SKU!M20,$C$53) -> 78.989018 | M23: =VLOOKUP(E23,$B$58:$D$63,2,FALSE()) -> 0.15 | N23: =VLOOKUP(E23,$B$58:$D$63,3,FALSE()) -> 0.14 | O23: =Z23-SUM(AA23:AF23)-AH23-BN23 -> -28804.875 | P23: =AN23-SUM(AO23:AX23) -> 38319.075 | Q23: =IF(MAX(O23,P23)<0,"Пауза",IF(P23>O23,"FBS","FBO")) -> FBS | R23: Авто | S23: =IF(R23="Авто",Q23,R23) -> FBS | T23: =IF(S23="FBO",O23,IF(S23="FBS",P23,0)) -> 38319.075 | U23: =IF(S23="FBS",AK23,0) -> 54 | V23: =IF(S23="FBS",AY23,0) -> 3.07125 | X23: =ROUNDUP(G23/(1-K23),0) -> 60 | Y23: =X23-G23 -> 5 | Z23: =G23*H23 -> 329450 | AA23: =G23*I23 -> 140250 | AB23: =Z23*M23 -> 49417.5 | AC23: =Z23*Тарифы!$B$32 -> 4941.75 | AD23: =X23*(Тарифы!$B$18+MAX(0,J23-5)*Тарифы!$B$19) -> 35925 | AE23: =X23*Тарифы!$B$20 -> 1500 | AF23: =BO23*J23*$C$48*IF(E23="Крупногабарит",$C$68,Тарифы!$B$21) -> 121314.38 | AG23: =X23*J23*'Затраты продавца'!$B$12 -> 8531.25 | AH23: =Y23*(Тарифы!$B$18+MAX(0,J23-5)*Тарифы!$B$19)*Тарифы!$B$22 -> 2993.75 | AI23: =ROUNDUP(G23/(1-MIN(0.99,MAX(0,K23+$C$51)))*$C$49,0) -> 60 | AJ23: =ROUNDUP(AI23*$C$50,0) -> 6 | AK23: =AI23-AJ23 -> 54 | AL23: =ROUNDUP(AK23*MIN(0.99,MAX(0,K23+$C$51)),0) -> 5 | AM23: =AK23-AL23 -> 49 | AN23: =AM23*H23 -> 293510 | AO23: =AM23*I23 -> 124950 | AP23: =AN23*N23 -> 41091.4 | AQ23: =AN23*Тарифы!$B$32 -> 4402.65 | AR23: =AK23*(Тарифы!$B$25+MAX(0,J23-5)*Тарифы!$B$26) -> 32332.5 | AS23: =AK23*Тарифы!$B$27 -> 1350 | AT23: =BP23*J23*$C$48*'Затраты продавца'!$B$5 -> 40438.125 | AU23: =AK23*('Затраты продавца'!$B$6+'Затраты продавца'!$B$7) -> 3780 | AV23: =AK23*Тарифы!$B$24 -> 540 | AW23: =AL23*((Тарифы!$B$25+MAX(0,J23-5)*Тарифы!$B$26)*Тарифы!$B$28+'Затраты продавца'!$B$9+(1-'Затраты продавца'!$B$10)*I23*$C$55) -> 5406.25 | AX23: =AJ23*Тарифы!$B$29 -> 900 | AY23: =AK23*J23/1000 -> 3.07125 | AZ23: =IF(S23="FBO",G23,IF(S23="FBS",AM23,0)) -> 49 | BA23: =IF(S23="FBO",X23,IF(S23="FBS",AK23,0)) -> 54 | BB23: =IF(S23="FBO",Z23,IF(S23="FBS",AN23,0)) -> 293510 | BC23: =IF(S23="FBO",AA23,IF(S23="FBS",AO23,0)) -> 124950 | BD23: =IF(S23="FBO",AB23,IF(S23="FBS",AP23,0)) -> 41091.4 | BE23: =IF(S23="FBO",AC23,IF(S23="FBS",AQ23,0)) -> 4402.65 | BF23: =IF(S23="FBO",AD23,IF(S23="FBS",AR23,0)) -> 32332.5 | BG23: =IF(S23="FBO",AE23,IF(S23="FBS",AS23,0)) -> 1350 | BH23: =IF(S23="FBO",AF23,IF(S23="FBS",AT23,0)) -> 40438.125 | BI23: =IF(S23="FBO",AG23,0) -> 0 | BJ23: =IF(S23="FBS",AU23,0) -> 3780 | BK23: =IF(S23="FBS",AV23,0) -> 540 | BL23: =IF(S23="FBO",AH23,IF(S23="FBS",AW23,0)) -> 5406.25 | BM23: =IF(S23="FBS",AX23,0) -> 900 | BN23: =Y23*I23*(1-'Затраты продавца'!$B$10)*$C$55 -> 1912.5 | BO23: =ROUNDUP(X23*L23/$C$48,0) -> 158 | BP23: =ROUNDUP(AI23*L23*$C$54/$C$48,0) -> 158 | BQ23: =IF(S23="FBO",BO23,IF(S23="FBS",BP23,0)) -> 158
B24: =HYPERLINK("#'SKU'!A21","SKU!21") -> SKU!21 | C24: =SKU!A21 -> SM-0020 | D24: =SKU!B21 -> Коврик туристический пенный | E24: =SKU!C21 -> Туризм | F24: =SKU!L21 -> FBO | G24: =SKU!K21*IF(SKU!L21="не представлен",$C$52,1) -> 90 | H24: =SKU!D21 -> 990 | I24: =SKU!E21 -> 370 | J24: =SKU!I21 -> 15.36 | K24: =SKU!N21 -> 0.03 | L24: =IF(ISNUMBER(SKU!M21),SKU!M21,$C$53) -> 88.712523 | M24: =VLOOKUP(E24,$B$58:$D$63,2,FALSE()) -> 0.15 | N24: =VLOOKUP(E24,$B$58:$D$63,3,FALSE()) -> 0.14 | O24: =Z24-SUM(AA24:AF24)-AH24-BN24 -> -36249.96 | P24: =AN24-SUM(AO24:AX24) -> -8224.22 | Q24: =IF(MAX(O24,P24)<0,"Пауза",IF(P24>O24,"FBS","FBO")) -> Пауза | R24: Авто | S24: =IF(R24="Авто",Q24,R24) -> Пауза | T24: =IF(S24="FBO",O24,IF(S24="FBS",P24,0)) -> 0 | U24: =IF(S24="FBS",AK24,0) -> 0 | V24: =IF(S24="FBS",AY24,0) -> 0 | X24: =ROUNDUP(G24/(1-K24),0) -> 93 | Y24: =X24-G24 -> 3 | Z24: =G24*H24 -> 89100 | AA24: =G24*I24 -> 33300 | AB24: =Z24*M24 -> 13365 | AC24: =Z24*Тарифы!$B$32 -> 1336.5 | AD24: =X24*(Тарифы!$B$18+MAX(0,J24-5)*Тарифы!$B$19) -> 17074.8 | AE24: =X24*Тарифы!$B$20 -> 2325 | AF24: =BO24*J24*$C$48*IF(E24="Крупногабарит",$C$68,Тарифы!$B$21) -> 57231.36 | AG24: =X24*J24*'Затраты продавца'!$B$12 -> 3571.2 | AH24: =Y24*(Тарифы!$B$18+MAX(0,J24-5)*Тарифы!$B$19)*Тарифы!$B$22 -> 550.8 | AI24: =ROUNDUP(G24/(1-MIN(0.99,MAX(0,K24+$C$51)))*$C$49,0) -> 93 | AJ24: =ROUNDUP(AI24*$C$50,0) -> 10 | AK24: =AI24-AJ24 -> 83 | AL24: =ROUNDUP(AK24*MIN(0.99,MAX(0,K24+$C$51)),0) -> 3 | AM24: =AK24-AL24 -> 80 | AN24: =AM24*H24 -> 79200 | AO24: =AM24*I24 -> 29600 | AP24: =AN24*N24 -> 11088 | AQ24: =AN24*Тарифы!$B$32 -> 1188 | AR24: =AK24*(Тарифы!$B$25+MAX(0,J24-5)*Тарифы!$B$26) -> 15238.8 | AS24: =AK24*Тарифы!$B$27 -> 2075 | AT24: =BP24*J24*$C$48*'Затраты продавца'!$B$5 -> 19077.12 | AU24: =AK24*('Затраты продавца'!$B$6+'Затраты продавца'!$B$7) -> 5810 | AV24: =AK24*Тарифы!$B$24 -> 830 | AW24: =AL24*((Тарифы!$B$25+MAX(0,J24-5)*Тарифы!$B$26)*Тарифы!$B$28+'Затраты продавца'!$B$9+(1-'Затраты продавца'!$B$10)*I24*$C$55) -> 1017.3 | AX24: =AJ24*Тарифы!$B$29 -> 1500 | AY24: =AK24*J24/1000 -> 1.27488 | AZ24: =IF(S24="FBO",G24,IF(S24="FBS",AM24,0)) -> 0 | BA24: =IF(S24="FBO",X24,IF(S24="FBS",AK24,0)) -> 0 | BB24: =IF(S24="FBO",Z24,IF(S24="FBS",AN24,0)) -> 0 | BC24: =IF(S24="FBO",AA24,IF(S24="FBS",AO24,0)) -> 0 | BD24: =IF(S24="FBO",AB24,IF(S24="FBS",AP24,0)) -> 0 | BE24: =IF(S24="FBO",AC24,IF(S24="FBS",AQ24,0)) -> 0 | BF24: =IF(S24="FBO",AD24,IF(S24="FBS",AR24,0)) -> 0 | BG24: =IF(S24="FBO",AE24,IF(S24="FBS",AS24,0)) -> 0 | BH24: =IF(S24="FBO",AF24,IF(S24="FBS",AT24,0)) -> 0 | BI24: =IF(S24="FBO",AG24,0) -> 0 | BJ24: =IF(S24="FBS",AU24,0) -> 0 | BK24: =IF(S24="FBS",AV24,0) -> 0 | BL24: =IF(S24="FBO",AH24,IF(S24="FBS",AW24,0)) -> 0 | BM24: =IF(S24="FBS",AX24,0) -> 0 | BN24: =Y24*I24*(1-'Затраты продавца'!$B$10)*$C$55 -> 166.5 | BO24: =ROUNDUP(X24*L24/$C$48,0) -> 276 | BP24: =ROUNDUP(AI24*L24*$C$54/$C$48,0) -> 276 | BQ24: =IF(S24="FBO",BO24,IF(S24="FBS",BP24,0)) -> 0
B25: =HYPERLINK("#'SKU'!A22","SKU!22") -> SKU!22 | C25: =SKU!A22 -> SM-0021 | D25: =SKU!B22 -> Велотренажёр магнитный | E25: =SKU!C22 -> Крупногабарит | F25: =SKU!L22 -> не представлен | G25: =SKU!K22*IF(SKU!L22="не представлен",$C$52,1) -> 25 | H25: =SKU!D22 -> 24990 | I25: =SKU!E22 -> 14200 | J25: =SKU!I22 -> 138 | K25: =SKU!N22 -> 0.05 | L25: =IF(ISNUMBER(SKU!M22),SKU!M22,$C$53) -> 75.361847 | M25: =VLOOKUP(E25,$B$58:$D$63,2,FALSE()) -> 0.12 | N25: =VLOOKUP(E25,$B$58:$D$63,3,FALSE()) -> 0.11 | O25: =Z25-SUM(AA25:AF25)-AH25-BN25 -> -1176.25 | P25: =AN25-SUM(AO25:AX25) -> 82339.5 | Q25: =IF(MAX(O25,P25)<0,"Пауза",IF(P25>O25,"FBS","FBO")) -> FBS | R25: Авто | S25: =IF(R25="Авто",Q25,R25) -> FBS | T25: =IF(S25="FBO",O25,IF(S25="FBS",P25,0)) -> 82339.5 | U25: =IF(S25="FBS",AK25,0) -> 24 | V25: =IF(S25="FBS",AY25,0) -> 3.312 | X25: =ROUNDUP(G25/(1-K25),0) -> 27 | Y25: =X25-G25 -> 2 | Z25: =G25*H25 -> 624750 | AA25: =G25*I25 -> 355000 | AB25: =Z25*M25 -> 74970 | AC25: =Z25*Тарифы!$B$32 -> 9371.25 | AD25: =X25*(Тарифы!$B$18+MAX(0,J25-5)*Тарифы!$B$19) -> 38070 | AE25: =X25*Тарифы!$B$20 -> 675 | AF25: =BO25*J25*$C$48*IF(E25="Крупногабарит",$C$68,Тарифы!$B$21) -> 140760 | AG25: =X25*J25*'Затраты продавца'!$B$12 -> 9315 | AH25: =Y25*(Тарифы!$B$18+MAX(0,J25-5)*Тарифы!$B$19)*Тарифы!$B$22 -> 2820 | AI25: =ROUNDUP(G25/(1-MIN(0.99,MAX(0,K25+$C$51)))*$C$49,0) -> 27 | AJ25: =ROUNDUP(AI25*$C$50,0) -> 3 | AK25: =AI25-AJ25 -> 24 | AL25: =ROUNDUP(AK25*MIN(0.99,MAX(0,K25+$C$51)),0) -> 2 | AM25: =AK25-AL25 -> 22 | AN25: =AM25*H25 -> 549780 | AO25: =AM25*I25 -> 312400 | AP25: =AN25*N25 -> 60475.8 | AQ25: =AN25*Тарифы!$B$32 -> 8246.7 | AR25: =AK25*(Тарифы!$B$25+MAX(0,J25-5)*Тарифы!$B$26) -> 33840 | AS25: =AK25*Тарифы!$B$27 -> 600 | AT25: =BP25*J25*$C$48*'Затраты продавца'!$B$5 -> 42228 | AU25: =AK25*('Затраты продавца'!$B$6+'Затраты продавца'!$B$7) -> 1680 | AV25: =AK25*Тарифы!$B$24 -> 240 | AW25: =AL25*((Тарифы!$B$25+MAX(0,J25-5)*Тарифы!$B$26)*Тарифы!$B$28+'Затраты продавца'!$B$9+(1-'Затраты продавца'!$B$10)*I25*$C$55) -> 7280 | AX25: =AJ25*Тарифы!$B$29 -> 450 | AY25: =AK25*J25/1000 -> 3.312 | AZ25: =IF(S25="FBO",G25,IF(S25="FBS",AM25,0)) -> 22 | BA25: =IF(S25="FBO",X25,IF(S25="FBS",AK25,0)) -> 24 | BB25: =IF(S25="FBO",Z25,IF(S25="FBS",AN25,0)) -> 549780 | BC25: =IF(S25="FBO",AA25,IF(S25="FBS",AO25,0)) -> 312400 | BD25: =IF(S25="FBO",AB25,IF(S25="FBS",AP25,0)) -> 60475.8 | BE25: =IF(S25="FBO",AC25,IF(S25="FBS",AQ25,0)) -> 8246.7 | BF25: =IF(S25="FBO",AD25,IF(S25="FBS",AR25,0)) -> 33840 | BG25: =IF(S25="FBO",AE25,IF(S25="FBS",AS25,0)) -> 600 | BH25: =IF(S25="FBO",AF25,IF(S25="FBS",AT25,0)) -> 42228 | BI25: =IF(S25="FBO",AG25,0) -> 0 | BJ25: =IF(S25="FBS",AU25,0) -> 1680 | BK25: =IF(S25="FBS",AV25,0) -> 240 | BL25: =IF(S25="FBO",AH25,IF(S25="FBS",AW25,0)) -> 7280 | BM25: =IF(S25="FBS",AX25,0) -> 450 | BN25: =Y25*I25*(1-'Затраты продавца'!$B$10)*$C$55 -> 4260 | BO25: =ROUNDUP(X25*L25/$C$48,0) -> 68 | BP25: =ROUNDUP(AI25*L25*$C$54/$C$48,0) -> 68 | BQ25: =IF(S25="FBO",BO25,IF(S25="FBS",BP25,0)) -> 68
B26: =HYPERLINK("#'SKU'!A23","SKU!23") -> SKU!23 | C26: =SKU!A23 -> SM-0022 | D26: =SKU!B23 -> Беговая дорожка складная | E26: =SKU!C23 -> Крупногабарит | F26: =SKU!L23 -> не представлен | G26: =SKU!K23*IF(SKU!L23="не представлен",$C$52,1) -> 12 | H26: =SKU!D23 -> 49990 | I26: =SKU!E23 -> 28900 | J26: =SKU!I23 -> 345.6 | K26: =SKU!N23 -> 0.05 | L26: =IF(ISNUMBER(SKU!M23),SKU!M23,$C$53) -> 75.361847 | M26: =VLOOKUP(E26,$B$58:$D$63,2,FALSE()) -> 0.12 | N26: =VLOOKUP(E26,$B$58:$D$63,3,FALSE()) -> 0.11 | O26: =Z26-SUM(AA26:AF26)-AH26-BN26 -> -52439.8 | P26: =AN26-SUM(AO26:AX26) -> 49368.9 | Q26: =IF(MAX(O26,P26)<0,"Пауза",IF(P26>O26,"FBS","FBO")) -> FBS | R26: Авто | S26: =IF(R26="Авто",Q26,R26) -> FBS | T26: =IF(S26="FBO",O26,IF(S26="FBS",P26,0)) -> 49368.9 | U26: =IF(S26="FBS",AK26,0) -> 11 | V26: =IF(S26="FBS",AY26,0) -> 3.8016 | X26: =ROUNDUP(G26/(1-K26),0) -> 13 | Y26: =X26-G26 -> 1 | Z26: =G26*H26 -> 599880 | AA26: =G26*I26 -> 346800 | AB26: =Z26*M26 -> 71985.6 | AC26: =Z26*Тарифы!$B$32 -> 8998.2 | AD26: =X26*(Тарифы!$B$18+MAX(0,J26-5)*Тарифы!$B$19) -> 45318 | AE26: =X26*Тарифы!$B$20 -> 325 | AF26: =BO26*J26*$C$48*IF(E26="Крупногабарит",$C$68,Тарифы!$B$21) -> 171072 | AG26: =X26*J26*'Затраты продавца'!$B$12 -> 11232 | AH26: =Y26*(Тарифы!$B$18+MAX(0,J26-5)*Тарифы!$B$19)*Тарифы!$B$22 -> 3486 | AI26: =ROUNDUP(G26/(1-MIN(0.99,MAX(0,K26+$C$51)))*$C$49,0) -> 13 | AJ26: =ROUNDUP(AI26*$C$50,0) -> 2 | AK26: =AI26-AJ26 -> 11 | AL26: =ROUNDUP(AK26*MIN(0.99,MAX(0,K26+$C$51)),0) -> 1 | AM26: =AK26-AL26 -> 10 | AN26: =AM26*H26 -> 499900 | AO26: =AM26*I26 -> 289000 | AP26: =AN26*N26 -> 54989 | AQ26: =AN26*Тарифы!$B$32 -> 7498.5 | AR26: =AK26*(Тарифы!$B$25+MAX(0,J26-5)*Тарифы!$B$26) -> 38346 | AS26: =AK26*Тарифы!$B$27 -> 275 | AT26: =BP26*J26*$C$48*'Затраты продавца'!$B$5 -> 51321.6 | AU26: =AK26*('Затраты продавца'!$B$6+'Затраты продавца'!$B$7) -> 770 | AV26: =AK26*Тарифы!$B$24 -> 110 | AW26: =AL26*((Тарифы!$B$25+MAX(0,J26-5)*Тарифы!$B$26)*Тарифы!$B$28+'Затраты продавца'!$B$9+(1-'Затраты продавца'!$B$10)*I26*$C$55) -> 7921 | AX26: =AJ26*Тарифы!$B$29 -> 300 | AY26: =AK26*J26/1000 -> 3.8016 | AZ26: =IF(S26="FBO",G26,IF(S26="FBS",AM26,0)) -> 10 | BA26: =IF(S26="FBO",X26,IF(S26="FBS",AK26,0)) -> 11 | BB26: =IF(S26="FBO",Z26,IF(S26="FBS",AN26,0)) -> 499900 | BC26: =IF(S26="FBO",AA26,IF(S26="FBS",AO26,0)) -> 289000 | BD26: =IF(S26="FBO",AB26,IF(S26="FBS",AP26,0)) -> 54989 | BE26: =IF(S26="FBO",AC26,IF(S26="FBS",AQ26,0)) -> 7498.5 | BF26: =IF(S26="FBO",AD26,IF(S26="FBS",AR26,0)) -> 38346 | BG26: =IF(S26="FBO",AE26,IF(S26="FBS",AS26,0)) -> 275 | BH26: =IF(S26="FBO",AF26,IF(S26="FBS",AT26,0)) -> 51321.6 | BI26: =IF(S26="FBO",AG26,0) -> 0 | BJ26: =IF(S26="FBS",AU26,0) -> 770 | BK26: =IF(S26="FBS",AV26,0) -> 110 | BL26: =IF(S26="FBO",AH26,IF(S26="FBS",AW26,0)) -> 7921 | BM26: =IF(S26="FBS",AX26,0) -> 300 | BN26: =Y26*I26*(1-'Затраты продавца'!$B$10)*$C$55 -> 4335 | BO26: =ROUNDUP(X26*L26/$C$48,0) -> 33 | BP26: =ROUNDUP(AI26*L26*$C$54/$C$48,0) -> 33 | BQ26: =IF(S26="FBO",BO26,IF(S26="FBS",BP26,0)) -> 33
B27: =HYPERLINK("#'SKU'!A24","SKU!24") -> SKU!24 | C27: =SKU!A24 -> SM-0023 | D27: =SKU!B24 -> Батут каркасный 305 см | E27: =SKU!C24 -> Крупногабарит | F27: =SKU!L24 -> не представлен | G27: =SKU!K24*IF(SKU!L24="не представлен",$C$52,1) -> 15 | H27: =SKU!D24 -> 18990 | I27: =SKU!E24 -> 10400 | J27: =SKU!I24 -> 228 | K27: =SKU!N24 -> 0.04 | L27: =IF(ISNUMBER(SKU!M24),SKU!M24,$C$53) -> 75.361847 | M27: =VLOOKUP(E27,$B$58:$D$63,2,FALSE()) -> 0.12 | N27: =VLOOKUP(E27,$B$58:$D$63,3,FALSE()) -> 0.11 | O27: =Z27-SUM(AA27:AF27)-AH27-BN27 -> -91054.75 | P27: =AN27-SUM(AO27:AX27) -> 665.25 | Q27: =IF(MAX(O27,P27)<0,"Пауза",IF(P27>O27,"FBS","FBO")) -> FBS | R27: Авто | S27: =IF(R27="Авто",Q27,R27) -> FBS | T27: =IF(S27="FBO",O27,IF(S27="FBS",P27,0)) -> 665.25 | U27: =IF(S27="FBS",AK27,0) -> 14 | V27: =IF(S27="FBS",AY27,0) -> 3.192 | X27: =ROUNDUP(G27/(1-K27),0) -> 16 | Y27: =X27-G27 -> 1 | Z27: =G27*H27 -> 284850 | AA27: =G27*I27 -> 156000 | AB27: =Z27*M27 -> 34182 | AC27: =Z27*Тарифы!$B$32 -> 4272.75 | AD27: =X27*(Тарифы!$B$18+MAX(0,J27-5)*Тарифы!$B$19) -> 36960 | AE27: =X27*Тарифы!$B$20 -> 400 | AF27: =BO27*J27*$C$48*IF(E27="Крупногабарит",$C$68,Тарифы!$B$21) -> 140220 | AG27: =X27*J27*'Затраты продавца'!$B$12 -> 9120 | AH27: =Y27*(Тарифы!$B$18+MAX(0,J27-5)*Тарифы!$B$19)*Тарифы!$B$22 -> 2310 | AI27: =ROUNDUP(G27/(1-MIN(0.99,MAX(0,K27+$C$51)))*$C$49,0) -> 16 | AJ27: =ROUNDUP(AI27*$C$50,0) -> 2 | AK27: =AI27-AJ27 -> 14 | AL27: =ROUNDUP(AK27*MIN(0.99,MAX(0,K27+$C$51)),0) -> 1 | AM27: =AK27-AL27 -> 13 | AN27: =AM27*H27 -> 246870 | AO27: =AM27*I27 -> 135200 | AP27: =AN27*N27 -> 27155.7 | AQ27: =AN27*Тарифы!$B$32 -> 3703.05 | AR27: =AK27*(Тарифы!$B$25+MAX(0,J27-5)*Тарифы!$B$26) -> 32340 | AS27: =AK27*Тарифы!$B$27 -> 350 | AT27: =BP27*J27*$C$48*'Затраты продавца'!$B$5 -> 42066 | AU27: =AK27*('Затраты продавца'!$B$6+'Затраты продавца'!$B$7) -> 980 | AV27: =AK27*Тарифы!$B$24 -> 140 | AW27: =AL27*((Тарифы!$B$25+MAX(0,J27-5)*Тарифы!$B$26)*Тарифы!$B$28+'Затраты продавца'!$B$9+(1-'Затраты продавца'!$B$10)*I27*$C$55) -> 3970 | AX27: =AJ27*Тарифы!$B$29 -> 300 | AY27: =AK27*J27/1000 -> 3.192 | AZ27: =IF(S27="FBO",G27,IF(S27="FBS",AM27,0)) -> 13 | BA27: =IF(S27="FBO",X27,IF(S27="FBS",AK27,0)) -> 14 | BB27: =IF(S27="FBO",Z27,IF(S27="FBS",AN27,0)) -> 246870 | BC27: =IF(S27="FBO",AA27,IF(S27="FBS",AO27,0)) -> 135200 | BD27: =IF(S27="FBO",AB27,IF(S27="FBS",AP27,0)) -> 27155.7 | BE27: =IF(S27="FBO",AC27,IF(S27="FBS",AQ27,0)) -> 3703.05 | BF27: =IF(S27="FBO",AD27,IF(S27="FBS",AR27,0)) -> 32340 | BG27: =IF(S27="FBO",AE27,IF(S27="FBS",AS27,0)) -> 350 | BH27: =IF(S27="FBO",AF27,IF(S27="FBS",AT27,0)) -> 42066 | BI27: =IF(S27="FBO",AG27,0) -> 0 | BJ27: =IF(S27="FBS",AU27,0) -> 980 | BK27: =IF(S27="FBS",AV27,0) -> 140 | BL27: =IF(S27="FBO",AH27,IF(S27="FBS",AW27,0)) -> 3970 | BM27: =IF(S27="FBS",AX27,0) -> 300 | BN27: =Y27*I27*(1-'Затраты продавца'!$B$10)*$C$55 -> 1560 | BO27: =ROUNDUP(X27*L27/$C$48,0) -> 41 | BP27: =ROUNDUP(AI27*L27*$C$54/$C$48,0) -> 41 | BQ27: =IF(S27="FBO",BO27,IF(S27="FBS",BP27,0)) -> 41
B28: =HYPERLINK("#'SKU'!A25","SKU!25") -> SKU!25 | C28: =SKU!A25 -> SM-0024 | D28: =SKU!B25 -> SUP-доска надувная | E28: =SKU!C25 -> Крупногабарит | F28: =SKU!L25 -> не представлен | G28: =SKU!K25*IF(SKU!L25="не представлен",$C$52,1) -> 20 | H28: =SKU!D25 -> 21990 | I28: =SKU!E25 -> 11900 | J28: =SKU!I25 -> 128.25 | K28: =SKU!N25 -> 0.06 | L28: =IF(ISNUMBER(SKU!M25),SKU!M25,$C$53) -> 75.361847 | M28: =VLOOKUP(E28,$B$58:$D$63,2,FALSE()) -> 0.12 | N28: =VLOOKUP(E28,$B$58:$D$63,3,FALSE()) -> 0.11 | O28: =Z28-SUM(AA28:AF28)-AH28-BN28 -> -923 | P28: =AN28-SUM(AO28:AX28) -> 58704.75 | Q28: =IF(MAX(O28,P28)<0,"Пауза",IF(P28>O28,"FBS","FBO")) -> FBS | R28: Авто | S28: =IF(R28="Авто",Q28,R28) -> FBS | T28: =IF(S28="FBO",O28,IF(S28="FBS",P28,0)) -> 58704.75 | U28: =IF(S28="FBS",AK28,0) -> 19 | V28: =IF(S28="FBS",AY28,0) -> 2.43675 | X28: =ROUNDUP(G28/(1-K28),0) -> 22 | Y28: =X28-G28 -> 2 | Z28: =G28*H28 -> 439800 | AA28: =G28*I28 -> 238000 | AB28: =Z28*M28 -> 52776 | AC28: =Z28*Тарифы!$B$32 -> 6597 | AD28: =X28*(Тарифы!$B$18+MAX(0,J28-5)*Тарифы!$B$19) -> 28875 | AE28: =X28*Тарифы!$B$20 -> 550 | AF28: =BO28*J28*$C$48*IF(E28="Крупногабарит",$C$68,Тарифы!$B$21) -> 107730 | AG28: =X28*J28*'Затраты продавца'!$B$12 -> 7053.75 | AH28: =Y28*(Тарифы!$B$18+MAX(0,J28-5)*Тарифы!$B$19)*Тарифы!$B$22 -> 2625 | AI28: =ROUNDUP(G28/(1-MIN(0.99,MAX(0,K28+$C$51)))*$C$49,0) -> 22 | AJ28: =ROUNDUP(AI28*$C$50,0) -> 3 | AK28: =AI28-AJ28 -> 19 | AL28: =ROUNDUP(AK28*MIN(0.99,MAX(0,K28+$C$51)),0) -> 2 | AM28: =AK28-AL28 -> 17 | AN28: =AM28*H28 -> 373830 | AO28: =AM28*I28 -> 202300 | AP28: =AN28*N28 -> 41121.3 | AQ28: =AN28*Тарифы!$B$32 -> 5607.45 | AR28: =AK28*(Тарифы!$B$25+MAX(0,J28-5)*Тарифы!$B$26) -> 24937.5 | AS28: =AK28*Тарифы!$B$27 -> 475 | AT28: =BP28*J28*$C$48*'Затраты продавца'!$B$5 -> 32319 | AU28: =AK28*('Затраты продавца'!$B$6+'Затраты продавца'!$B$7) -> 1330 | AV28: =AK28*Тарифы!$B$24 -> 190 | AW28: =AL28*((Тарифы!$B$25+MAX(0,J28-5)*Тарифы!$B$26)*Тарифы!$B$28+'Затраты продавца'!$B$9+(1-'Затраты продавца'!$B$10)*I28*$C$55) -> 6395 | AX28: =AJ28*Тарифы!$B$29 -> 450 | AY28: =AK28*J28/1000 -> 2.43675 | AZ28: =IF(S28="FBO",G28,IF(S28="FBS",AM28,0)) -> 17 | BA28: =IF(S28="FBO",X28,IF(S28="FBS",AK28,0)) -> 19 | BB28: =IF(S28="FBO",Z28,IF(S28="FBS",AN28,0)) -> 373830 | BC28: =IF(S28="FBO",AA28,IF(S28="FBS",AO28,0)) -> 202300 | BD28: =IF(S28="FBO",AB28,IF(S28="FBS",AP28,0)) -> 41121.3 | BE28: =IF(S28="FBO",AC28,IF(S28="FBS",AQ28,0)) -> 5607.45 | BF28: =IF(S28="FBO",AD28,IF(S28="FBS",AR28,0)) -> 24937.5 | BG28: =IF(S28="FBO",AE28,IF(S28="FBS",AS28,0)) -> 475 | BH28: =IF(S28="FBO",AF28,IF(S28="FBS",AT28,0)) -> 32319 | BI28: =IF(S28="FBO",AG28,0) -> 0 | BJ28: =IF(S28="FBS",AU28,0) -> 1330 | BK28: =IF(S28="FBS",AV28,0) -> 190 | BL28: =IF(S28="FBO",AH28,IF(S28="FBS",AW28,0)) -> 6395 | BM28: =IF(S28="FBS",AX28,0) -> 450 | BN28: =Y28*I28*(1-'Затраты продавца'!$B$10)*$C$55 -> 3570 | BO28: =ROUNDUP(X28*L28/$C$48,0) -> 56 | BP28: =ROUNDUP(AI28*L28*$C$54/$C$48,0) -> 56 | BQ28: =IF(S28="FBO",BO28,IF(S28="FBS",BP28,0)) -> 56
B29: =HYPERLINK("#'SKU'!A26","SKU!26") -> SKU!26 | C29: =SKU!A26 -> SM-0025 | D29: =SKU!B26 -> Каяк надувной 2-местный | E29: =SKU!C26 -> Крупногабарит | F29: =SKU!L26 -> не представлен | G29: =SKU!K26*IF(SKU!L26="не представлен",$C$52,1) -> 8 | H29: =SKU!D26 -> 34990 | I29: =SKU!E26 -> 19400 | J29: =SKU!I26 -> 182 | K29: =SKU!N26 -> 0.06 | L29: =IF(ISNUMBER(SKU!M26),SKU!M26,$C$53) -> 75.361847 | M29: =VLOOKUP(E29,$B$58:$D$63,2,FALSE()) -> 0.12 | N29: =VLOOKUP(E29,$B$58:$D$63,3,FALSE()) -> 0.11 | O29: =Z29-SUM(AA29:AF29)-AH29-BN29 -> 2505.8 | P29: =AN29-SUM(AO29:AX29) -> 39026.75 | Q29: =IF(MAX(O29,P29)<0,"Пауза",IF(P29>O29,"FBS","FBO")) -> FBS | R29: Авто | S29: =IF(R29="Авто",Q29,R29) -> FBS | T29: =IF(S29="FBO",O29,IF(S29="FBS",P29,0)) -> 39026.75 | U29: =IF(S29="FBS",AK29,0) -> 8 | V29: =IF(S29="FBS",AY29,0) -> 1.456 | X29: =ROUNDUP(G29/(1-K29),0) -> 9 | Y29: =X29-G29 -> 1 | Z29: =G29*H29 -> 279920 | AA29: =G29*I29 -> 155200 | AB29: =Z29*M29 -> 33590.4 | AC29: =Z29*Тарифы!$B$32 -> 4198.8 | AD29: =X29*(Тарифы!$B$18+MAX(0,J29-5)*Тарифы!$B$19) -> 16650 | AE29: =X29*Тарифы!$B$20 -> 225 | AF29: =BO29*J29*$C$48*IF(E29="Крупногабарит",$C$68,Тарифы!$B$21) -> 62790 | AG29: =X29*J29*'Затраты продавца'!$B$12 -> 4095 | AH29: =Y29*(Тарифы!$B$18+MAX(0,J29-5)*Тарифы!$B$19)*Тарифы!$B$22 -> 1850 | AI29: =ROUNDUP(G29/(1-MIN(0.99,MAX(0,K29+$C$51)))*$C$49,0) -> 9 | AJ29: =ROUNDUP(AI29*$C$50,0) -> 1 | AK29: =AI29-AJ29 -> 8 | AL29: =ROUNDUP(AK29*MIN(0.99,MAX(0,K29+$C$51)),0) -> 1 | AM29: =AK29-AL29 -> 7 | AN29: =AM29*H29 -> 244930 | AO29: =AM29*I29 -> 135800 | AP29: =AN29*N29 -> 26942.3 | AQ29: =AN29*Тарифы!$B$32 -> 3673.95 | AR29: =AK29*(Тарифы!$B$25+MAX(0,J29-5)*Тарифы!$B$26) -> 14800 | AS29: =AK29*Тарифы!$B$27 -> 200 | AT29: =BP29*J29*$C$48*'Затраты продавца'!$B$5 -> 18837 | AU29: =AK29*('Затраты продавца'!$B$6+'Затраты продавца'!$B$7) -> 560 | AV29: =AK29*Тарифы!$B$24 -> 80 | AW29: =AL29*((Тарифы!$B$25+MAX(0,J29-5)*Тарифы!$B$26)*Тарифы!$B$28+'Затраты продавца'!$B$9+(1-'Затраты продавца'!$B$10)*I29*$C$55) -> 4860 | AX29: =AJ29*Тарифы!$B$29 -> 150 | AY29: =AK29*J29/1000 -> 1.456 | AZ29: =IF(S29="FBO",G29,IF(S29="FBS",AM29,0)) -> 7 | BA29: =IF(S29="FBO",X29,IF(S29="FBS",AK29,0)) -> 8 | BB29: =IF(S29="FBO",Z29,IF(S29="FBS",AN29,0)) -> 244930 | BC29: =IF(S29="FBO",AA29,IF(S29="FBS",AO29,0)) -> 135800 | BD29: =IF(S29="FBO",AB29,IF(S29="FBS",AP29,0)) -> 26942.3 | BE29: =IF(S29="FBO",AC29,IF(S29="FBS",AQ29,0)) -> 3673.95 | BF29: =IF(S29="FBO",AD29,IF(S29="FBS",AR29,0)) -> 14800 | BG29: =IF(S29="FBO",AE29,IF(S29="FBS",AS29,0)) -> 200 | BH29: =IF(S29="FBO",AF29,IF(S29="FBS",AT29,0)) -> 18837 | BI29: =IF(S29="FBO",AG29,0) -> 0 | BJ29: =IF(S29="FBS",AU29,0) -> 560 | BK29: =IF(S29="FBS",AV29,0) -> 80 | BL29: =IF(S29="FBO",AH29,IF(S29="FBS",AW29,0)) -> 4860 | BM29: =IF(S29="FBS",AX29,0) -> 150 | BN29: =Y29*I29*(1-'Затраты продавца'!$B$10)*$C$55 -> 2910 | BO29: =ROUNDUP(X29*L29/$C$48,0) -> 23 | BP29: =ROUNDUP(AI29*L29*$C$54/$C$48,0) -> 23 | BQ29: =IF(S29="FBO",BO29,IF(S29="FBS",BP29,0)) -> 23
B30: =HYPERLINK("#'SKU'!A27","SKU!27") -> SKU!27 | C30: =SKU!A27 -> SM-0026 | D30: =SKU!B27 -> Стол теннисный складной | E30: =SKU!C27 -> Крупногабарит | F30: =SKU!L27 -> не представлен | G30: =SKU!K27*IF(SKU!L27="не представлен",$C$52,1) -> 6 | H30: =SKU!D27 -> 54990 | I30: =SKU!E27 -> 31800 | J30: =SKU!I27 -> 272.64 | K30: =SKU!N27 -> 0.04 | L30: =IF(ISNUMBER(SKU!M27),SKU!M27,$C$53) -> 75.361847 | M30: =VLOOKUP(E30,$B$58:$D$63,2,FALSE()) -> 0.12 | N30: =VLOOKUP(E30,$B$58:$D$63,3,FALSE()) -> 0.11 | O30: =Z30-SUM(AA30:AF30)-AH30-BN30 -> -6010.9 | P30: =AN30-SUM(AO30:AX30) -> 34552.61 | Q30: =IF(MAX(O30,P30)<0,"Пауза",IF(P30>O30,"FBS","FBO")) -> FBS | R30: Авто | S30: =IF(R30="Авто",Q30,R30) -> FBS | T30: =IF(S30="FBO",O30,IF(S30="FBS",P30,0)) -> 34552.61 | U30: =IF(S30="FBS",AK30,0) -> 6 | V30: =IF(S30="FBS",AY30,0) -> 1.63584 | X30: =ROUNDUP(G30/(1-K30),0) -> 7 | Y30: =X30-G30 -> 1 | Z30: =G30*H30 -> 329940 | AA30: =G30*I30 -> 190800 | AB30: =Z30*M30 -> 39592.8 | AC30: =Z30*Тарифы!$B$32 -> 4949.1 | AD30: =X30*(Тарифы!$B$18+MAX(0,J30-5)*Тарифы!$B$19) -> 19294.8 | AE30: =X30*Тарифы!$B$20 -> 175 | AF30: =BO30*J30*$C$48*IF(E30="Крупногабарит",$C$68,Тарифы!$B$21) -> 73612.8 | AG30: =X30*J30*'Затраты продавца'!$B$12 -> 4771.2 | AH30: =Y30*(Тарифы!$B$18+MAX(0,J30-5)*Тарифы!$B$19)*Тарифы!$B$22 -> 2756.4 | AI30: =ROUNDUP(G30/(1-MIN(0.99,MAX(0,K30+$C$51)))*$C$49,0) -> 7 | AJ30: =ROUNDUP(AI30*$C$50,0) -> 1 | AK30: =AI30-AJ30 -> 6 | AL30: =ROUNDUP(AK30*MIN(0.99,MAX(0,K30+$C$51)),0) -> 1 | AM30: =AK30-AL30 -> 5 | AN30: =AM30*H30 -> 274950 | AO30: =AM30*I30 -> 159000 | AP30: =AN30*N30 -> 30244.5 | AQ30: =AN30*Тарифы!$B$32 -> 4124.25 | AR30: =AK30*(Тарифы!$B$25+MAX(0,J30-5)*Тарифы!$B$26) -> 16538.4 | AS30: =AK30*Тарифы!$B$27 -> 150 | AT30: =BP30*J30*$C$48*'Затраты продавца'!$B$5 -> 22083.84 | AU30: =AK30*('Затраты продавца'!$B$6+'Затраты продавца'!$B$7) -> 420 | AV30: =AK30*Тарифы!$B$24 -> 60 | AW30: =AL30*((Тарифы!$B$25+MAX(0,J30-5)*Тарифы!$B$26)*Тарифы!$B$28+'Затраты продавца'!$B$9+(1-'Затраты продавца'!$B$10)*I30*$C$55) -> 7626.4 | AX30: =AJ30*Тарифы!$B$29 -> 150 | AY30: =AK30*J30/1000 -> 1.63584 | AZ30: =IF(S30="FBO",G30,IF(S30="FBS",AM30,0)) -> 5 | BA30: =IF(S30="FBO",X30,IF(S30="FBS",AK30,0)) -> 6 | BB30: =IF(S30="FBO",Z30,IF(S30="FBS",AN30,0)) -> 274950 | BC30: =IF(S30="FBO",AA30,IF(S30="FBS",AO30,0)) -> 159000 | BD30: =IF(S30="FBO",AB30,IF(S30="FBS",AP30,0)) -> 30244.5 | BE30: =IF(S30="FBO",AC30,IF(S30="FBS",AQ30,0)) -> 4124.25 | BF30: =IF(S30="FBO",AD30,IF(S30="FBS",AR30,0)) -> 16538.4 | BG30: =IF(S30="FBO",AE30,IF(S30="FBS",AS30,0)) -> 150 | BH30: =IF(S30="FBO",AF30,IF(S30="FBS",AT30,0)) -> 22083.84 | BI30: =IF(S30="FBO",AG30,0) -> 0 | BJ30: =IF(S30="FBS",AU30,0) -> 420 | BK30: =IF(S30="FBS",AV30,0) -> 60 | BL30: =IF(S30="FBO",AH30,IF(S30="FBS",AW30,0)) -> 7626.4 | BM30: =IF(S30="FBS",AX30,0) -> 150 | BN30: =Y30*I30*(1-'Затраты продавца'!$B$10)*$C$55 -> 4770 | BO30: =ROUNDUP(X30*L30/$C$48,0) -> 18 | BP30: =ROUNDUP(AI30*L30*$C$54/$C$48,0) -> 18 | BQ30: =IF(S30="FBO",BO30,IF(S30="FBS",BP30,0)) -> 18
B31: =HYPERLINK("#'SKU'!A28","SKU!28") -> SKU!28 | C31: =SKU!A28 -> SM-0027 | D31: =SKU!B28 -> Шведская стенка деревянная | E31: =SKU!C28 -> Крупногабарит | F31: =SKU!L28 -> не представлен | G31: =SKU!K28*IF(SKU!L28="не представлен",$C$52,1) -> 10 | H31: =SKU!D28 -> 15990 | I31: =SKU!E28 -> 8700 | J31: =SKU!I28 -> 123.904 | K31: =SKU!N28 -> 0.05 | L31: =IF(ISNUMBER(SKU!M28),SKU!M28,$C$53) -> 75.361847 | M31: =VLOOKUP(E31,$B$58:$D$63,2,FALSE()) -> 0.12 | N31: =VLOOKUP(E31,$B$58:$D$63,3,FALSE()) -> 0.11 | O31: =Z31-SUM(AA31:AF31)-AH31-BN31 -> -17534.66 | P31: =AN31-SUM(AO31:AX31) -> 11377.696 | Q31: =IF(MAX(O31,P31)<0,"Пауза",IF(P31>O31,"FBS","FBO")) -> FBS | R31: Авто | S31: =IF(R31="Авто",Q31,R31) -> FBS | T31: =IF(S31="FBO",O31,IF(S31="FBS",P31,0)) -> 11377.696 | U31: =IF(S31="FBS",AK31,0) -> 9 | V31: =IF(S31="FBS",AY31,0) -> 1.115136 | X31: =ROUNDUP(G31/(1-K31),0) -> 11 | Y31: =X31-G31 -> 1 | Z31: =G31*H31 -> 159900 | AA31: =G31*I31 -> 87000 | AB31: =Z31*M31 -> 19188 | AC31: =Z31*Тарифы!$B$32 -> 2398.5 | AD31: =X31*(Тарифы!$B$18+MAX(0,J31-5)*Тарифы!$B$19) -> 13959.44 | AE31: =X31*Тарифы!$B$20 -> 275 | AF31: =BO31*J31*$C$48*IF(E31="Крупногабарит",$C$68,Тарифы!$B$21) -> 52039.68 | AG31: =X31*J31*'Затраты продавца'!$B$12 -> 3407.36 | AH31: =Y31*(Тарифы!$B$18+MAX(0,J31-5)*Тарифы!$B$19)*Тарифы!$B$22 -> 1269.04 | AI31: =ROUNDUP(G31/(1-MIN(0.99,MAX(0,K31+$C$51)))*$C$49,0) -> 11 | AJ31: =ROUNDUP(AI31*$C$50,0) -> 2 | AK31: =AI31-AJ31 -> 9 | AL31: =ROUNDUP(AK31*MIN(0.99,MAX(0,K31+$C$51)),0) -> 1 | AM31: =AK31-AL31 -> 8 | AN31: =AM31*H31 -> 127920 | AO31: =AM31*I31 -> 69600 | AP31: =AN31*N31 -> 14071.2 | AQ31: =AN31*Тарифы!$B$32 -> 1918.8 | AR31: =AK31*(Тарифы!$B$25+MAX(0,J31-5)*Тарифы!$B$26) -> 11421.36 | AS31: =AK31*Тарифы!$B$27 -> 225 | AT31: =BP31*J31*$C$48*'Затраты продавца'!$B$5 -> 15611.904 | AU31: =AK31*('Затраты продавца'!$B$6+'Затраты продавца'!$B$7) -> 630 | AV31: =AK31*Тарифы!$B$24 -> 90 | AW31: =AL31*((Тарифы!$B$25+MAX(0,J31-5)*Тарифы!$B$26)*Тарифы!$B$28+'Затраты продавца'!$B$9+(1-'Затраты продавца'!$B$10)*I31*$C$55) -> 2674.04 | AX31: =AJ31*Тарифы!$B$29 -> 300 | AY31: =AK31*J31/1000 -> 1.115136 | AZ31: =IF(S31="FBO",G31,IF(S31="FBS",AM31,0)) -> 8 | BA31: =IF(S31="FBO",X31,IF(S31="FBS",AK31,0)) -> 9 | BB31: =IF(S31="FBO",Z31,IF(S31="FBS",AN31,0)) -> 127920 | BC31: =IF(S31="FBO",AA31,IF(S31="FBS",AO31,0)) -> 69600 | BD31: =IF(S31="FBO",AB31,IF(S31="FBS",AP31,0)) -> 14071.2 | BE31: =IF(S31="FBO",AC31,IF(S31="FBS",AQ31,0)) -> 1918.8 | BF31: =IF(S31="FBO",AD31,IF(S31="FBS",AR31,0)) -> 11421.36 | BG31: =IF(S31="FBO",AE31,IF(S31="FBS",AS31,0)) -> 225 | BH31: =IF(S31="FBO",AF31,IF(S31="FBS",AT31,0)) -> 15611.904 | BI31: =IF(S31="FBO",AG31,0) -> 0 | BJ31: =IF(S31="FBS",AU31,0) -> 630 | BK31: =IF(S31="FBS",AV31,0) -> 90 | BL31: =IF(S31="FBO",AH31,IF(S31="FBS",AW31,0)) -> 2674.04 | BM31: =IF(S31="FBS",AX31,0) -> 300 | BN31: =Y31*I31*(1-'Затраты продавца'!$B$10)*$C$55 -> 1305 | BO31: =ROUNDUP(X31*L31/$C$48,0) -> 28 | BP31: =ROUNDUP(AI31*L31*$C$54/$C$48,0) -> 28 | BQ31: =IF(S31="FBO",BO31,IF(S31="FBS",BP31,0)) -> 28
B32: =HYPERLINK("#'SKU'!A29","SKU!29") -> SKU!29 | C32: =SKU!A29 -> SM-0028 | D32: =SKU!B29 -> Ласты тренировочные | E32: =SKU!C29 -> Фитнес | F32: =SKU!L29 -> не представлен | G32: =SKU!K29*IF(SKU!L29="не представлен",$C$52,1) -> 25 | H32: =SKU!D29 -> 1990 | I32: =SKU!E29 -> 790 | J32: =SKU!I29 -> 8.448 | K32: =SKU!N29 -> 0.07 | L32: =IF(ISNUMBER(SKU!M29),SKU!M29,$C$53) -> 75.361847 | M32: =VLOOKUP(E32,$B$58:$D$63,2,FALSE()) -> 0.15 | N32: =VLOOKUP(E32,$B$58:$D$63,3,FALSE()) -> 0.14 | O32: =Z32-SUM(AA32:AF32)-AH32-BN32 -> 9804.066 | P32: =AN32-SUM(AO32:AX32) -> 10645.532 | Q32: =IF(MAX(O32,P32)<0,"Пауза",IF(P32>O32,"FBS","FBO")) -> FBS | R32: Авто | S32: =IF(R32="Авто",Q32,R32) -> FBS | T32: =IF(S32="FBO",O32,IF(S32="FBS",P32,0)) -> 10645.532 | U32: =IF(S32="FBS",AK32,0) -> 24 | V32: =IF(S32="FBS",AY32,0) -> 0.202752 | X32: =ROUNDUP(G32/(1-K32),0) -> 27 | Y32: =X32-G32 -> 2 | Z32: =G32*H32 -> 49750 | AA32: =G32*I32 -> 19750 | AB32: =Z32*M32 -> 7462.5 | AC32: =Z32*Тарифы!$B$32 -> 746.25 | AD32: =X32*(Тарифы!$B$18+MAX(0,J32-5)*Тарифы!$B$19) -> 3090.96 | AE32: =X32*Тарифы!$B$20 -> 675 | AF32: =BO32*J32*$C$48*IF(E32="Крупногабарит",$C$68,Тарифы!$B$21) -> 7755.264 | AG32: =X32*J32*'Затраты продавца'!$B$12 -> 570.24 | AH32: =Y32*(Тарифы!$B$18+MAX(0,J32-5)*Тарифы!$B$19)*Тарифы!$B$22 -> 228.96 | AI32: =ROUNDUP(G32/(1-MIN(0.99,MAX(0,K32+$C$51)))*$C$49,0) -> 27 | AJ32: =ROUNDUP(AI32*$C$50,0) -> 3 | AK32: =AI32-AJ32 -> 24 | AL32: =ROUNDUP(AK32*MIN(0.99,MAX(0,K32+$C$51)),0) -> 2 | AM32: =AK32-AL32 -> 22 | AN32: =AM32*H32 -> 43780 | AO32: =AM32*I32 -> 17380 | AP32: =AN32*N32 -> 6129.2 | AQ32: =AN32*Тарифы!$B$32 -> 656.7 | AR32: =AK32*(Тарифы!$B$25+MAX(0,J32-5)*Тарифы!$B$26) -> 2747.52 | AS32: =AK32*Тарифы!$B$27 -> 600 | AT32: =BP32*J32*$C$48*'Затраты продавца'!$B$5 -> 2585.088 | AU32: =AK32*('Затраты продавца'!$B$6+'Затраты продавца'!$B$7) -> 1680 | AV32: =AK32*Тарифы!$B$24 -> 240 | AW32: =AL32*((Тарифы!$B$25+MAX(0,J32-5)*Тарифы!$B$26)*Тарифы!$B$28+'Затраты продавца'!$B$9+(1-'Затраты продавца'!$B$10)*I32*$C$55) -> 665.96 | AX32: =AJ32*Тарифы!$B$29 -> 450 | AY32: =AK32*J32/1000 -> 0.202752 | AZ32: =IF(S32="FBO",G32,IF(S32="FBS",AM32,0)) -> 22 | BA32: =IF(S32="FBO",X32,IF(S32="FBS",AK32,0)) -> 24 | BB32: =IF(S32="FBO",Z32,IF(S32="FBS",AN32,0)) -> 43780 | BC32: =IF(S32="FBO",AA32,IF(S32="FBS",AO32,0)) -> 17380 | BD32: =IF(S32="FBO",AB32,IF(S32="FBS",AP32,0)) -> 6129.2 | BE32: =IF(S32="FBO",AC32,IF(S32="FBS",AQ32,0)) -> 656.7 | BF32: =IF(S32="FBO",AD32,IF(S32="FBS",AR32,0)) -> 2747.52 | BG32: =IF(S32="FBO",AE32,IF(S32="FBS",AS32,0)) -> 600 | BH32: =IF(S32="FBO",AF32,IF(S32="FBS",AT32,0)) -> 2585.088 | BI32: =IF(S32="FBO",AG32,0) -> 0 | BJ32: =IF(S32="FBS",AU32,0) -> 1680 | BK32: =IF(S32="FBS",AV32,0) -> 240 | BL32: =IF(S32="FBO",AH32,IF(S32="FBS",AW32,0)) -> 665.96 | BM32: =IF(S32="FBS",AX32,0) -> 450 | BN32: =Y32*I32*(1-'Затраты продавца'!$B$10)*$C$55 -> 237 | BO32: =ROUNDUP(X32*L32/$C$48,0) -> 68 | BP32: =ROUNDUP(AI32*L32*$C$54/$C$48,0) -> 68 | BQ32: =IF(S32="FBO",BO32,IF(S32="FBS",BP32,0)) -> 68
B33: =HYPERLINK("#'SKU'!A30","SKU!30") -> SKU!30 | C33: =SKU!A30 -> SM-0029 | D33: =SKU!B30 -> Очки для плавания стартовые | E33: =SKU!C30 -> Аксессуары | F33: =SKU!L30 -> не представлен | G33: =SKU!K30*IF(SKU!L30="не представлен",$C$52,1) -> 40 | H33: =SKU!D30 -> 2490 | I33: =SKU!E30 -> 880 | J33: =SKU!I30 -> 0.63 | K33: =SKU!N30 -> 0.05 | L33: =IF(ISNUMBER(SKU!M30),SKU!M30,$C$53) -> 75.361847 | M33: =VLOOKUP(E33,$B$58:$D$63,2,FALSE()) -> 0.18 | N33: =VLOOKUP(E33,$B$58:$D$63,3,FALSE()) -> 0.17 | O33: =Z33-SUM(AA33:AF33)-AH33-BN33 -> 38899.955 | P33: =AN33-SUM(AO33:AX33) -> 32663.585 | Q33: =IF(MAX(O33,P33)<0,"Пауза",IF(P33>O33,"FBS","FBO")) -> FBO | R33: Авто | S33: =IF(R33="Авто",Q33,R33) -> FBO | T33: =IF(S33="FBO",O33,IF(S33="FBS",P33,0)) -> 38899.955 | U33: =IF(S33="FBS",AK33,0) -> 0 | V33: =IF(S33="FBS",AY33,0) -> 0 | X33: =ROUNDUP(G33/(1-K33),0) -> 43 | Y33: =X33-G33 -> 3 | Z33: =G33*H33 -> 99600 | AA33: =G33*I33 -> 35200 | AB33: =Z33*M33 -> 17928 | AC33: =Z33*Тарифы!$B$32 -> 1494 | AD33: =X33*(Тарифы!$B$18+MAX(0,J33-5)*Тарифы!$B$19) -> 3440 | AE33: =X33*Тарифы!$B$20 -> 1075 | AF33: =BO33*J33*$C$48*IF(E33="Крупногабарит",$C$68,Тарифы!$B$21) -> 927.045 | AG33: =X33*J33*'Затраты продавца'!$B$12 -> 67.725 | AH33: =Y33*(Тарифы!$B$18+MAX(0,J33-5)*Тарифы!$B$19)*Тарифы!$B$22 -> 240 | AI33: =ROUNDUP(G33/(1-MIN(0.99,MAX(0,K33+$C$51)))*$C$49,0) -> 43 | AJ33: =ROUNDUP(AI33*$C$50,0) -> 5 | AK33: =AI33-AJ33 -> 38 | AL33: =ROUNDUP(AK33*MIN(0.99,MAX(0,K33+$C$51)),0) -> 2 | AM33: =AK33-AL33 -> 36 | AN33: =AM33*H33 -> 89640 | AO33: =AM33*I33 -> 31680 | AP33: =AN33*N33 -> 15238.8 | AQ33: =AN33*Тарифы!$B$32 -> 1344.6 | AR33: =AK33*(Тарифы!$B$25+MAX(0,J33-5)*Тарифы!$B$26) -> 3040 | AS33: =AK33*Тарифы!$B$27 -> 950 | AT33: =BP33*J33*$C$48*'Затраты продавца'!$B$5 -> 309.015 | AU33: =AK33*('Затраты продавца'!$B$6+'Затраты продавца'!$B$7) -> 2660 | AV33: =AK33*Тарифы!$B$24 -> 380 | AW33: =AL33*((Тарифы!$B$25+MAX(0,J33-5)*Тарифы!$B$26)*Тарифы!$B$28+'Затраты продавца'!$B$9+(1-'Затраты продавца'!$B$10)*I33*$C$55) -> 624 | AX33: =AJ33*Тарифы!$B$29 -> 750 | AY33: =AK33*J33/1000 -> 0.02394 | AZ33: =IF(S33="FBO",G33,IF(S33="FBS",AM33,0)) -> 40 | BA33: =IF(S33="FBO",X33,IF(S33="FBS",AK33,0)) -> 43 | BB33: =IF(S33="FBO",Z33,IF(S33="FBS",AN33,0)) -> 99600 | BC33: =IF(S33="FBO",AA33,IF(S33="FBS",AO33,0)) -> 35200 | BD33: =IF(S33="FBO",AB33,IF(S33="FBS",AP33,0)) -> 17928 | BE33: =IF(S33="FBO",AC33,IF(S33="FBS",AQ33,0)) -> 1494 | BF33: =IF(S33="FBO",AD33,IF(S33="FBS",AR33,0)) -> 3440 | BG33: =IF(S33="FBO",AE33,IF(S33="FBS",AS33,0)) -> 1075 | BH33: =IF(S33="FBO",AF33,IF(S33="FBS",AT33,0)) -> 927.045 | BI33: =IF(S33="FBO",AG33,0) -> 67.725 | BJ33: =IF(S33="FBS",AU33,0) -> 0 | BK33: =IF(S33="FBS",AV33,0) -> 0 | BL33: =IF(S33="FBO",AH33,IF(S33="FBS",AW33,0)) -> 240 | BM33: =IF(S33="FBS",AX33,0) -> 0 | BN33: =Y33*I33*(1-'Затраты продавца'!$B$10)*$C$55 -> 396 | BO33: =ROUNDUP(X33*L33/$C$48,0) -> 109 | BP33: =ROUNDUP(AI33*L33*$C$54/$C$48,0) -> 109 | BQ33: =IF(S33="FBO",BO33,IF(S33="FBS",BP33,0)) -> 109
B34: =HYPERLINK("#'SKU'!A31","SKU!31") -> SKU!31 | C34: =SKU!A31 -> SM-0030 | D34: =SKU!B31 -> Перчатки боксёрские 14 oz | E34: =SKU!C31 -> Фитнес | F34: =SKU!L31 -> не представлен | G34: =SKU!K31*IF(SKU!L31="не представлен",$C$52,1) -> 30 | H34: =SKU!D31 -> 3490 | I34: =SKU!E31 -> 1520 | J34: =SKU!I31 -> 9.1 | K34: =SKU!N31 -> 0.06 | L34: =IF(ISNUMBER(SKU!M31),SKU!M31,$C$53) -> 75.361847 | M34: =VLOOKUP(E34,$B$58:$D$63,2,FALSE()) -> 0.15 | N34: =VLOOKUP(E34,$B$58:$D$63,3,FALSE()) -> 0.14 | O34: =Z34-SUM(AA34:AF34)-AH34-BN34 -> 26503.65 | P34: =AN34-SUM(AO34:AX34) -> 26012.35 | Q34: =IF(MAX(O34,P34)<0,"Пауза",IF(P34>O34,"FBS","FBO")) -> FBO | R34: Авто | S34: =IF(R34="Авто",Q34,R34) -> FBO | T34: =IF(S34="FBO",O34,IF(S34="FBS",P34,0)) -> 26503.65 | U34: =IF(S34="FBS",AK34,0) -> 0 | V34: =IF(S34="FBS",AY34,0) -> 0 | X34: =ROUNDUP(G34/(1-K34),0) -> 32 | Y34: =X34-G34 -> 2 | Z34: =G34*H34 -> 104700 | AA34: =G34*I34 -> 45600 | AB34: =Z34*M34 -> 15705 | AC34: =Z34*Тарифы!$B$32 -> 1570.5 | AD34: =X34*(Тарифы!$B$18+MAX(0,J34-5)*Тарифы!$B$19) -> 3872 | AE34: =X34*Тарифы!$B$20 -> 800 | AF34: =BO34*J34*$C$48*IF(E34="Крупногабарит",$C$68,Тарифы!$B$21) -> 9950.85 | AG34: =X34*J34*'Затраты продавца'!$B$12 -> 728 | AH34: =Y34*(Тарифы!$B$18+MAX(0,J34-5)*Тарифы!$B$19)*Тарифы!$B$22 -> 242 | AI34: =ROUNDUP(G34/(1-MIN(0.99,MAX(0,K34+$C$51)))*$C$49,0) -> 32 | AJ34: =ROUNDUP(AI34*$C$50,0) -> 4 | AK34: =AI34-AJ34 -> 28 | AL34: =ROUNDUP(AK34*MIN(0.99,MAX(0,K34+$C$51)),0) -> 2 | AM34: =AK34-AL34 -> 26 | AN34: =AM34*H34 -> 90740 | AO34: =AM34*I34 -> 39520 | AP34: =AN34*N34 -> 12703.6 | AQ34: =AN34*Тарифы!$B$32 -> 1361.1 | AR34: =AK34*(Тарифы!$B$25+MAX(0,J34-5)*Тарифы!$B$26) -> 3388 | AS34: =AK34*Тарифы!$B$27 -> 700 | AT34: =BP34*J34*$C$48*'Затраты продавца'!$B$5 -> 3316.95 | AU34: =AK34*('Затраты продавца'!$B$6+'Затраты продавца'!$B$7) -> 1960 | AV34: =AK34*Тарифы!$B$24 -> 280 | AW34: =AL34*((Тарифы!$B$25+MAX(0,J34-5)*Тарифы!$B$26)*Тарифы!$B$28+'Затраты продавца'!$B$9+(1-'Затраты продавца'!$B$10)*I34*$C$55) -> 898 | AX34: =AJ34*Тарифы!$B$29 -> 600 | AY34: =AK34*J34/1000 -> 0.2548 | AZ34: =IF(S34="FBO",G34,IF(S34="FBS",AM34,0)) -> 30 | BA34: =IF(S34="FBO",X34,IF(S34="FBS",AK34,0)) -> 32 | BB34: =IF(S34="FBO",Z34,IF(S34="FBS",AN34,0)) -> 104700 | BC34: =IF(S34="FBO",AA34,IF(S34="FBS",AO34,0)) -> 45600 | BD34: =IF(S34="FBO",AB34,IF(S34="FBS",AP34,0)) -> 15705 | BE34: =IF(S34="FBO",AC34,IF(S34="FBS",AQ34,0)) -> 1570.5 | BF34: =IF(S34="FBO",AD34,IF(S34="FBS",AR34,0)) -> 3872 | BG34: =IF(S34="FBO",AE34,IF(S34="FBS",AS34,0)) -> 800 | BH34: =IF(S34="FBO",AF34,IF(S34="FBS",AT34,0)) -> 9950.85 | BI34: =IF(S34="FBO",AG34,0) -> 728 | BJ34: =IF(S34="FBS",AU34,0) -> 0 | BK34: =IF(S34="FBS",AV34,0) -> 0 | BL34: =IF(S34="FBO",AH34,IF(S34="FBS",AW34,0)) -> 242 | BM34: =IF(S34="FBS",AX34,0) -> 0 | BN34: =Y34*I34*(1-'Затраты продавца'!$B$10)*$C$55 -> 456 | BO34: =ROUNDUP(X34*L34/$C$48,0) -> 81 | BP34: =ROUNDUP(AI34*L34*$C$54/$C$48,0) -> 81 | BQ34: =IF(S34="FBO",BO34,IF(S34="FBS",BP34,0)) -> 81
B35: =HYPERLINK("#'SKU'!A32","SKU!32") -> SKU!32 | C35: =SKU!A32 -> SM-0031 | D35: =SKU!B32 -> Шлем горнолыжный | E35: =SKU!C32 -> Аксессуары | F35: =SKU!L32 -> не представлен | G35: =SKU!K32*IF(SKU!L32="не представлен",$C$52,1) -> 15 | H35: =SKU!D32 -> 4990 | I35: =SKU!E32 -> 2250 | J35: =SKU!I32 -> 18 | K35: =SKU!N32 -> 0.09 | L35: =IF(ISNUMBER(SKU!M32),SKU!M32,$C$53) -> 75.361847 | M35: =VLOOKUP(E35,$B$58:$D$63,2,FALSE()) -> 0.18 | N35: =VLOOKUP(E35,$B$58:$D$63,3,FALSE()) -> 0.17 | O35: =Z35-SUM(AA35:AF35)-AH35-BN35 -> 10965.25 | P35: =AN35-SUM(AO35:AX35) -> 13816.05 | Q35: =IF(MAX(O35,P35)<0,"Пауза",IF(P35>O35,"FBS","FBO")) -> FBS | R35: Авто | S35: =IF(R35="Авто",Q35,R35) -> FBS | T35: =IF(S35="FBO",O35,IF(S35="FBS",P35,0)) -> 13816.05 | U35: =IF(S35="FBS",AK35,0) -> 15 | V35: =IF(S35="FBS",AY35,0) -> 0.27 | X35: =ROUNDUP(G35/(1-K35),0) -> 17 | Y35: =X35-G35 -> 2 | Z35: =G35*H35 -> 74850 | AA35: =G35*I35 -> 33750 | AB35: =Z35*M35 -> 13473 | AC35: =Z35*Тарифы!$B$32 -> 1122.75 | AD35: =X35*(Тарифы!$B$18+MAX(0,J35-5)*Тарифы!$B$19) -> 3570 | AE35: =X35*Тарифы!$B$20 -> 425 | AF35: =BO35*J35*$C$48*IF(E35="Крупногабарит",$C$68,Тарифы!$B$21) -> 10449 | AG35: =X35*J35*'Затраты продавца'!$B$12 -> 765 | AH35: =Y35*(Тарифы!$B$18+MAX(0,J35-5)*Тарифы!$B$19)*Тарифы!$B$22 -> 420 | AI35: =ROUNDUP(G35/(1-MIN(0.99,MAX(0,K35+$C$51)))*$C$49,0) -> 17 | AJ35: =ROUNDUP(AI35*$C$50,0) -> 2 | AK35: =AI35-AJ35 -> 15 | AL35: =ROUNDUP(AK35*MIN(0.99,MAX(0,K35+$C$51)),0) -> 2 | AM35: =AK35-AL35 -> 13 | AN35: =AM35*H35 -> 64870 | AO35: =AM35*I35 -> 29250 | AP35: =AN35*N35 -> 11027.9 | AQ35: =AN35*Тарифы!$B$32 -> 973.05 | AR35: =AK35*(Тарифы!$B$25+MAX(0,J35-5)*Тарифы!$B$26) -> 3150 | AS35: =AK35*Тарифы!$B$27 -> 375 | AT35: =BP35*J35*$C$48*'Затраты продавца'!$B$5 -> 3483 | AU35: =AK35*('Затраты продавца'!$B$6+'Затраты продавца'!$B$7) -> 1050 | AV35: =AK35*Тарифы!$B$24 -> 150 | AW35: =AL35*((Тарифы!$B$25+MAX(0,J35-5)*Тарифы!$B$26)*Тарифы!$B$28+'Затраты продавца'!$B$9+(1-'Затраты продавца'!$B$10)*I35*$C$55) -> 1295 | AX35: =AJ35*Тарифы!$B$29 -> 300 | AY35: =AK35*J35/1000 -> 0.27 | AZ35: =IF(S35="FBO",G35,IF(S35="FBS",AM35,0)) -> 13 | BA35: =IF(S35="FBO",X35,IF(S35="FBS",AK35,0)) -> 15 | BB35: =IF(S35="FBO",Z35,IF(S35="FBS",AN35,0)) -> 64870 | BC35: =IF(S35="FBO",AA35,IF(S35="FBS",AO35,0)) -> 29250 | BD35: =IF(S35="FBO",AB35,IF(S35="FBS",AP35,0)) -> 11027.9 | BE35: =IF(S35="FBO",AC35,IF(S35="FBS",AQ35,0)) -> 973.05 | BF35: =IF(S35="FBO",AD35,IF(S35="FBS",AR35,0)) -> 3150 | BG35: =IF(S35="FBO",AE35,IF(S35="FBS",AS35,0)) -> 375 | BH35: =IF(S35="FBO",AF35,IF(S35="FBS",AT35,0)) -> 3483 | BI35: =IF(S35="FBO",AG35,0) -> 0 | BJ35: =IF(S35="FBS",AU35,0) -> 1050 | BK35: =IF(S35="FBS",AV35,0) -> 150 | BL35: =IF(S35="FBO",AH35,IF(S35="FBS",AW35,0)) -> 1295 | BM35: =IF(S35="FBS",AX35,0) -> 300 | BN35: =Y35*I35*(1-'Затраты продавца'!$B$10)*$C$55 -> 675 | BO35: =ROUNDUP(X35*L35/$C$48,0) -> 43 | BP35: =ROUNDUP(AI35*L35*$C$54/$C$48,0) -> 43 | BQ35: =IF(S35="FBO",BO35,IF(S35="FBS",BP35,0)) -> 43
B36: =HYPERLINK("#'SKU'!A33","SKU!33") -> SKU!33 | C36: =SKU!A33 -> SM-0032 | D36: =SKU!B33 -> Крепления для сноуборда | E36: =SKU!C33 -> Аксессуары | F36: =SKU!L33 -> не представлен | G36: =SKU!K33*IF(SKU!L33="не представлен",$C$52,1) -> 10 | H36: =SKU!D33 -> 8990 | I36: =SKU!E33 -> 4280 | J36: =SKU!I33 -> 14.56 | K36: =SKU!N33 -> 0.07 | L36: =IF(ISNUMBER(SKU!M33),SKU!M33,$C$53) -> 75.361847 | M36: =VLOOKUP(E36,$B$58:$D$63,2,FALSE()) -> 0.18 | N36: =VLOOKUP(E36,$B$58:$D$63,3,FALSE()) -> 0.17 | O36: =Z36-SUM(AA36:AF36)-AH36-BN36 -> 21041.62 | P36: =AN36-SUM(AO36:AX36) -> 18797.24 | Q36: =IF(MAX(O36,P36)<0,"Пауза",IF(P36>O36,"FBS","FBO")) -> FBO | R36: Авто | S36: =IF(R36="Авто",Q36,R36) -> FBO | T36: =IF(S36="FBO",O36,IF(S36="FBS",P36,0)) -> 21041.62 | U36: =IF(S36="FBS",AK36,0) -> 0 | V36: =IF(S36="FBS",AY36,0) -> 0 | X36: =ROUNDUP(G36/(1-K36),0) -> 11 | Y36: =X36-G36 -> 1 | Z36: =G36*H36 -> 89900 | AA36: =G36*I36 -> 42800 | AB36: =Z36*M36 -> 16182 | AC36: =Z36*Тарифы!$B$32 -> 1348.5 | AD36: =X36*(Тарифы!$B$18+MAX(0,J36-5)*Тарифы!$B$19) -> 1931.6 | AE36: =X36*Тарифы!$B$20 -> 275 | AF36: =BO36*J36*$C$48*IF(E36="Крупногабарит",$C$68,Тарифы!$B$21) -> 5503.68 | AG36: =X36*J36*'Затраты продавца'!$B$12 -> 400.4 | AH36: =Y36*(Тарифы!$B$18+MAX(0,J36-5)*Тарифы!$B$19)*Тарифы!$B$22 -> 175.6 | AI36: =ROUNDUP(G36/(1-MIN(0.99,MAX(0,K36+$C$51)))*$C$49,0) -> 11 | AJ36: =ROUNDUP(AI36*$C$50,0) -> 2 | AK36: =AI36-AJ36 -> 9 | AL36: =ROUNDUP(AK36*MIN(0.99,MAX(0,K36+$C$51)),0) -> 1 | AM36: =AK36-AL36 -> 8 | AN36: =AM36*H36 -> 71920 | AO36: =AM36*I36 -> 34240 | AP36: =AN36*N36 -> 12226.4 | AQ36: =AN36*Тарифы!$B$32 -> 1078.8 | AR36: =AK36*(Тарифы!$B$25+MAX(0,J36-5)*Тарифы!$B$26) -> 1580.4 | AS36: =AK36*Тарифы!$B$27 -> 225 | AT36: =BP36*J36*$C$48*'Затраты продавца'!$B$5 -> 1834.56 | AU36: =AK36*('Затраты продавца'!$B$6+'Затраты продавца'!$B$7) -> 630 | AV36: =AK36*Тарифы!$B$24 -> 90 | AW36: =AL36*((Тарифы!$B$25+MAX(0,J36-5)*Тарифы!$B$26)*Тарифы!$B$28+'Затраты продавца'!$B$9+(1-'Затраты продавца'!$B$10)*I36*$C$55) -> 917.6 | AX36: =AJ36*Тарифы!$B$29 -> 300 | AY36: =AK36*J36/1000 -> 0.13104 | AZ36: =IF(S36="FBO",G36,IF(S36="FBS",AM36,0)) -> 10 | BA36: =IF(S36="FBO",X36,IF(S36="FBS",AK36,0)) -> 11 | BB36: =IF(S36="FBO",Z36,IF(S36="FBS",AN36,0)) -> 89900 | BC36: =IF(S36="FBO",AA36,IF(S36="FBS",AO36,0)) -> 42800 | BD36: =IF(S36="FBO",AB36,IF(S36="FBS",AP36,0)) -> 16182 | BE36: =IF(S36="FBO",AC36,IF(S36="FBS",AQ36,0)) -> 1348.5 | BF36: =IF(S36="FBO",AD36,IF(S36="FBS",AR36,0)) -> 1931.6 | BG36: =IF(S36="FBO",AE36,IF(S36="FBS",AS36,0)) -> 275 | BH36: =IF(S36="FBO",AF36,IF(S36="FBS",AT36,0)) -> 5503.68 | BI36: =IF(S36="FBO",AG36,0) -> 400.4 | BJ36: =IF(S36="FBS",AU36,0) -> 0 | BK36: =IF(S36="FBS",AV36,0) -> 0 | BL36: =IF(S36="FBO",AH36,IF(S36="FBS",AW36,0)) -> 175.6 | BM36: =IF(S36="FBS",AX36,0) -> 0 | BN36: =Y36*I36*(1-'Затраты продавца'!$B$10)*$C$55 -> 642 | BO36: =ROUNDUP(X36*L36/$C$48,0) -> 28 | BP36: =ROUNDUP(AI36*L36*$C$54/$C$48,0) -> 28 | BQ36: =IF(S36="FBO",BO36,IF(S36="FBS",BP36,0)) -> 28
B37: =HYPERLINK("#'SKU'!A34","SKU!34") -> SKU!34 | C37: =SKU!A34 -> SM-0033 | D37: =SKU!B34 -> Бутылка спортивная 0,7 л | E37: =SKU!C34 -> Аксессуары | F37: =SKU!L34 -> FBO | G37: =SKU!K34*IF(SKU!L34="не представлен",$C$52,1) -> 520 | H37: =SKU!D34 -> 690 | I37: =SKU!E34 -> 210 | J37: =SKU!I34 -> 1.664 | K37: =SKU!N34 -> 0.02 | L37: =IF(ISNUMBER(SKU!M34),SKU!M34,$C$53) -> 92.494763 | M37: =VLOOKUP(E37,$B$58:$D$63,2,FALSE()) -> 0.18 | N37: =VLOOKUP(E37,$B$58:$D$63,3,FALSE()) -> 0.17 | O37: =Z37-SUM(AA37:AF37)-AH37-BN37 -> 85856.468 | P37: =AN37-SUM(AO37:AX37) -> 53822.106 | Q37: =IF(MAX(O37,P37)<0,"Пауза",IF(P37>O37,"FBS","FBO")) -> FBO | R37: Авто | S37: =IF(R37="Авто",Q37,R37) -> FBO | T37: =IF(S37="FBO",O37,IF(S37="FBS",P37,0)) -> 85856.468 | U37: =IF(S37="FBS",AK37,0) -> 0 | V37: =IF(S37="FBS",AY37,0) -> 0 | X37: =ROUNDUP(G37/(1-K37),0) -> 531 | Y37: =X37-G37 -> 11 | Z37: =G37*H37 -> 358800 | AA37: =G37*I37 -> 109200 | AB37: =Z37*M37 -> 64584 | AC37: =Z37*Тарифы!$B$32 -> 5382 | AD37: =X37*(Тарифы!$B$18+MAX(0,J37-5)*Тарифы!$B$19) -> 42480 | AE37: =X37*Тарифы!$B$20 -> 13275 | AF37: =BO37*J37*$C$48*IF(E37="Крупногабарит",$C$68,Тарифы!$B$21) -> 36796.032 | AG37: =X37*J37*'Затраты продавца'!$B$12 -> 2208.96 | AH37: =Y37*(Тарифы!$B$18+MAX(0,J37-5)*Тарифы!$B$19)*Тарифы!$B$22 -> 880 | AI37: =ROUNDUP(G37/(1-MIN(0.99,MAX(0,K37+$C$51)))*$C$49,0) -> 531 | AJ37: =ROUNDUP(AI37*$C$50,0) -> 54 | AK37: =AI37-AJ37 -> 477 | AL37: =ROUNDUP(AK37*MIN(0.99,MAX(0,K37+$C$51)),0) -> 10 | AM37: =AK37-AL37 -> 467 | AN37: =AM37*H37 -> 322230 | AO37: =AM37*I37 -> 98070 | AP37: =AN37*N37 -> 54779.1 | AQ37: =AN37*Тарифы!$B$32 -> 4833.45 | AR37: =AK37*(Тарифы!$B$25+MAX(0,J37-5)*Тарифы!$B$26) -> 38160 | AS37: =AK37*Тарифы!$B$27 -> 11925 | AT37: =BP37*J37*$C$48*'Затраты продавца'!$B$5 -> 12265.344 | AU37: =AK37*('Затраты продавца'!$B$6+'Затраты продавца'!$B$7) -> 33390 | AV37: =AK37*Тарифы!$B$24 -> 4770 | AW37: =AL37*((Тарифы!$B$25+MAX(0,J37-5)*Тарифы!$B$26)*Тарифы!$B$28+'Затраты продавца'!$B$9+(1-'Затраты продавца'!$B$10)*I37*$C$55) -> 2115 | AX37: =AJ37*Тарифы!$B$29 -> 8100 | AY37: =AK37*J37/1000 -> 0.793728 | AZ37: =IF(S37="FBO",G37,IF(S37="FBS",AM37,0)) -> 520 | BA37: =IF(S37="FBO",X37,IF(S37="FBS",AK37,0)) -> 531 | BB37: =IF(S37="FBO",Z37,IF(S37="FBS",AN37,0)) -> 358800 | BC37: =IF(S37="FBO",AA37,IF(S37="FBS",AO37,0)) -> 109200 | BD37: =IF(S37="FBO",AB37,IF(S37="FBS",AP37,0)) -> 64584 | BE37: =IF(S37="FBO",AC37,IF(S37="FBS",AQ37,0)) -> 5382 | BF37: =IF(S37="FBO",AD37,IF(S37="FBS",AR37,0)) -> 42480 | BG37: =IF(S37="FBO",AE37,IF(S37="FBS",AS37,0)) -> 13275 | BH37: =IF(S37="FBO",AF37,IF(S37="FBS",AT37,0)) -> 36796.032 | BI37: =IF(S37="FBO",AG37,0) -> 2208.96 | BJ37: =IF(S37="FBS",AU37,0) -> 0 | BK37: =IF(S37="FBS",AV37,0) -> 0 | BL37: =IF(S37="FBO",AH37,IF(S37="FBS",AW37,0)) -> 880 | BM37: =IF(S37="FBS",AX37,0) -> 0 | BN37: =Y37*I37*(1-'Затраты продавца'!$B$10)*$C$55 -> 346.5 | BO37: =ROUNDUP(X37*L37/$C$48,0) -> 1638 | BP37: =ROUNDUP(AI37*L37*$C$54/$C$48,0) -> 1638 | BQ37: =IF(S37="FBO",BO37,IF(S37="FBS",BP37,0)) -> 1638
B38: =HYPERLINK("#'SKU'!A35","SKU!35") -> SKU!35 | C38: =SKU!A35 -> SM-0034 | D38: =SKU!B35 -> Носки спортивные (3 пары) | E38: =SKU!C35 -> Аксессуары | F38: =SKU!L35 -> FBO | G38: =SKU!K35*IF(SKU!L35="не представлен",$C$52,1) -> 700 | H38: =SKU!D35 -> 590 | I38: =SKU!E35 -> 175 | J38: =SKU!I35 -> 0.96 | K38: =SKU!N35 -> 0.03 | L38: =IF(ISNUMBER(SKU!M35),SKU!M35,$C$53) -> 59.783911 | M38: =VLOOKUP(E38,$B$58:$D$63,2,FALSE()) -> 0.18 | N38: =VLOOKUP(E38,$B$58:$D$63,3,FALSE()) -> 0.17 | O38: =Z38-SUM(AA38:AF38)-AH38-BN38 -> 113168.06 | P38: =AN38-SUM(AO38:AX38) -> 51023.17 | Q38: =IF(MAX(O38,P38)<0,"Пауза",IF(P38>O38,"FBS","FBO")) -> FBO | R38: Авто | S38: =IF(R38="Авто",Q38,R38) -> FBO | T38: =IF(S38="FBO",O38,IF(S38="FBS",P38,0)) -> 113168.06 | U38: =IF(S38="FBS",AK38,0) -> 0 | V38: =IF(S38="FBS",AY38,0) -> 0 | X38: =ROUNDUP(G38/(1-K38),0) -> 722 | Y38: =X38-G38 -> 22 | Z38: =G38*H38 -> 413000 | AA38: =G38*I38 -> 122500 | AB38: =Z38*M38 -> 74340 | AC38: =Z38*Тарифы!$B$32 -> 6195 | AD38: =X38*(Тарифы!$B$18+MAX(0,J38-5)*Тарифы!$B$19) -> 57760 | AE38: =X38*Тарифы!$B$20 -> 18050 | AF38: =BO38*J38*$C$48*IF(E38="Крупногабарит",$C$68,Тарифы!$B$21) -> 18649.44 | AG38: =X38*J38*'Затраты продавца'!$B$12 -> 1732.8 | AH38: =Y38*(Тарифы!$B$18+MAX(0,J38-5)*Тарифы!$B$19)*Тарифы!$B$22 -> 1760 | AI38: =ROUNDUP(G38/(1-MIN(0.99,MAX(0,K38+$C$51)))*$C$49,0) -> 722 | AJ38: =ROUNDUP(AI38*$C$50,0) -> 73 | AK38: =AI38-AJ38 -> 649 | AL38: =ROUNDUP(AK38*MIN(0.99,MAX(0,K38+$C$51)),0) -> 20 | AM38: =AK38-AL38 -> 629 | AN38: =AM38*H38 -> 371110 | AO38: =AM38*I38 -> 110075 | AP38: =AN38*N38 -> 63088.7 | AQ38: =AN38*Тарифы!$B$32 -> 5566.65 | AR38: =AK38*(Тарифы!$B$25+MAX(0,J38-5)*Тарифы!$B$26) -> 51920 | AS38: =AK38*Тарифы!$B$27 -> 16225 | AT38: =BP38*J38*$C$48*'Затраты продавца'!$B$5 -> 6216.48 | AU38: =AK38*('Затраты продавца'!$B$6+'Затраты продавца'!$B$7) -> 45430 | AV38: =AK38*Тарифы!$B$24 -> 6490 | AW38: =AL38*((Тарифы!$B$25+MAX(0,J38-5)*Тарифы!$B$26)*Тарифы!$B$28+'Затраты продавца'!$B$9+(1-'Затраты продавца'!$B$10)*I38*$C$55) -> 4125 | AX38: =AJ38*Тарифы!$B$29 -> 10950 | AY38: =AK38*J38/1000 -> 0.62304 | AZ38: =IF(S38="FBO",G38,IF(S38="FBS",AM38,0)) -> 700 | BA38: =IF(S38="FBO",X38,IF(S38="FBS",AK38,0)) -> 722 | BB38: =IF(S38="FBO",Z38,IF(S38="FBS",AN38,0)) -> 413000 | BC38: =IF(S38="FBO",AA38,IF(S38="FBS",AO38,0)) -> 122500 | BD38: =IF(S38="FBO",AB38,IF(S38="FBS",AP38,0)) -> 74340 | BE38: =IF(S38="FBO",AC38,IF(S38="FBS",AQ38,0)) -> 6195 | BF38: =IF(S38="FBO",AD38,IF(S38="FBS",AR38,0)) -> 57760 | BG38: =IF(S38="FBO",AE38,IF(S38="FBS",AS38,0)) -> 18050 | BH38: =IF(S38="FBO",AF38,IF(S38="FBS",AT38,0)) -> 18649.44 | BI38: =IF(S38="FBO",AG38,0) -> 1732.8 | BJ38: =IF(S38="FBS",AU38,0) -> 0 | BK38: =IF(S38="FBS",AV38,0) -> 0 | BL38: =IF(S38="FBO",AH38,IF(S38="FBS",AW38,0)) -> 1760 | BM38: =IF(S38="FBS",AX38,0) -> 0 | BN38: =Y38*I38*(1-'Затраты продавца'!$B$10)*$C$55 -> 577.5 | BO38: =ROUNDUP(X38*L38/$C$48,0) -> 1439 | BP38: =ROUNDUP(AI38*L38*$C$54/$C$48,0) -> 1439 | BQ38: =IF(S38="FBO",BO38,IF(S38="FBS",BP38,0)) -> 1439
B39: =HYPERLINK("#'SKU'!A36","SKU!36") -> SKU!36 | C39: =SKU!A36 -> SM-0035 | D39: =SKU!B36 -> Перчатки для фитнеса | E39: =SKU!C36 -> Аксессуары | F39: =SKU!L36 -> FBO | G39: =SKU!K36*IF(SKU!L36="не представлен",$C$52,1) -> 260 | H39: =SKU!D36 -> 690 | I39: =SKU!E36 -> 225 | J39: =SKU!I36 -> 0.648 | K39: =SKU!N36 -> 0.05 | L39: =IF(ISNUMBER(SKU!M36),SKU!M36,$C$53) -> 77.854435 | M39: =VLOOKUP(E39,$B$58:$D$63,2,FALSE()) -> 0.18 | N39: =VLOOKUP(E39,$B$58:$D$63,3,FALSE()) -> 0.17 | O39: =Z39-SUM(AA39:AF39)-AH39-BN39 -> 49325.924 | P39: =AN39-SUM(AO39:AX39) -> 24037.608 | Q39: =IF(MAX(O39,P39)<0,"Пауза",IF(P39>O39,"FBS","FBO")) -> FBO | R39: Авто | S39: =IF(R39="Авто",Q39,R39) -> FBO | T39: =IF(S39="FBO",O39,IF(S39="FBS",P39,0)) -> 49325.924 | U39: =IF(S39="FBS",AK39,0) -> 0 | V39: =IF(S39="FBS",AY39,0) -> 0 | X39: =ROUNDUP(G39/(1-K39),0) -> 274 | Y39: =X39-G39 -> 14 | Z39: =G39*H39 -> 179400 | AA39: =G39*I39 -> 58500 | AB39: =Z39*M39 -> 32292 | AC39: =Z39*Тарифы!$B$32 -> 2691 | AD39: =X39*(Тарифы!$B$18+MAX(0,J39-5)*Тарифы!$B$19) -> 21920 | AE39: =X39*Тарифы!$B$20 -> 6850 | AF39: =BO39*J39*$C$48*IF(E39="Крупногабарит",$C$68,Тарифы!$B$21) -> 6228.576 | AG39: =X39*J39*'Затраты продавца'!$B$12 -> 443.88 | AH39: =Y39*(Тарифы!$B$18+MAX(0,J39-5)*Тарифы!$B$19)*Тарифы!$B$22 -> 1120 | AI39: =ROUNDUP(G39/(1-MIN(0.99,MAX(0,K39+$C$51)))*$C$49,0) -> 274 | AJ39: =ROUNDUP(AI39*$C$50,0) -> 28 | AK39: =AI39-AJ39 -> 246 | AL39: =ROUNDUP(AK39*MIN(0.99,MAX(0,K39+$C$51)),0) -> 13 | AM39: =AK39-AL39 -> 233 | AN39: =AM39*H39 -> 160770 | AO39: =AM39*I39 -> 52425 | AP39: =AN39*N39 -> 27330.9 | AQ39: =AN39*Тарифы!$B$32 -> 2411.55 | AR39: =AK39*(Тарифы!$B$25+MAX(0,J39-5)*Тарифы!$B$26) -> 19680 | AS39: =AK39*Тарифы!$B$27 -> 6150 | AT39: =BP39*J39*$C$48*'Затраты продавца'!$B$5 -> 2076.192 | AU39: =AK39*('Затраты продавца'!$B$6+'Затраты продавца'!$B$7) -> 17220 | AV39: =AK39*Тарифы!$B$24 -> 2460 | AW39: =AL39*((Тарифы!$B$25+MAX(0,J39-5)*Тарифы!$B$26)*Тарифы!$B$28+'Затраты продавца'!$B$9+(1-'Затраты продавца'!$B$10)*I39*$C$55) -> 2778.75 | AX39: =AJ39*Тарифы!$B$29 -> 4200 | AY39: =AK39*J39/1000 -> 0.159408 | AZ39: =IF(S39="FBO",G39,IF(S39="FBS",AM39,0)) -> 260 | BA39: =IF(S39="FBO",X39,IF(S39="FBS",AK39,0)) -> 274 | BB39: =IF(S39="FBO",Z39,IF(S39="FBS",AN39,0)) -> 179400 | BC39: =IF(S39="FBO",AA39,IF(S39="FBS",AO39,0)) -> 58500 | BD39: =IF(S39="FBO",AB39,IF(S39="FBS",AP39,0)) -> 32292 | BE39: =IF(S39="FBO",AC39,IF(S39="FBS",AQ39,0)) -> 2691 | BF39: =IF(S39="FBO",AD39,IF(S39="FBS",AR39,0)) -> 21920 | BG39: =IF(S39="FBO",AE39,IF(S39="FBS",AS39,0)) -> 6850 | BH39: =IF(S39="FBO",AF39,IF(S39="FBS",AT39,0)) -> 6228.576 | BI39: =IF(S39="FBO",AG39,0) -> 443.88 | BJ39: =IF(S39="FBS",AU39,0) -> 0 | BK39: =IF(S39="FBS",AV39,0) -> 0 | BL39: =IF(S39="FBO",AH39,IF(S39="FBS",AW39,0)) -> 1120 | BM39: =IF(S39="FBS",AX39,0) -> 0 | BN39: =Y39*I39*(1-'Затраты продавца'!$B$10)*$C$55 -> 472.5 | BO39: =ROUNDUP(X39*L39/$C$48,0) -> 712 | BP39: =ROUNDUP(AI39*L39*$C$54/$C$48,0) -> 712 | BQ39: =IF(S39="FBO",BO39,IF(S39="FBS",BP39,0)) -> 712
B40: =HYPERLINK("#'SKU'!A37","SKU!37") -> SKU!37 | C40: =SKU!A37 -> SM-0036 | D40: =SKU!B37 -> Рюкзак городской 22 л | E40: =SKU!C37 -> Аксессуары | F40: =SKU!L37 -> FBO | G40: =SKU!K37*IF(SKU!L37="не представлен",$C$52,1) -> 190 | H40: =SKU!D37 -> 2990 | I40: =SKU!E37 -> 1180 | J40: =SKU!I37 -> 21.6 | K40: =SKU!N37 -> 0.08 | L40: =IF(ISNUMBER(SKU!M37),SKU!M37,$C$53) -> 61.07212 | M40: =VLOOKUP(E40,$B$58:$D$63,2,FALSE()) -> 0.18 | N40: =VLOOKUP(E40,$B$58:$D$63,3,FALSE()) -> 0.17 | O40: =Z40-SUM(AA40:AF40)-AH40-BN40 -> 46777.3 | P40: =AN40-SUM(AO40:AX40) -> 97621.95 | Q40: =IF(MAX(O40,P40)<0,"Пауза",IF(P40>O40,"FBS","FBO")) -> FBS | R40: Авто | S40: =IF(R40="Авто",Q40,R40) -> FBS | T40: =IF(S40="FBO",O40,IF(S40="FBS",P40,0)) -> 97621.95 | U40: =IF(S40="FBS",AK40,0) -> 186 | V40: =IF(S40="FBS",AY40,0) -> 4.0176 | X40: =ROUNDUP(G40/(1-K40),0) -> 207 | Y40: =X40-G40 -> 17 | Z40: =G40*H40 -> 568100 | AA40: =G40*I40 -> 224200 | AB40: =Z40*M40 -> 102258 | AC40: =Z40*Тарифы!$B$32 -> 8521.5 | AD40: =X40*(Тарифы!$B$18+MAX(0,J40-5)*Тарифы!$B$19) -> 50922 | AE40: =X40*Тарифы!$B$20 -> 5175 | AF40: =BO40*J40*$C$48*IF(E40="Крупногабарит",$C$68,Тарифы!$B$21) -> 123055.2 | AG40: =X40*J40*'Затраты продавца'!$B$12 -> 11178 | AH40: =Y40*(Тарифы!$B$18+MAX(0,J40-5)*Тарифы!$B$19)*Тарифы!$B$22 -> 4182 | AI40: =ROUNDUP(G40/(1-MIN(0.99,MAX(0,K40+$C$51)))*$C$49,0) -> 207 | AJ40: =ROUNDUP(AI40*$C$50,0) -> 21 | AK40: =AI40-AJ40 -> 186 | AL40: =ROUNDUP(AK40*MIN(0.99,MAX(0,K40+$C$51)),0) -> 15 | AM40: =AK40-AL40 -> 171 | AN40: =AM40*H40 -> 511290 | AO40: =AM40*I40 -> 201780 | AP40: =AN40*N40 -> 86919.3 | AQ40: =AN40*Тарифы!$B$32 -> 7669.35 | AR40: =AK40*(Тарифы!$B$25+MAX(0,J40-5)*Тарифы!$B$26) -> 45756 | AS40: =AK40*Тарифы!$B$27 -> 4650 | AT40: =BP40*J40*$C$48*'Затраты продавца'!$B$5 -> 41018.4 | AU40: =AK40*('Затраты продавца'!$B$6+'Затраты продавца'!$B$7) -> 13020 | AV40: =AK40*Тарифы!$B$24 -> 1860 | AW40: =AL40*((Тарифы!$B$25+MAX(0,J40-5)*Тарифы!$B$26)*Тарифы!$B$28+'Затраты продавца'!$B$9+(1-'Затраты продавца'!$B$10)*I40*$C$55) -> 7845 | AX40: =AJ40*Тарифы!$B$29 -> 3150 | AY40: =AK40*J40/1000 -> 4.0176 | AZ40: =IF(S40="FBO",G40,IF(S40="FBS",AM40,0)) -> 171 | BA40: =IF(S40="FBO",X40,IF(S40="FBS",AK40,0)) -> 186 | BB40: =IF(S40="FBO",Z40,IF(S40="FBS",AN40,0)) -> 511290 | BC40: =IF(S40="FBO",AA40,IF(S40="FBS",AO40,0)) -> 201780 | BD40: =IF(S40="FBO",AB40,IF(S40="FBS",AP40,0)) -> 86919.3 | BE40: =IF(S40="FBO",AC40,IF(S40="FBS",AQ40,0)) -> 7669.35 | BF40: =IF(S40="FBO",AD40,IF(S40="FBS",AR40,0)) -> 45756 | BG40: =IF(S40="FBO",AE40,IF(S40="FBS",AS40,0)) -> 4650 | BH40: =IF(S40="FBO",AF40,IF(S40="FBS",AT40,0)) -> 41018.4 | BI40: =IF(S40="FBO",AG40,0) -> 0 | BJ40: =IF(S40="FBS",AU40,0) -> 13020 | BK40: =IF(S40="FBS",AV40,0) -> 1860 | BL40: =IF(S40="FBO",AH40,IF(S40="FBS",AW40,0)) -> 7845 | BM40: =IF(S40="FBS",AX40,0) -> 3150 | BN40: =Y40*I40*(1-'Затраты продавца'!$B$10)*$C$55 -> 3009 | BO40: =ROUNDUP(X40*L40/$C$48,0) -> 422 | BP40: =ROUNDUP(AI40*L40*$C$54/$C$48,0) -> 422 | BQ40: =IF(S40="FBO",BO40,IF(S40="FBS",BP40,0)) -> 422
B41: =HYPERLINK("#'SKU'!A38","SKU!38") -> SKU!38 | C41: =SKU!A38 -> SM-0037 | D41: =SKU!B38 -> Сумка спортивная 45 л | E41: =SKU!C38 -> Аксессуары | F41: =SKU!L38 -> FBO | G41: =SKU!K38*IF(SKU!L38="не представлен",$C$52,1) -> 140 | H41: =SKU!D38 -> 2490 | I41: =SKU!E38 -> 990 | J41: =SKU!I38 -> 43.12 | K41: =SKU!N38 -> 0.07 | L41: =IF(ISNUMBER(SKU!M38),SKU!M38,$C$53) -> 69.625232 | M41: =VLOOKUP(E41,$B$58:$D$63,2,FALSE()) -> 0.18 | N41: =VLOOKUP(E41,$B$58:$D$63,3,FALSE()) -> 0.17 | O41: =Z41-SUM(AA41:AF41)-AH41-BN41 -> -142424.02 | P41: =AN41-SUM(AO41:AX41) -> -24123.29 | Q41: =IF(MAX(O41,P41)<0,"Пауза",IF(P41>O41,"FBS","FBO")) -> Пауза | R41: Авто | S41: =IF(R41="Авто",Q41,R41) -> Пауза | T41: =IF(S41="FBO",O41,IF(S41="FBS",P41,0)) -> 0 | U41: =IF(S41="FBS",AK41,0) -> 0 | V41: =IF(S41="FBS",AY41,0) -> 0 | X41: =ROUNDUP(G41/(1-K41),0) -> 151 | Y41: =X41-G41 -> 11 | Z41: =G41*H41 -> 348600 | AA41: =G41*I41 -> 138600 | AB41: =Z41*M41 -> 62748 | AC41: =Z41*Тарифы!$B$32 -> 5229 | AD41: =X41*(Тарифы!$B$18+MAX(0,J41-5)*Тарифы!$B$19) -> 69641.2 | AE41: =X41*Тарифы!$B$20 -> 3775 | AF41: =BO41*J41*$C$48*IF(E41="Крупногабарит",$C$68,Тарифы!$B$21) -> 204324.12 | AG41: =X41*J41*'Затраты продавца'!$B$12 -> 16277.8 | AH41: =Y41*(Тарифы!$B$18+MAX(0,J41-5)*Тарифы!$B$19)*Тарифы!$B$22 -> 5073.2 | AI41: =ROUNDUP(G41/(1-MIN(0.99,MAX(0,K41+$C$51)))*$C$49,0) -> 151 | AJ41: =ROUNDUP(AI41*$C$50,0) -> 16 | AK41: =AI41-AJ41 -> 135 | AL41: =ROUNDUP(AK41*MIN(0.99,MAX(0,K41+$C$51)),0) -> 10 | AM41: =AK41-AL41 -> 125 | AN41: =AM41*H41 -> 311250 | AO41: =AM41*I41 -> 123750 | AP41: =AN41*N41 -> 52912.5 | AQ41: =AN41*Тарифы!$B$32 -> 4668.75 | AR41: =AK41*(Тарифы!$B$25+MAX(0,J41-5)*Тарифы!$B$26) -> 62262 | AS41: =AK41*Тарифы!$B$27 -> 3375 | AT41: =BP41*J41*$C$48*'Затраты продавца'!$B$5 -> 68108.04 | AU41: =AK41*('Затраты продавца'!$B$6+'Затраты продавца'!$B$7) -> 9450 | AV41: =AK41*Тарифы!$B$24 -> 1350 | AW41: =AL41*((Тарифы!$B$25+MAX(0,J41-5)*Тарифы!$B$26)*Тарифы!$B$28+'Затраты продавца'!$B$9+(1-'Затраты продавца'!$B$10)*I41*$C$55) -> 7097 | AX41: =AJ41*Тарифы!$B$29 -> 2400 | AY41: =AK41*J41/1000 -> 5.8212 | AZ41: =IF(S41="FBO",G41,IF(S41="FBS",AM41,0)) -> 0 | BA41: =IF(S41="FBO",X41,IF(S41="FBS",AK41,0)) -> 0 | BB41: =IF(S41="FBO",Z41,IF(S41="FBS",AN41,0)) -> 0 | BC41: =IF(S41="FBO",AA41,IF(S41="FBS",AO41,0)) -> 0 | BD41: =IF(S41="FBO",AB41,IF(S41="FBS",AP41,0)) -> 0 | BE41: =IF(S41="FBO",AC41,IF(S41="FBS",AQ41,0)) -> 0 | BF41: =IF(S41="FBO",AD41,IF(S41="FBS",AR41,0)) -> 0 | BG41: =IF(S41="FBO",AE41,IF(S41="FBS",AS41,0)) -> 0 | BH41: =IF(S41="FBO",AF41,IF(S41="FBS",AT41,0)) -> 0 | BI41: =IF(S41="FBO",AG41,0) -> 0 | BJ41: =IF(S41="FBS",AU41,0) -> 0 | BK41: =IF(S41="FBS",AV41,0) -> 0 | BL41: =IF(S41="FBO",AH41,IF(S41="FBS",AW41,0)) -> 0 | BM41: =IF(S41="FBS",AX41,0) -> 0 | BN41: =Y41*I41*(1-'Затраты продавца'!$B$10)*$C$55 -> 1633.5 | BO41: =ROUNDUP(X41*L41/$C$48,0) -> 351 | BP41: =ROUNDUP(AI41*L41*$C$54/$C$48,0) -> 351 | BQ41: =IF(S41="FBO",BO41,IF(S41="FBS",BP41,0)) -> 0
B42: =HYPERLINK("#'SKU'!A39","SKU!39") -> SKU!39 | C42: =SKU!A39 -> SM-0038 | D42: =SKU!B39 -> Мяч футбольный (без накачки) | E42: =SKU!C39 -> Фитнес | F42: =SKU!L39 -> FBO | G42: =SKU!K39*IF(SKU!L39="не представлен",$C$52,1) -> 210 | H42: =SKU!D39 -> 1890 | I42: =SKU!E39 -> 690 | J42: =SKU!I39 -> 6.348 | K42: =SKU!N39 -> 0.03 | L42: =IF(ISNUMBER(SKU!M39),SKU!M39,$C$53) -> 73.412177 | M42: =VLOOKUP(E42,$B$58:$D$63,2,FALSE()) -> 0.15 | N42: =VLOOKUP(E42,$B$58:$D$63,3,FALSE()) -> 0.14 | O42: =Z42-SUM(AA42:AF42)-AH42-BN42 -> 113831.14 | P42: =AN42-SUM(AO42:AX42) -> 112449.86 | Q42: =IF(MAX(O42,P42)<0,"Пауза",IF(P42>O42,"FBS","FBO")) -> FBO | R42: Авто | S42: =IF(R42="Авто",Q42,R42) -> FBO | T42: =IF(S42="FBO",O42,IF(S42="FBS",P42,0)) -> 113831.14 | U42: =IF(S42="FBS",AK42,0) -> 0 | V42: =IF(S42="FBS",AY42,0) -> 0 | X42: =ROUNDUP(G42/(1-K42),0) -> 217 | Y42: =X42-G42 -> 7 | Z42: =G42*H42 -> 396900 | AA42: =G42*I42 -> 144900 | AB42: =Z42*M42 -> 59535 | AC42: =Z42*Тарифы!$B$32 -> 5953.5 | AD42: =X42*(Тарифы!$B$18+MAX(0,J42-5)*Тарифы!$B$19) -> 20285.16 | AE42: =X42*Тарифы!$B$20 -> 5425 | AF42: =BO42*J42*$C$48*IF(E42="Крупногабарит",$C$68,Тарифы!$B$21) -> 45591.336 | AG42: =X42*J42*'Затраты продавца'!$B$12 -> 3443.79 | AH42: =Y42*(Тарифы!$B$18+MAX(0,J42-5)*Тарифы!$B$19)*Тарифы!$B$22 -> 654.36 | AI42: =ROUNDUP(G42/(1-MIN(0.99,MAX(0,K42+$C$51)))*$C$49,0) -> 217 | AJ42: =ROUNDUP(AI42*$C$50,0) -> 22 | AK42: =AI42-AJ42 -> 195 | AL42: =ROUNDUP(AK42*MIN(0.99,MAX(0,K42+$C$51)),0) -> 6 | AM42: =AK42-AL42 -> 189 | AN42: =AM42*H42 -> 357210 | AO42: =AM42*I42 -> 130410 | AP42: =AN42*N42 -> 50009.4 | AQ42: =AN42*Тарифы!$B$32 -> 5358.15 | AR42: =AK42*(Тарифы!$B$25+MAX(0,J42-5)*Тарифы!$B$26) -> 18228.6 | AS42: =AK42*Тарифы!$B$27 -> 4875 | AT42: =BP42*J42*$C$48*'Затраты продавца'!$B$5 -> 15197.112 | AU42: =AK42*('Затраты продавца'!$B$6+'Затраты продавца'!$B$7) -> 13650 | AV42: =AK42*Тарифы!$B$24 -> 1950 | AW42: =AL42*((Тарифы!$B$25+MAX(0,J42-5)*Тарифы!$B$26)*Тарифы!$B$28+'Затраты продавца'!$B$9+(1-'Затраты продавца'!$B$10)*I42*$C$55) -> 1781.88 | AX42: =AJ42*Тарифы!$B$29 -> 3300 | AY42: =AK42*J42/1000 -> 1.23786 | AZ42: =IF(S42="FBO",G42,IF(S42="FBS",AM42,0)) -> 210 | BA42: =IF(S42="FBO",X42,IF(S42="FBS",AK42,0)) -> 217 | BB42: =IF(S42="FBO",Z42,IF(S42="FBS",AN42,0)) -> 396900 | BC42: =IF(S42="FBO",AA42,IF(S42="FBS",AO42,0)) -> 144900 | BD42: =IF(S42="FBO",AB42,IF(S42="FBS",AP42,0)) -> 59535 | BE42: =IF(S42="FBO",AC42,IF(S42="FBS",AQ42,0)) -> 5953.5 | BF42: =IF(S42="FBO",AD42,IF(S42="FBS",AR42,0)) -> 20285.16 | BG42: =IF(S42="FBO",AE42,IF(S42="FBS",AS42,0)) -> 5425 | BH42: =IF(S42="FBO",AF42,IF(S42="FBS",AT42,0)) -> 45591.336 | BI42: =IF(S42="FBO",AG42,0) -> 3443.79 | BJ42: =IF(S42="FBS",AU42,0) -> 0 | BK42: =IF(S42="FBS",AV42,0) -> 0 | BL42: =IF(S42="FBO",AH42,IF(S42="FBS",AW42,0)) -> 654.36 | BM42: =IF(S42="FBS",AX42,0) -> 0 | BN42: =Y42*I42*(1-'Затраты продавца'!$B$10)*$C$55 -> 724.5 | BO42: =ROUNDUP(X42*L42/$C$48,0) -> 532 | BP42: =ROUNDUP(AI42*L42*$C$54/$C$48,0) -> 532 | BQ42: =IF(S42="FBO",BO42,IF(S42="FBS",BP42,0)) -> 532
B43: =HYPERLINK("#'SKU'!A40","SKU!40") -> SKU!40 | C43: =SKU!A40 -> SM-0039 | D43: =SKU!B40 -> Мяч баскетбольный | E43: =SKU!C40 -> Фитнес | F43: =SKU!L40 -> FBO | G43: =SKU!K40*IF(SKU!L40="не представлен",$C$52,1) -> 130 | H43: =SKU!D40 -> 2190 | I43: =SKU!E40 -> 830 | J43: =SKU!I40 -> 8.125 | K43: =SKU!N40 -> 0.04 | L43: =IF(ISNUMBER(SKU!M40),SKU!M40,$C$53) -> 102.70633 | M43: =VLOOKUP(E43,$B$58:$D$63,2,FALSE()) -> 0.15 | N43: =VLOOKUP(E43,$B$58:$D$63,3,FALSE()) -> 0.14 | O43: =Z43-SUM(AA43:AF43)-AH43-BN43 -> 58765.625 | P43: =AN43-SUM(AO43:AX43) -> 72204.975 | Q43: =IF(MAX(O43,P43)<0,"Пауза",IF(P43>O43,"FBS","FBO")) -> FBS | R43: Авто | S43: =IF(R43="Авто",Q43,R43) -> FBS | T43: =IF(S43="FBO",O43,IF(S43="FBS",P43,0)) -> 72204.975 | U43: =IF(S43="FBS",AK43,0) -> 122 | V43: =IF(S43="FBS",AY43,0) -> 0.99125 | X43: =ROUNDUP(G43/(1-K43),0) -> 136 | Y43: =X43-G43 -> 6 | Z43: =G43*H43 -> 284700 | AA43: =G43*I43 -> 107900 | AB43: =Z43*M43 -> 42705 | AC43: =Z43*Тарифы!$B$32 -> 4270.5 | AD43: =X43*(Тарифы!$B$18+MAX(0,J43-5)*Тарифы!$B$19) -> 15130 | AE43: =X43*Тарифы!$B$20 -> 3400 | AF43: =BO43*J43*$C$48*IF(E43="Крупногабарит",$C$68,Тарифы!$B$21) -> 51114.375 | AG43: =X43*J43*'Затраты продавца'!$B$12 -> 2762.5 | AH43: =Y43*(Тарифы!$B$18+MAX(0,J43-5)*Тарифы!$B$19)*Тарифы!$B$22 -> 667.5 | AI43: =ROUNDUP(G43/(1-MIN(0.99,MAX(0,K43+$C$51)))*$C$49,0) -> 136 | AJ43: =ROUNDUP(AI43*$C$50,0) -> 14 | AK43: =AI43-AJ43 -> 122 | AL43: =ROUNDUP(AK43*MIN(0.99,MAX(0,K43+$C$51)),0) -> 5 | AM43: =AK43-AL43 -> 117 | AN43: =AM43*H43 -> 256230 | AO43: =AM43*I43 -> 97110 | AP43: =AN43*N43 -> 35872.2 | AQ43: =AN43*Тарифы!$B$32 -> 3843.45 | AR43: =AK43*(Тарифы!$B$25+MAX(0,J43-5)*Тарифы!$B$26) -> 13572.5 | AS43: =AK43*Тарифы!$B$27 -> 3050 | AT43: =BP43*J43*$C$48*'Затраты продавца'!$B$5 -> 17038.125 | AU43: =AK43*('Затраты продавца'!$B$6+'Затраты продавца'!$B$7) -> 8540 | AV43: =AK43*Тарифы!$B$24 -> 1220 | AW43: =AL43*((Тарифы!$B$25+MAX(0,J43-5)*Тарифы!$B$26)*Тарифы!$B$28+'Затраты продавца'!$B$9+(1-'Затраты продавца'!$B$10)*I43*$C$55) -> 1678.75 | AX43: =AJ43*Тарифы!$B$29 -> 2100 | AY43: =AK43*J43/1000 -> 0.99125 | AZ43: =IF(S43="FBO",G43,IF(S43="FBS",AM43,0)) -> 117 | BA43: =IF(S43="FBO",X43,IF(S43="FBS",AK43,0)) -> 122 | BB43: =IF(S43="FBO",Z43,IF(S43="FBS",AN43,0)) -> 256230 | BC43: =IF(S43="FBO",AA43,IF(S43="FBS",AO43,0)) -> 97110 | BD43: =IF(S43="FBO",AB43,IF(S43="FBS",AP43,0)) -> 35872.2 | BE43: =IF(S43="FBO",AC43,IF(S43="FBS",AQ43,0)) -> 3843.45 | BF43: =IF(S43="FBO",AD43,IF(S43="FBS",AR43,0)) -> 13572.5 | BG43: =IF(S43="FBO",AE43,IF(S43="FBS",AS43,0)) -> 3050 | BH43: =IF(S43="FBO",AF43,IF(S43="FBS",AT43,0)) -> 17038.125 | BI43: =IF(S43="FBO",AG43,0) -> 0 | BJ43: =IF(S43="FBS",AU43,0) -> 8540 | BK43: =IF(S43="FBS",AV43,0) -> 1220 | BL43: =IF(S43="FBO",AH43,IF(S43="FBS",AW43,0)) -> 1678.75 | BM43: =IF(S43="FBS",AX43,0) -> 2100 | BN43: =Y43*I43*(1-'Затраты продавца'!$B$10)*$C$55 -> 747 | BO43: =ROUNDUP(X43*L43/$C$48,0) -> 466 | BP43: =ROUNDUP(AI43*L43*$C$54/$C$48,0) -> 466 | BQ43: =IF(S43="FBO",BO43,IF(S43="FBS",BP43,0)) -> 466
B44: =HYPERLINK("#'SKU'!A41","SKU!41") -> SKU!41 | C44: =SKU!A41 -> SM-0040 | D44: =SKU!B41 -> Ролики раздвижные р. 38–41 | E44: =SKU!C41 -> Обувь | F44: =SKU!L41 -> FBO | G44: =SKU!K41*IF(SKU!L41="не представлен",$C$52,1) -> 45 | H44: =SKU!D41 -> 6990 | I44: =SKU!E41 -> 3250 | J44: =SKU!I41 -> 16.8 | K44: =SKU!N41 -> 0.11 | L44: =IF(ISNUMBER(SKU!M41),SKU!M41,$C$53) -> 97.91727 | M44: =VLOOKUP(E44,$B$58:$D$63,2,FALSE()) -> 0.16 | N44: =VLOOKUP(E44,$B$58:$D$63,3,FALSE()) -> 0.15 | O44: =Z44-SUM(AA44:AF44)-AH44-BN44 -> 59892.15 | P44: =AN44-SUM(AO44:AX44) -> 72378.3 | Q44: =IF(MAX(O44,P44)<0,"Пауза",IF(P44>O44,"FBS","FBO")) -> FBS | R44: Авто | S44: =IF(R44="Авто",Q44,R44) -> FBS | T44: =IF(S44="FBO",O44,IF(S44="FBS",P44,0)) -> 72378.3 | U44: =IF(S44="FBS",AK44,0) -> 45 | V44: =IF(S44="FBS",AY44,0) -> 0.756 | X44: =ROUNDUP(G44/(1-K44),0) -> 51 | Y44: =X44-G44 -> 6 | Z44: =G44*H44 -> 314550 | AA44: =G44*I44 -> 146250 | AB44: =Z44*M44 -> 50328 | AC44: =Z44*Тарифы!$B$32 -> 4718.25 | AD44: =X44*(Тарифы!$B$18+MAX(0,J44-5)*Тарифы!$B$19) -> 10098 | AE44: =X44*Тарифы!$B$20 -> 1275 | AF44: =BO44*J44*$C$48*IF(E44="Крупногабарит",$C$68,Тарифы!$B$21) -> 37875.6 | AG44: =X44*J44*'Затраты продавца'!$B$12 -> 2142 | AH44: =Y44*(Тарифы!$B$18+MAX(0,J44-5)*Тарифы!$B$19)*Тарифы!$B$22 -> 1188 | AI44: =ROUNDUP(G44/(1-MIN(0.99,MAX(0,K44+$C$51)))*$C$49,0) -> 51 | AJ44: =ROUNDUP(AI44*$C$50,0) -> 6 | AK44: =AI44-AJ44 -> 45 | AL44: =ROUNDUP(AK44*MIN(0.99,MAX(0,K44+$C$51)),0) -> 5 | AM44: =AK44-AL44 -> 40 | AN44: =AM44*H44 -> 279600 | AO44: =AM44*I44 -> 130000 | AP44: =AN44*N44 -> 41940 | AQ44: =AN44*Тарифы!$B$32 -> 4194 | AR44: =AK44*(Тарифы!$B$25+MAX(0,J44-5)*Тарифы!$B$26) -> 8910 | AS44: =AK44*Тарифы!$B$27 -> 1125 | AT44: =BP44*J44*$C$48*'Затраты продавца'!$B$5 -> 12625.2 | AU44: =AK44*('Затраты продавца'!$B$6+'Затраты продавца'!$B$7) -> 3150 | AV44: =AK44*Тарифы!$B$24 -> 450 | AW44: =AL44*((Тарифы!$B$25+MAX(0,J44-5)*Тарифы!$B$26)*Тарифы!$B$28+'Затраты продавца'!$B$9+(1-'Затраты продавца'!$B$10)*I44*$C$55) -> 3927.5 | AX44: =AJ44*Тарифы!$B$29 -> 900 | AY44: =AK44*J44/1000 -> 0.756 | AZ44: =IF(S44="FBO",G44,IF(S44="FBS",AM44,0)) -> 40 | BA44: =IF(S44="FBO",X44,IF(S44="FBS",AK44,0)) -> 45 | BB44: =IF(S44="FBO",Z44,IF(S44="FBS",AN44,0)) -> 279600 | BC44: =IF(S44="FBO",AA44,IF(S44="FBS",AO44,0)) -> 130000 | BD44: =IF(S44="FBO",AB44,IF(S44="FBS",AP44,0)) -> 41940 | BE44: =IF(S44="FBO",AC44,IF(S44="FBS",AQ44,0)) -> 4194 | BF44: =IF(S44="FBO",AD44,IF(S44="FBS",AR44,0)) -> 8910 | BG44: =IF(S44="FBO",AE44,IF(S44="FBS",AS44,0)) -> 1125 | BH44: =IF(S44="FBO",AF44,IF(S44="FBS",AT44,0)) -> 12625.2 | BI44: =IF(S44="FBO",AG44,0) -> 0 | BJ44: =IF(S44="FBS",AU44,0) -> 3150 | BK44: =IF(S44="FBS",AV44,0) -> 450 | BL44: =IF(S44="FBO",AH44,IF(S44="FBS",AW44,0)) -> 3927.5 | BM44: =IF(S44="FBS",AX44,0) -> 900 | BN44: =Y44*I44*(1-'Затраты продавца'!$B$10)*$C$55 -> 2925 | BO44: =ROUNDUP(X44*L44/$C$48,0) -> 167 | BP44: =ROUNDUP(AI44*L44*$C$54/$C$48,0) -> 167 | BQ44: =IF(S44="FBO",BO44,IF(S44="FBS",BP44,0)) -> 167
B46: ПАРАМЕТРЫ И СПРАВОЧНИКИ МОДЕЛИ
B47: Параметр модели | C47: Значение | D47: Единица | E47: Источник / основание
B48: Модельный месяц и дней отгрузки | C48: 30 | D48: дней | E48: Равномерный месячный поток
B49: Спрос FBS относительно базы | C49: 1 | D49: множитель | E49: Нейтральная база
B50: Нарушение SLA FBS → отмена продавцом | C50: 0.1 | D50: доля заказов | E50: Рабочее допущение: 90% заказов передаются ≤24 ч; редактируемый sensitivity
B51: Поправка к возвратам FBS | C51: 0 | D51: доля | E51: Нейтральная база
B52: Выполнение прогноза новых SKU | C52: 1 | D52: множитель | E52: =HYPERLINK("#'SKU'!K22","SKU!K22:K33") -> SKU!K22:K33
B53: Оборачиваемость новых SKU | C53: =AVERAGE(SKU!M2:M41) -> 75.361847 | D53: дней | E53: =HYPERLINK("#'SKU'!M2","SKU!M2:M41") -> SKU!M2:M41
B54: Множитель запаса собственного склада | C54: 1 | D54: множитель | E54: Та же оборачиваемость
B55: Потеря невосстановимых возвратов | C55: 1 | D55: доля себестоимости | E55: 15% возвратов списываются полностью
B57: Категория | C57: Комиссия FBO | D57: Комиссия FBS | E57: Источник
B58: Обувь | C58: =Тарифы!B5 -> 0.16 | D58: =Тарифы!B6 -> 0.15 | E58: =HYPERLINK("#'Тарифы'!B5","Тарифы!B5:B6") -> Тарифы!B5:B6
B59: Одежда | C59: =Тарифы!B7 -> 0.17 | D59: =Тарифы!B8 -> 0.16 | E59: =HYPERLINK("#'Тарифы'!B7","Тарифы!B7:B8") -> Тарифы!B7:B8
B60: Фитнес | C60: =Тарифы!B9 -> 0.15 | D60: =Тарифы!B10 -> 0.14 | E60: =HYPERLINK("#'Тарифы'!B9","Тарифы!B9:B10") -> Тарифы!B9:B10
B61: Туризм | C61: =Тарифы!B11 -> 0.15 | D61: =Тарифы!B12 -> 0.14 | E61: =HYPERLINK("#'Тарифы'!B11","Тарифы!B11:B12") -> Тарифы!B11:B12
B62: Крупногабарит | C62: =Тарифы!B13 -> 0.12 | D62: =Тарифы!B14 -> 0.11 | E62: =HYPERLINK("#'Тарифы'!B13","Тарифы!B13:B14") -> Тарифы!B13:B14
B63: Аксессуары | C63: =Тарифы!B15 -> 0.18 | D63: =Тарифы!B16 -> 0.17 | E63: =HYPERLINK("#'Тарифы'!B15","Тарифы!B15:B16") -> Тарифы!B15:B16
B65: Параметр рейса | C65: Значение | D65: Единица | E65: Источник
B66: Вместимость по отправлениям | C66: 250 | D66: шт. | E66: =HYPERLINK("#'Затраты продавца'!B8","Затраты продавца!B8") -> Затраты продавца!B8
B67: Вместимость по объёму | C67: 6 | D67: м³ | E67: =HYPERLINK("#'Затраты продавца'!B8","Затраты продавца!B8") -> Затраты продавца!B8
B68: Хранение КГТ на FBO | C68: 0.5 | D68: руб./л/день | E68: =HYPERLINK("#'Тарифы'!D21","Тарифы!D21") -> Тарифы!D21

Sheet Fulllog 3PL
B2: Fulllog 3PL — тарифы и расчёт услуг
B4: Поток и ввод скидки | F4: Тарифы Fulllog | K4: Параметры
B5: Скидка Fulllog — ВВОД | D5: 0 | F5: Услуга | G5: Ставка | H5: Единица | I5: Источник | K5: Параметр | L5: Значение | M5: Единица | N5: Источник
B6: FBS-отправления, шт. | D6: =SUM(Модель!$U$5:$U$44) -> 1175 | F6: Приёмка | G6: 5 | H6: ₽/шт. | I6: =HYPERLINK("https://fulllog.ru/prices","Fulllog") -> Fulllog | K6: Коэффициент складского объёма | L6: 1.25 | M6: коэффициент | N6: Допущение модели
B7: FBS-возвраты, шт. | D7: =SUMPRODUCT((Модель!$S$5:$S$44="FBS")*Модель!$AL$5:$AL$44) -> 87 | F7: Подбор заказа | G7: 9 | H7: ₽/шт. | I7: =HYPERLINK("https://fulllog.ru/prices","Fulllog") -> Fulllog | K7: Первая миля SM → Fulllog | L7: 2.5 | M7: ₽/л | N7: Допущение до КП
B8: Объём отправлений, м³ | D8: =SUM(Модель!$V$5:$V$44) -> 37.699011 | F8: Нанесение штрихкода | G8: 4 | H8: ₽/шт. | I8: =HYPERLINK("https://fulllog.ru/3pl","Fulllog 3PL") -> Fulllog 3PL
F9: Доставка FBS до Ozon | G9: 25 | H9: ₽/шт. | I9: =HYPERLINK("https://fulllog.ru/fulfillment-ozon","Fulllog для Ozon") -> Fulllog для Ozon
B10: Стоимость услуг с введённой скидкой | F10: Хранение | G10: 89 | H10: ₽/м³/день | I10: =HYPERLINK("https://fulllog.ru/prices","Fulllog") -> Fulllog
B11: Приёмка | D11: =SUM(J25:J64)*(1-$D$5) -> 5875 | F11: Возврат / невыкуп | G11: 58 | H11: ₽/шт. | I11: =HYPERLINK("https://fulllog.ru/fulfillment-ozon","Fulllog для Ozon") -> Fulllog для Ozon
B12: Хранение | D12: =SUM(K25:K64)*(1-$D$5) -> 362833.56 | F12: Минимальный чек | G12: 10000 | H12: ₽/мес. | I12: =HYPERLINK("https://fulllog.ru/company","Fulllog") -> Fulllog
B13: Подбор | D13: =SUM(L25:L64)*(1-$D$5) -> 10575
B14: Упаковка | D14: =SUM(M25:M64)*(1-$D$5) -> 28410 | F14: POF-упаковка
B15: Нанесение штрихкода | D15: =SUM(N25:N64)*(1-$D$5) -> 4700 | F15: Сумма сторон до, см | G15: Ставка | H15: Единица | I15: Источник
B16: Передача заказов в Ozon | D16: =SUM(O25:O64)*(1-$D$5) -> 29375 | F16: 30 | G16: 6 | H16: ₽/шт. | I16: =HYPERLINK("https://fulllog.ru/pereupakovka","Fulllog") -> Fulllog
B17: Обработка возвратов | D17: =SUM(P25:P64)*(1-$D$5) -> 5046 | F17: 50 | G17: 12 | H17: ₽/шт. | I17: =HYPERLINK("https://fulllog.ru/pereupakovka","Fulllog") -> Fulllog
B18: Услуги до минимального чека | D18: =SUM(D11:D17) -> 446814.56 | F18: 70 | G18: 16 | H18: ₽/шт. | I18: =HYPERLINK("https://fulllog.ru/pereupakovka","Fulllog") -> Fulllog
B19: Доплата до минимального чека | D19: =MAX(0,IF(D6>0,G12,0)-D18) -> 0 | F19: 90 | G19: 20 | H19: ₽/шт. | I19: =HYPERLINK("https://fulllog.ru/pereupakovka","Fulllog") -> Fulllog
B20: Итого услуги Fulllog | D20: =SUM(D18:D19) -> 446814.56 | F20: 120 | G20: 26 | H20: ₽/шт. | I20: =HYPERLINK("https://fulllog.ru/pereupakovka","Fulllog") -> Fulllog
B21: База услуг до скидки | D21: =SUM(Q25:Q64) -> 446814.56 | F21: 150 | G21: 32 | H21: ₽/шт. | I21: =HYPERLINK("https://fulllog.ru/pereupakovka","Fulllog") -> Fulllog
F22: >150 | G22: 32 | H22: ₽/шт., допущение | I22: TBD
B24: Артикул | C24: Товар | D24: Схема | E24: Сумма сторон, см | F24: Объём, м³ | G24: FBS-отправления | H24: FBS-возвраты | I24: Дни хранения | J24: Приёмка, ₽ | K24: Хранение, ₽ | L24: Подбор, ₽ | M24: Упаковка, ₽ | N24: Штрихкод, ₽ | O24: Fulllog → Ozon, ₽ | P24: Возвраты: обработка, ₽ | Q24: Услуги до скидки, ₽
B25: =SKU!A2 -> SM-0001 | C25: =SKU!B2 -> Кроссовки беговые мужские | D25: =Модель!S5 -> FBO | E25: =SUM(SKU!F2:H2) -> 66 | F25: =SKU!I2/1000 -> 0.008316 | G25: =Модель!U5 -> 0 | H25: =IF(D25="FBS",Модель!AL5,0) -> 0 | I25: =Модель!L5 -> 66.679446 | J25: =IF(D25="FBS",G25*$G$6,0) -> 0 | K25: =IF(D25="FBS",Модель!BP5*F25*Модель!$C$48*$G$10*$L$6,0) -> 0 | L25: =IF(D25="FBS",G25*$G$7,0) -> 0 | M25: =IF(D25="FBS",G25*IF(E25<=$F$16,$G$16,IF(E25<=$F$17,$G$17,IF(E25<=$F$18,$G$18,IF(E25<=$F$19,$G$19,IF(E25<=$F$20,$G$20,IF(E25<=$F$21,$G$21,$G$22)))))),0) -> 0 | N25: =IF(D25="FBS",G25*$G$8,0) -> 0 | O25: =IF(D25="FBS",G25*$G$9,0) -> 0 | P25: =IF(D25="FBS",H25*$G$11,0) -> 0 | Q25: =SUM(J25:P25) -> 0
B26: =SKU!A3 -> SM-0002 | C26: =SKU!B3 -> Кроссовки трейловые | D26: =Модель!S6 -> FBO | E26: =SUM(SKU!F3:H3) -> 69 | F26: =SKU!I3/1000 -> 0.009724 | G26: =Модель!U6 -> 0 | H26: =IF(D26="FBS",Модель!AL6,0) -> 0 | I26: =Модель!L6 -> 67.064723 | J26: =IF(D26="FBS",G26*$G$6,0) -> 0 | K26: =IF(D26="FBS",Модель!BP6*F26*Модель!$C$48*$G$10*$L$6,0) -> 0 | L26: =IF(D26="FBS",G26*$G$7,0) -> 0 | M26: =IF(D26="FBS",G26*IF(E26<=$F$16,$G$16,IF(E26<=$F$17,$G$17,IF(E26<=$F$18,$G$18,IF(E26<=$F$19,$G$19,IF(E26<=$F$20,$G$20,IF(E26<=$F$21,$G$21,$G$22)))))),0) -> 0 | N26: =IF(D26="FBS",G26*$G$8,0) -> 0 | O26: =IF(D26="FBS",G26*$G$9,0) -> 0 | P26: =IF(D26="FBS",H26*$G$11,0) -> 0 | Q26: =SUM(J26:P26) -> 0
B27: =SKU!A4 -> SM-0003 | C27: =SKU!B4 -> Кеды классические | D27: =Модель!S7 -> FBO | E27: =SUM(SKU!F4:H4) -> 63 | F27: =SKU!I4/1000 -> 0.00704 | G27: =Модель!U7 -> 0 | H27: =IF(D27="FBS",Модель!AL7,0) -> 0 | I27: =Модель!L7 -> 48.031221 | J27: =IF(D27="FBS",G27*$G$6,0) -> 0 | K27: =IF(D27="FBS",Модель!BP7*F27*Модель!$C$48*$G$10*$L$6,0) -> 0 | L27: =IF(D27="FBS",G27*$G$7,0) -> 0 | M27: =IF(D27="FBS",G27*IF(E27<=$F$16,$G$16,IF(E27<=$F$17,$G$17,IF(E27<=$F$18,$G$18,IF(E27<=$F$19,$G$19,IF(E27<=$F$20,$G$20,IF(E27<=$F$21,$G$21,$G$22)))))),0) -> 0 | N27: =IF(D27="FBS",G27*$G$8,0) -> 0 | O27: =IF(D27="FBS",G27*$G$9,0) -> 0 | P27: =IF(D27="FBS",H27*$G$11,0) -> 0 | Q27: =SUM(J27:P27) -> 0
B28: =SKU!A5 -> SM-0004 | C28: =SKU!B5 -> Ботинки треккинговые | D28: =Модель!S8 -> FBS | E28: =SUM(SKU!F5:H5) -> 73 | F28: =SKU!I5/1000 -> 0.01176 | G28: =Модель!U8 -> 91 | H28: =IF(D28="FBS",Модель!AL8,0) -> 15 | I28: =Модель!L8 -> 73.154068 | J28: =IF(D28="FBS",G28*$G$6,0) -> 455 | K28: =IF(D28="FBS",Модель!BP8*F28*Модель!$C$48*$G$10*$L$6,0) -> 9773.001 | L28: =IF(D28="FBS",G28*$G$7,0) -> 819 | M28: =IF(D28="FBS",G28*IF(E28<=$F$16,$G$16,IF(E28<=$F$17,$G$17,IF(E28<=$F$18,$G$18,IF(E28<=$F$19,$G$19,IF(E28<=$F$20,$G$20,IF(E28<=$F$21,$G$21,$G$22)))))),0) -> 1820 | N28: =IF(D28="FBS",G28*$G$8,0) -> 364 | O28: =IF(D28="FBS",G28*$G$9,0) -> 2275 | P28: =IF(D28="FBS",H28*$G$11,0) -> 870 | Q28: =SUM(J28:P28) -> 16376.001
B29: =SKU!A6 -> SM-0005 | C29: =SKU!B6 -> Сланцы пляжные | D29: =Модель!S9 -> FBO | E29: =SUM(SKU!F6:H6) -> 50 | F29: =SKU!I6/1000 -> 0.00336 | G29: =Модель!U9 -> 0 | H29: =IF(D29="FBS",Модель!AL9,0) -> 0 | I29: =Модель!L9 -> 79.611473 | J29: =IF(D29="FBS",G29*$G$6,0) -> 0 | K29: =IF(D29="FBS",Модель!BP9*F29*Модель!$C$48*$G$10*$L$6,0) -> 0 | L29: =IF(D29="FBS",G29*$G$7,0) -> 0 | M29: =IF(D29="FBS",G29*IF(E29<=$F$16,$G$16,IF(E29<=$F$17,$G$17,IF(E29<=$F$18,$G$18,IF(E29<=$F$19,$G$19,IF(E29<=$F$20,$G$20,IF(E29<=$F$21,$G$21,$G$22)))))),0) -> 0 | N29: =IF(D29="FBS",G29*$G$8,0) -> 0 | O29: =IF(D29="FBS",G29*$G$9,0) -> 0 | P29: =IF(D29="FBS",H29*$G$11,0) -> 0 | Q29: =SUM(J29:P29) -> 0
B30: =SKU!A7 -> SM-0006 | C30: =SKU!B7 -> Футболка тренировочная | D30: =Модель!S10 -> FBO | E30: =SUM(SKU!F7:H7) -> 55 | F30: =SKU!I7/1000 -> 0.00198 | G30: =Модель!U10 -> 0 | H30: =IF(D30="FBS",Модель!AL10,0) -> 0 | I30: =Модель!L10 -> 77.881051 | J30: =IF(D30="FBS",G30*$G$6,0) -> 0 | K30: =IF(D30="FBS",Модель!BP10*F30*Модель!$C$48*$G$10*$L$6,0) -> 0 | L30: =IF(D30="FBS",G30*$G$7,0) -> 0 | M30: =IF(D30="FBS",G30*IF(E30<=$F$16,$G$16,IF(E30<=$F$17,$G$17,IF(E30<=$F$18,$G$18,IF(E30<=$F$19,$G$19,IF(E30<=$F$20,$G$20,IF(E30<=$F$21,$G$21,$G$22)))))),0) -> 0 | N30: =IF(D30="FBS",G30*$G$8,0) -> 0 | O30: =IF(D30="FBS",G30*$G$9,0) -> 0 | P30: =IF(D30="FBS",H30*$G$11,0) -> 0 | Q30: =SUM(J30:P30) -> 0
B31: =SKU!A8 -> SM-0007 | C31: =SKU!B8 -> Шорты беговые | D31: =Модель!S11 -> FBO | E31: =SUM(SKU!F8:H8) -> 52 | F31: =SKU!I8/1000 -> 0.00224 | G31: =Модель!U11 -> 0 | H31: =IF(D31="FBS",Модель!AL11,0) -> 0 | I31: =Модель!L11 -> 82.191663 | J31: =IF(D31="FBS",G31*$G$6,0) -> 0 | K31: =IF(D31="FBS",Модель!BP11*F31*Модель!$C$48*$G$10*$L$6,0) -> 0 | L31: =IF(D31="FBS",G31*$G$7,0) -> 0 | M31: =IF(D31="FBS",G31*IF(E31<=$F$16,$G$16,IF(E31<=$F$17,$G$17,IF(E31<=$F$18,$G$18,IF(E31<=$F$19,$G$19,IF(E31<=$F$20,$G$20,IF(E31<=$F$21,$G$21,$G$22)))))),0) -> 0 | N31: =IF(D31="FBS",G31*$G$8,0) -> 0 | O31: =IF(D31="FBS",G31*$G$9,0) -> 0 | P31: =IF(D31="FBS",H31*$G$11,0) -> 0 | Q31: =SUM(J31:P31) -> 0
B32: =SKU!A9 -> SM-0008 | C32: =SKU!B9 -> Ветровка для бега | D32: =Модель!S12 -> FBO | E32: =SUM(SKU!F9:H9) -> 66 | F32: =SKU!I9/1000 -> 0.00525 | G32: =Модель!U12 -> 0 | H32: =IF(D32="FBS",Модель!AL12,0) -> 0 | I32: =Модель!L12 -> 79.712035 | J32: =IF(D32="FBS",G32*$G$6,0) -> 0 | K32: =IF(D32="FBS",Модель!BP12*F32*Модель!$C$48*$G$10*$L$6,0) -> 0 | L32: =IF(D32="FBS",G32*$G$7,0) -> 0 | M32: =IF(D32="FBS",G32*IF(E32<=$F$16,$G$16,IF(E32<=$F$17,$G$17,IF(E32<=$F$18,$G$18,IF(E32<=$F$19,$G$19,IF(E32<=$F$20,$G$20,IF(E32<=$F$21,$G$21,$G$22)))))),0) -> 0 | N32: =IF(D32="FBS",G32*$G$8,0) -> 0 | O32: =IF(D32="FBS",G32*$G$9,0) -> 0 | P32: =IF(D32="FBS",H32*$G$11,0) -> 0 | Q32: =SUM(J32:P32) -> 0
B33: =SKU!A10 -> SM-0009 | C33: =SKU!B10 -> Куртка зимняя утеплённая | D33: =Модель!S13 -> FBS | E33: =SUM(SKU!F10:H10) -> 95 | F33: =SKU!I10/1000 -> 0.023625 | G33: =Модель!U13 -> 20 | H33: =IF(D33="FBS",Модель!AL13,0) -> 4 | I33: =Модель!L13 -> 140 | J33: =IF(D33="FBS",G33*$G$6,0) -> 100 | K33: =IF(D33="FBS",Модель!BP13*F33*Модель!$C$48*$G$10*$L$6,0) -> 8515.6313 | L33: =IF(D33="FBS",G33*$G$7,0) -> 180 | M33: =IF(D33="FBS",G33*IF(E33<=$F$16,$G$16,IF(E33<=$F$17,$G$17,IF(E33<=$F$18,$G$18,IF(E33<=$F$19,$G$19,IF(E33<=$F$20,$G$20,IF(E33<=$F$21,$G$21,$G$22)))))),0) -> 520 | N33: =IF(D33="FBS",G33*$G$8,0) -> 80 | O33: =IF(D33="FBS",G33*$G$9,0) -> 500 | P33: =IF(D33="FBS",H33*$G$11,0) -> 232 | Q33: =SUM(J33:P33) -> 10127.631
B34: =SKU!A11 -> SM-0010 | C34: =SKU!B11 -> Леггинсы женские | D34: =Модель!S14 -> FBO | E34: =SUM(SKU!F11:H11) -> 52 | F34: =SKU!I11/1000 -> 0.00224 | G34: =Модель!U14 -> 0 | H34: =IF(D34="FBS",Модель!AL14,0) -> 0 | I34: =Модель!L14 -> 77.397201 | J34: =IF(D34="FBS",G34*$G$6,0) -> 0 | K34: =IF(D34="FBS",Модель!BP14*F34*Модель!$C$48*$G$10*$L$6,0) -> 0 | L34: =IF(D34="FBS",G34*$G$7,0) -> 0 | M34: =IF(D34="FBS",G34*IF(E34<=$F$16,$G$16,IF(E34<=$F$17,$G$17,IF(E34<=$F$18,$G$18,IF(E34<=$F$19,$G$19,IF(E34<=$F$20,$G$20,IF(E34<=$F$21,$G$21,$G$22)))))),0) -> 0 | N34: =IF(D34="FBS",G34*$G$8,0) -> 0 | O34: =IF(D34="FBS",G34*$G$9,0) -> 0 | P34: =IF(D34="FBS",H34*$G$11,0) -> 0 | Q34: =SUM(J34:P34) -> 0
B35: =SKU!A12 -> SM-0011 | C35: =SKU!B12 -> Гантели разборные 2×10 кг | D35: =Модель!S15 -> FBS | E35: =SUM(SKU!F12:H12) -> 85 | F35: =SKU!I12/1000 -> 0.016875 | G35: =Модель!U15 -> 55 | H35: =IF(D35="FBS",Модель!AL15,0) -> 2 | I35: =Модель!L15 -> 81.658982 | J35: =IF(D35="FBS",G35*$G$6,0) -> 275 | K35: =IF(D35="FBS",Модель!BP15*F35*Модель!$C$48*$G$10*$L$6,0) -> 9518.1328 | L35: =IF(D35="FBS",G35*$G$7,0) -> 495 | M35: =IF(D35="FBS",G35*IF(E35<=$F$16,$G$16,IF(E35<=$F$17,$G$17,IF(E35<=$F$18,$G$18,IF(E35<=$F$19,$G$19,IF(E35<=$F$20,$G$20,IF(E35<=$F$21,$G$21,$G$22)))))),0) -> 1100 | N35: =IF(D35="FBS",G35*$G$8,0) -> 220 | O35: =IF(D35="FBS",G35*$G$9,0) -> 1375 | P35: =IF(D35="FBS",H35*$G$11,0) -> 116 | Q35: =SUM(J35:P35) -> 13099.133
B36: =SKU!A13 -> SM-0012 | C36: =SKU!B13 -> Гиря чугунная 16 кг | D36: =Модель!S16 -> FBS | E36: =SUM(SKU!F13:H13) -> 67 | F36: =SKU!I13/1000 -> 0.011 | G36: =Модель!U16 -> 41 | H36: =IF(D36="FBS",Модель!AL16,0) -> 1 | I36: =Модель!L16 -> 60.716212 | J36: =IF(D36="FBS",G36*$G$6,0) -> 205 | K36: =IF(D36="FBS",Модель!BP16*F36*Модель!$C$48*$G$10*$L$6,0) -> 3450.975 | L36: =IF(D36="FBS",G36*$G$7,0) -> 369 | M36: =IF(D36="FBS",G36*IF(E36<=$F$16,$G$16,IF(E36<=$F$17,$G$17,IF(E36<=$F$18,$G$18,IF(E36<=$F$19,$G$19,IF(E36<=$F$20,$G$20,IF(E36<=$F$21,$G$21,$G$22)))))),0) -> 656 | N36: =IF(D36="FBS",G36*$G$8,0) -> 164 | O36: =IF(D36="FBS",G36*$G$9,0) -> 1025 | P36: =IF(D36="FBS",H36*$G$11,0) -> 58 | Q36: =SUM(J36:P36) -> 5927.975
... B64: =SKU!A41 -> SM-0040 | C64: =SKU!B41 -> Ролики раздвижные р. 38–41 | D64: =Модель!S44 -> FBS | E64: =SUM(SKU!F41:H41) -> 87 | F64: =SKU!I41/1000 -> 0.0168 | G64: =Модель!U44 -> 45 | H64: =IF(D64="FBS",Модель!AL44,0) -> 5 | I64: =Модель!L44 -> 97.91727 | J64: =IF(D64="FBS",G64*$G$6,0) -> 225 | K64: =IF(D64="FBS",Модель!BP44*F64*Модель!$C$48*$G$10*$L$6,0) -> 9363.69 | L64: =IF(D64="FBS",G64*$G$7,0) -> 405 | M64: =IF(D64="FBS",G64*IF(E64<=$F$16,$G$16,IF(E64<=$F$17,$G$17,IF(E64<=$F$18,$G$18,IF(E64<=$F$19,$G$19,IF(E64<=$F$20,$G$20,IF(E64<=$F$21,$G$21,$G$22)))))),0) -> 900 | N64: =IF(D64="FBS",G64*$G$8,0) -> 180 | O64: =IF(D64="FBS",G64*$G$9,0) -> 1125 | P64: =IF(D64="FBS",H64*$G$11,0) -> 290 | Q64: =SUM(J64:P64) -> 12488.69

Sheet Инструкция
A1: Data pack к тестовому заданию «Запуск схемы FBS на Ozon»
B3: Назначение файла
C4: Файл содержит единые вводные для всех кандидатов: ассортимент (лист «SKU»), тарифы маркетплейса (лист «Тарифы») и операционные затраты продавца (лист «Затраты продавца»). Все расчёты в вашем Excel-файле должны опираться на эти данные.
B6: Правила использования
B7: 1. | C7: Тарифы в файле — УСЛОВНЫЕ. Они приближены к публичной логике тарификации Ozon, но зафиксированы для сопоставимости работ. Используйте их, а не актуальные тарифы с сайта.
B8: 2. | C8: Документацию (база знаний Ozon для продавцов, Ozon Seller API) используйте реальную и актуальную — со ссылками на конкретные разделы и методы.
B9: 3. | C9: Все недостающие данные закрывайте допущениями и фиксируйте их на листе «Допущения» (или на аналогичном листе вашей модели).
B10: 4. | C10: Итоговые цифры в модели должны считаться формулами: при изменении входного параметра (например, комиссии) результат должен пересчитываться. Модель должна быть аккуратной и читаемой.
B11: 5. | C11: Колонка «Продажи, шт/мес» для товаров со схемой «не представлен» — это прогноз категорийного менеджера, а не факт.
B13: Что можно упрощать
C14: Налоги, индекс локализации, программы лояльности и рекламные расходы в модели можно не учитывать. Сезонность достаточно учесть на уровне комментария/допущения.
B16: =HYPERLINK("#'Итоги'!B2","Перейти к итогам модели") -> Перейти к итогам модели
B17: Ключевые листы кандидата
B18: Сценарный анализ | C18: Отдельный reviewer-view: физические количества и стандартный P&L по FBO / FBS / Hybrid / Hybrid с Fulllog.
B19: SLA sensitivity | C19: Модель!C50 — доля FBS-заказов, нарушивших SLA ≤24ч и отменённых продавцом. База 10%, параметр редактируемый.
B20: Fulllog | C20: Публичные тарифы — рабочая оценка, а не коммерческое подтверждение. Перед GO требуется КП и SLA.

Sheet SKU
A1: Артикул | B1: Наименование | C1: Категория | D1: Цена на МП, руб. | E1: Себестоимость, руб. | F1: Длина, см | G1: Ширина, см | H1: Высота, см | I1: Объём, л | J1: Вес, кг | K1: Продажи, шт./мес. | L1: Текущая схема | M1: Оборач-ть FBO, дн. | N1: Возвраты, % | O1: Остаток на своём складе, шт. | P1: Комментарий
A2: SM-0001 | B2: Кроссовки беговые мужские | C2: Обувь | D2: 3990 | E2: 1900 | F2: 33 | G2: 21 | H2: 12 | I2: =F2*G2*H2/1000 -> 8.316 | J2: 0.9 | K2: 260 | L2: FBO | M2: 66.679446 | N2: 0.14 | O2: 780
A3: SM-0002 | B3: Кроссовки трейловые | C3: Обувь | D3: 5490 | E3: 2600 | F3: 34 | G3: 22 | H3: 13 | I3: =F3*G3*H3/1000 -> 9.724 | J3: 1 | K3: 180 | L3: FBO | M3: 67.064723 | N3: 0.15 | O3: 540
A4: SM-0003 | B4: Кеды классические | C4: Обувь | D4: 2490 | E4: 1050 | F4: 32 | G4: 20 | H4: 11 | I4: =F4*G4*H4/1000 -> 7.04 | J4: 0.8 | K4: 340 | L4: FBO | M4: 48.031221 | N4: 0.12 | O4: 900
A5: SM-0004 | B5: Ботинки треккинговые | C5: Обувь | D5: 7990 | E5: 3800 | F5: 35 | G5: 24 | H5: 14 | I5: =F5*G5*H5/1000 -> 11.76 | J5: 1.4 | K5: 85 | L5: FBO | M5: 73.154068 | N5: 0.16 | O5: 260
A6: SM-0005 | B6: Сланцы пляжные | C6: Обувь | D6: 890 | E6: 290 | F6: 28 | G6: 12 | H6: 10 | I6: =F6*G6*H6/1000 -> 3.36 | J6: 0.4 | K6: 480 | L6: FBO | M6: 79.611473 | N6: 0.06 | O6: 1200 | P6: сезонный товар (весна-лето)
A7: SM-0006 | B7: Футболка тренировочная | C7: Одежда | D7: 990 | E7: 340 | F7: 30 | G7: 22 | H7: 3 | I7: =F7*G7*H7/1000 -> 1.98 | J7: 0.25 | K7: 620 | L7: FBO | M7: 77.881051 | N7: 0.15 | O7: 1800
A8: SM-0007 | B8: Шорты беговые | C8: Одежда | D8: 1290 | E8: 430 | F8: 28 | G8: 20 | H8: 4 | I8: =F8*G8*H8/1000 -> 2.24 | J8: 0.25 | K8: 380 | L8: FBO | M8: 82.191663 | N8: 0.14 | O8: 950 | P8: сезонный товар (весна-лето)
A9: SM-0008 | B9: Ветровка для бега | C9: Одежда | D9: 3490 | E9: 1400 | F9: 35 | G9: 25 | H9: 6 | I9: =F9*G9*H9/1000 -> 5.25 | J9: 0.5 | K9: 150 | L9: FBO | M9: 79.712035 | N9: 0.17 | O9: 420
A10: SM-0009 | B10: Куртка зимняя утеплённая | C10: Одежда | D10: 8990 | E10: 4100 | F10: 45 | G10: 35 | H10: 15 | I10: =F10*G10*H10/1000 -> 23.625 | J10: 1.6 | K10: 18 | L10: FBO | M10: 140 | N10: 0.2 | O10: 620 | P10: сезонный товар (осень-зима), сток вне сезона
A11: SM-0010 | B11: Леггинсы женские | C11: Одежда | D11: 1790 | E11: 620 | F11: 28 | G11: 20 | H11: 4 | I11: =F11*G11*H11/1000 -> 2.24 | J11: 0.3 | K11: 290 | L11: FBO | M11: 77.397201 | N11: 0.18 | O11: 700
A12: SM-0011 | B12: Гантели разборные 2×10 кг | C12: Фитнес | D12: 4990 | E12: 2750 | F12: 45 | G12: 25 | H12: 15 | I12: =F12*G12*H12/1000 -> 16.875 | J12: 20.5 | K12: 60 | L12: FBO | M12: 81.658982 | N12: 0.03 | O12: 150
A13: SM-0012 | B13: Гиря чугунная 16 кг | C13: Фитнес | D13: 2990 | E13: 1750 | F13: 25 | G13: 20 | H13: 22 | I13: =F13*G13*H13/1000 -> 11 | J13: 16.2 | K13: 45 | L13: FBO | M13: 60.716212 | N13: 0.02 | O13: 110
A14: SM-0013 | B14: Коврик для йоги 6 мм | C14: Фитнес | D14: 1490 | E14: 520 | F14: 66 | G14: 15 | H14: 15 | I14: =F14*G14*H14/1000 -> 14.85 | J14: 1.1 | K14: 320 | L14: FBO | M14: 88.153619 | N14: 0.04 | O14: 800
A15: SM-0014 | B15: Набор эспандеров | C15: Фитнес | D15: 790 | E15: 260 | F15: 18 | G15: 12 | H15: 6 | I15: =F15*G15*H15/1000 -> 1.296 | J15: 0.4 | K15: 410 | L15: FBO | M15: 44.843155 | N15: 0.04 | O15: 950
A16: SM-0015 | B16: Скакалка скоростная | C16: Аксессуары | D16: 490 | E16: 150 | F16: 20 | G16: 12 | H16: 4 | I16: =F16*G16*H16/1000 -> 0.96 | J16: 0.2 | K16: 370 | L16: FBO | M16: 79.62719 | N16: 0.03 | O16: 850
A17: SM-0016 | B17: Палатка 2-местная | C17: Туризм | D17: 6990 | E17: 3200 | F17: 58 | G17: 20 | H17: 20 | I17: =F17*G17*H17/1000 -> 23.2 | J17: 3.8 | K17: 45 | L17: FBO | M17: 44.53253 | N17: 0.06 | O17: 340 | P17: сезонный товар (весна-лето)
A18: SM-0017 | B18: Палатка 4-местная | C18: Туризм | D18: 12990 | E18: 6100 | F18: 68 | G18: 26 | H18: 26 | I18: =F18*G18*H18/1000 -> 45.968 | J18: 7.5 | K18: 22 | L18: FBO | M18: 47.409611 | N18: 0.07 | O18: 180 | P18: сезонный товар (весна-лето)
A19: SM-0018 | B19: Спальный мешок −5 °C | C19: Туризм | D19: 3490 | E19: 1480 | F19: 40 | G19: 28 | H19: 28 | I19: =F19*G19*H19/1000 -> 31.36 | J19: 1.9 | K19: 70 | L19: FBO | M19: 68.899772 | N19: 0.06 | O19: 260
A20: SM-0019 | B20: Рюкзак туристический 60 л | C20: Туризм | D20: 5990 | E20: 2550 | F20: 65 | G20: 35 | H20: 25 | I20: =F20*G20*H20/1000 -> 56.875 | J20: 2.1 | K20: 55 | L20: FBO | M20: 78.989018 | N20: 0.08 | O20: 210
A21: SM-0020 | B21: Коврик туристический пенный | C21: Туризм | D21: 990 | E21: 370 | F21: 60 | G21: 16 | H21: 16 | I21: =F21*G21*H21/1000 -> 15.36 | J21: 0.6 | K21: 90 | L21: FBO | M21: 88.712523 | N21: 0.03 | O21: 320
A22: SM-0021 | B22: Велотренажёр магнитный | C22: Крупногабарит | D22: 24990 | E22: 14200 | F22: 92 | G22: 50 | H22: 30 | I22: =F22*G22*H22/1000 -> 138 | J22: 31 | K22: 25 | L22: не представлен | M22: n/a | N22: 0.05 | O22: 60 | P22: оценка КМ, листинга на Ozon нет
A23: SM-0022 | B23: Беговая дорожка складная | C23: Крупногабарит | D23: 49990 | E23: 28900 | F23: 160 | G23: 72 | H23: 30 | I23: =F23*G23*H23/1000 -> 345.6 | J23: 58 | K23: 12 | L23: не представлен | M23: n/a | N23: 0.05 | O23: 30 | P23: оценка КМ, листинга на Ozon нет
A24: SM-0023 | B24: Батут каркасный 305 см | C24: Крупногабарит | D24: 18990 | E24: 10400 | F24: 150 | G24: 40 | H24: 38 | I24: =F24*G24*H24/1000 -> 228 | J24: 46 | K24: 15 | L24: не представлен | M24: n/a | N24: 0.04 | O24: 45 | P24: оценка КМ, сезонный (весна-лето)
A25: SM-0024 | B25: SUP-доска надувная | C25: Крупногабарит | D25: 21990 | E25: 11900 | F25: 95 | G25: 45 | H25: 30 | I25: =F25*G25*H25/1000 -> 128.25 | J25: 12.5 | K25: 20 | L25: не представлен | M25: n/a | N25: 0.06 | O25: 55 | P25: оценка КМ, сезонный (весна-лето)
A26: SM-0025 | B26: Каяк надувной 2-местный | C26: Крупногабарит | D26: 34990 | E26: 19400 | F26: 100 | G26: 52 | H26: 35 | I26: =F26*G26*H26/1000 -> 182 | J26: 24 | K26: 8 | L26: не представлен | M26: n/a | N26: 0.06 | O26: 25 | P26: оценка КМ, сезонный (весна-лето)
A27: SM-0026 | B27: Стол теннисный складной | C27: Крупногабарит | D27: 54990 | E27: 31800 | F27: 160 | G27: 142 | H27: 12 | I27: =F27*G27*H27/1000 -> 272.64 | J27: 68 | K27: 6 | L27: не представлен | M27: n/a | N27: 0.04 | O27: 15 | P27: оценка КМ
A28: SM-0027 | B28: Шведская стенка деревянная | C28: Крупногабарит | D28: 15990 | E28: 8700 | F28: 242 | G28: 32 | H28: 16 | I28: =F28*G28*H28/1000 -> 123.904 | J28: 27 | K28: 10 | L28: не представлен | M28: n/a | N28: 0.05 | O28: 35 | P28: оценка КМ
A29: SM-0028 | B29: Ласты тренировочные | C29: Фитнес | D29: 1990 | E29: 790 | F29: 48 | G29: 22 | H29: 8 | I29: =F29*G29*H29/1000 -> 8.448 | J29: 0.9 | K29: 25 | L29: не представлен | M29: n/a | N29: 0.07 | O29: 90 | P29: оценка КМ
A30: SM-0029 | B30: Очки для плавания стартовые | C30: Аксессуары | D30: 2490 | E30: 880 | F30: 15 | G30: 7 | H30: 6 | I30: =F30*G30*H30/1000 -> 0.63 | J30: 0.1 | K30: 40 | L30: не представлен | M30: n/a | N30: 0.05 | O30: 130 | P30: оценка КМ
A31: SM-0030 | B31: Перчатки боксёрские 14 oz | C31: Фитнес | D31: 3490 | E31: 1520 | F31: 35 | G31: 20 | H31: 13 | I31: =F31*G31*H31/1000 -> 9.1 | J31: 0.8 | K31: 30 | L31: не представлен | M31: n/a | N31: 0.06 | O31: 100 | P31: оценка КМ
A32: SM-0031 | B32: Шлем горнолыжный | C32: Аксессуары | D32: 4990 | E32: 2250 | F32: 30 | G32: 25 | H32: 24 | I32: =F32*G32*H32/1000 -> 18 | J32: 0.7 | K32: 15 | L32: не представлен | M32: n/a | N32: 0.09 | O32: 140 | P32: оценка КМ, сезонный (осень-зима)
A33: SM-0032 | B33: Крепления для сноуборда | C33: Аксессуары | D33: 8990 | E33: 4280 | F33: 35 | G33: 32 | H33: 13 | I33: =F33*G33*H33/1000 -> 14.56 | J33: 2.4 | K33: 10 | L33: не представлен | M33: n/a | N33: 0.07 | O33: 85 | P33: оценка КМ, сезонный (осень-зима)
A34: SM-0033 | B34: Бутылка спортивная 0,7 л | C34: Аксессуары | D34: 690 | E34: 210 | F34: 26 | G34: 8 | H34: 8 | I34: =F34*G34*H34/1000 -> 1.664 | J34: 0.15 | K34: 520 | L34: FBO | M34: 92.494763 | N34: 0.02 | O34: 1500
A35: SM-0034 | B35: Носки спортивные (3 пары) | C35: Аксессуары | D35: 590 | E35: 175 | F35: 20 | G35: 12 | H35: 4 | I35: =F35*G35*H35/1000 -> 0.96 | J35: 0.15 | K35: 700 | L35: FBO | M35: 59.783911 | N35: 0.03 | O35: 2100
A36: SM-0035 | B36: Перчатки для фитнеса | C36: Аксессуары | D36: 690 | E36: 225 | F36: 18 | G36: 12 | H36: 3 | I36: =F36*G36*H36/1000 -> 0.648 | J36: 0.1 | K36: 260 | L36: FBO | M36: 77.854435 | N36: 0.05 | O36: 600
A37: SM-0036 | B37: Рюкзак городской 22 л | C37: Аксессуары | D37: 2990 | E37: 1180 | F37: 45 | G37: 30 | H37: 16 | I37: =F37*G37*H37/1000 -> 21.6 | J37: 0.7 | K37: 190 | L37: FBO | M37: 61.07212 | N37: 0.08 | O37: 480
A38: SM-0037 | B38: Сумка спортивная 45 л | C38: Аксессуары | D38: 2490 | E38: 990 | F38: 55 | G38: 28 | H38: 28 | I38: =F38*G38*H38/1000 -> 43.12 | J38: 0.8 | K38: 140 | L38: FBO | M38: 69.625232 | N38: 0.07 | O38: 380
A39: SM-0038 | B39: Мяч футбольный (без накачки) | C39: Фитнес | D39: 1890 | E39: 690 | F39: 23 | G39: 23 | H39: 12 | I39: =F39*G39*H39/1000 -> 6.348 | J39: 0.45 | K39: 210 | L39: FBO | M39: 73.412177 | N39: 0.03 | O39: 520
A40: SM-0039 | B40: Мяч баскетбольный | C40: Фитнес | D40: 2190 | E40: 830 | F40: 25 | G40: 25 | H40: 13 | I40: =F40*G40*H40/1000 -> 8.125 | J40: 0.6 | K40: 130 | L40: FBO | M40: 102.70633 | N40: 0.04 | O40: 300
A41: SM-0040 | B41: Ролики раздвижные р. 38–41 | C41: Обувь | D41: 6990 | E41: 3250 | F41: 40 | G41: 35 | H41: 12 | I41: =F41*G41*H41/1000 -> 16.8 | J41: 2.6 | K41: 45 | L41: FBO | M41: 97.91727 | N41: 0.11 | O41: 160
B43: Примечание: «Продажи, шт/мес» для схемы «не представлен» — прогноз категорийного менеджера. Возвраты, % — доля заказов, возвращаемых покупателем.

Sheet Тарифы
A1: Тарифы маркетплейса (УСЛОВНЫЕ, зафиксированы для сопоставимости работ)
A3: Параметр | B3: Значение | C3: Ед. изм. | D3: Комментарий
A4: Комиссия за продажу, % от цены (FBO / FBS)
A5: Комиссия FBO — Обувь | B5: 0.16 | C5: % от цены
A6: Комиссия FBS — Обувь | B6: 0.15 | C6: % от цены
A7: Комиссия FBO — Одежда | B7: 0.17 | C7: % от цены
A8: Комиссия FBS — Одежда | B8: 0.16 | C8: % от цены
A9: Комиссия FBO — Фитнес | B9: 0.15 | C9: % от цены
A10: Комиссия FBS — Фитнес | B10: 0.14 | C10: % от цены
A11: Комиссия FBO — Туризм | B11: 0.15 | C11: % от цены
A12: Комиссия FBS — Туризм | B12: 0.14 | C12: % от цены
A13: Комиссия FBO — Крупногабарит | B13: 0.12 | C13: % от цены
A14: Комиссия FBS — Крупногабарит | B14: 0.11 | C14: % от цены
A15: Комиссия FBO — Аксессуары | B15: 0.18 | C15: % от цены
A16: Комиссия FBS — Аксессуары | B16: 0.17 | C16: % от цены
A17: Логистика и обработка — FBO
A18: Логистика FBO: базовая ставка (до 5 л) | B18: 80 | C18: руб./отправл. | D18: За отправление объёмом до 5 л включительно
A19: Логистика FBO: доплата за каждый литр свыше 5 л | B19: 10 | C19: руб./л
A20: Последняя миля | B20: 25 | C20: руб./отправл.
A21: Хранение на складе FBO | B21: 0.45 | C21: руб./л/сутки | D21: Категория «Крупногабарит» — 0,50 руб/л/сутки
A22: Обратная логистика возврата FBO | B22: 1 | C22: × Логистика FBO | D22: Равна прямой; последняя миля при возврате не взимается
A23: Логистика и обработка — FBS
A24: Обработка отправления в пункте приёма (drop-off) | B24: 10 | C24: руб./отправл.
A25: Логистика FBS: базовая ставка (до 5 л) | B25: 80 | C25: руб./отправл. | D25: За отправление объёмом до 5 л включительно
A26: Логистика FBS: доплата за каждый литр свыше 5 л | B26: 10 | C26: руб./л
A27: Последняя миля | B27: 25 | C27: руб./отправл.
A28: Обратная логистика возврата FBS | B28: 1 | C28: × логистика FBS | D28: Равна прямой; последняя миля и тариф за drop-off не взимаются
A29: Штраф за отмену по вине продавца | B29: 150 | C29: руб./отправл. | D29: Условно; дополнительно — влияние на рейтинг продавца
A30: SLA сборки и передачи отправления FBS | B30: 24 | C30: часа | D30: С момента поступления заказа; просрочка ведёт к отмене
A31: Общие условия
A32: Эквайринг | B32: 0.015 | C32: % от цены | D32: Применяется в обеих схемах
A33: Индекс локализации, реклама, программы лояльности | B33: не учитывать | D33: Сознательное упрощение модели

Sheet Затраты продавца
A1: Операционные затраты продавца (собственный контур)
A3: Параметр | B3: Значение | C3: Ед. изм. | D3: Комментарий
A4: Собственный склад и сборка (для FBS)
A5: Хранение на собственном складе | B5: 0.15 | C5: руб./л/сутки | D5: Учётная ставка: аренда + обслуживание
A6: Сборка отправления FBS (труд) | B6: 60 | C6: руб./отправл.
A7: Упаковочные материалы | B7: 10 | C7: руб./отправл.
A8: Рейс до пункта приёма Ozon | B8: 2500 | C8: руб./рейс | D8: Вместимость рейса: до 250 отправлений или до 6 м³ (что наступит раньше). Плановая частота — ежедневно
A9: Обработка возврата на своём складе (приёмка, проверка) | B9: 100 | C9: руб./шт
A10: Доля возвратов, возвращаемая в продажу | B10: 0.85 | C10: % | D10: Остальное — уценка −50% к себестоимости или списание
A11: Поставки на склад FBO
A12: Входящая логистика до склада Ozon (амортизированно) | B12: 2.5 | C12: руб./л | D12: Транспорт + обработка поставки, в расчёте на литр поставленного товара

Sheet Допущения
A1: Журнал допущений кандидата
A3: № | B3: Блок | C3: Допущение | D3: Обоснование / источник
A4: 1 | B4: Экономика | C4: «Продажи, шт./мес.» считаются выкупленными товарами. Физические количества округляются вверх: отправления = ROUNDUP(выкупы / (1 − доля возвратов)); возвраты = отправления − выкупы. | D4: Согласованная трактовка data pack; физически дробных отправлений/возвратов не бывает.
A5: 2 | B5: Спрос | C5: В базовом сценарии спрос FBS равен спросу из дата-пака. | D5: Фактическую эластичность к сроку доставки проверяем отдельно
A6: 3 | B6: Отмены | C6: В базовом сценарии 10% FBS-заказов считаются нарушившими SLA ≤24 ч и отменёнными продавцом. Они не становятся отправлениями/выкупами; на каждую отмену начисляется штраф 150 ₽. | D6: Рабочий sensitivity после senior-review; редактируется в Модель!C50. Финальный target пилота должен быть подтверждён операциями.
A7: 4 | B7: Новые SKU | C7: Прогноз продаж новых SKU выполняется на 100%. | D7: Прогноз категорийного менеджера из исходного файла
A8: 5 | B8: Оборачиваемость | C8: Для новых SKU используется средняя оборачиваемость действующих FBO-товаров. | D8: В исходных данных нет фактической оборачиваемости новых SKU. Допущение оставить до появления данных пилота.
A9: 6 | B9: Возвраты: единое правило | C9: 15% возвратов списываются по полной себестоимости во всех схемах; годные 85% возвращаются в оборот. | D9: Затраты продавца B10 и Модель C55; применяется и к FBO.
A10: 7 | B10: Хранение | C10: Для собственного склада используется та же оборачиваемость, что и для FBO. | D10: Отдельный прогноз запаса собственного склада отсутствует
A11: 8 | B11: Рейсы | C11: Месяц — 30 дней, передача ежедневная; рейсы определяет более жёсткий лимит: 250 отправлений или 6 м³. | D11: Параметры вместимости из листа «Затраты продавца»
A12: 9 | B12: Первая миля | C12: FBO: объём поставки × 2,5 ₽/л. Собственный FBS: число рейсов × 2 500 ₽/рейс. Hybrid: FBO-часть по объёму + общие FBS-рейсы. Hybrid с Fulllog: FBO-часть по data pack + FBS-поток Sportmaster → Fulllog по отдельному допущению. | D12: Data pack: «Затраты продавца» B8 и B12. Для SM → Fulllog используется отдельное допущение до коммерческого предложения.
A13: 10 | B13: Рейсы | C13: Для собственного FBS число рейсов считается на весь FBS-поток портфеля по более жёсткому лимиту: 250 отправлений или 6 м³; затем умножается на 2 500 ₽/рейс. | D13: «Затраты продавца» B8; модельный месяц — 30 дней.
A14: 11 | B14: Fulllog: поток | C14: Fulllog принимает только FBS-поток выбранного гибрида. Выбор FBO/FBS/Пауза выполняется на уровне SKU без общей первой мили; первая миля начисляется затем на портфель в P&L. | D14: Модель S, U, V; Fulllog 3PL K7:N7.
A15: 12 | B15: Fulllog: приёмка | C15: 5 ₽ за единицу. | D15: Публичный прайс: https://fulllog.ru/prices ; проверен 13.09.2026, коммерчески не подтверждён.
... A35: 32 | B35: Пауза SKU | C35: Если SKU убыточен и в FBO, и в FBS, он исключается из активных продаж во всех четырёх сценариях: FBO, FBS, Hybrid и Hybrid с Fulllog. | D35: Единый ассортиментный принцип для сопоставимости моделей: схема исполнения не должна заставлять продавать заведомо убыточный SKU. Экономика таких SKU сохраняется на листе «Модель» как обоснование решения.

Sheet Сценарный анализ
A1: Сценарный анализ — операционные показатели и P&L по четырём вариантам
A2: Расчётный движок остаётся на листе «Модель». Сценарии разнесены для ревью; SKU с отрицательной экономикой и в FBO, и в FBS ставятся на паузу во всех сценариях.
A4: FBO | E4: FBS | I4: Гибрид | M4: Гибрид с Fulllog (3PL)
A5: Операционные показатели | B5: Значение | C5: Комментарий | E5: Операционные показатели | F5: Значение | G5: Комментарий | I5: Операционные показатели | J5: Значение | K5: Комментарий | M5: Операционные показатели | N5: Значение | O5: Комментарий
A6: Активные SKU, шт. | B6: =Итоги!C12 -> 38 | C6: Портфель в сценарии | E6: Активные SKU, шт. | F6: =Итоги!D12 -> 0 | G6: Портфель в сценарии | I6: Активные SKU, шт. | J6: =Итоги!E12 -> 17 | K6: Портфель в сценарии | M6: Активные SKU, шт. | N6: =Итоги!F12 -> 17 | O6: Портфель в сценарии
A7: SKU → FBO, шт. | B7: =Итоги!C13 -> 0 | C7: Распределение SKU | E7: SKU → FBO, шт. | F7: =Итоги!D13 -> 38 | G7: Распределение SKU | I7: SKU → FBO, шт. | J7: =Итоги!E13 -> 21 | K7: Распределение SKU | M7: SKU → FBO, шт. | N7: =Итоги!F13 -> 21 | O7: Распределение SKU
A8: SKU → FBS, шт. | B8: =Итоги!C14 -> 2 | C8: Распределение SKU | E8: SKU → FBS, шт. | F8: =Итоги!D14 -> 2 | G8: Распределение SKU | I8: SKU → FBS, шт. | J8: =Итоги!E14 -> 2 | K8: Распределение SKU | M8: SKU → FBS, шт. | N8: =Итоги!F14 -> 2 | O8: Распределение SKU
A9: SKU → Пауза, шт. | B9: =Итоги!C15 -> 0 | C9: Отрицательная экономика → управленческое решение | E9: SKU → Пауза, шт. | F9: =Итоги!D15 -> 30 | G9: Отрицательная экономика → управленческое решение | I9: SKU → Пауза, шт. | J9: =Итоги!E15 -> 30 | K9: Отрицательная экономика → управленческое решение | M9: SKU → Пауза, шт. | N9: =Итоги!F15 -> 0 | O9: Отрицательная экономика → управленческое решение
A10: Отправления, шт./мес. | B10: =SUMPRODUCT((Модель!S5:S44<>"Пауза")*Модель!X5:X44) -> 7077 | C10: Физически обработанный поток | E10: Отправления, шт./мес. | F10: =SUMPRODUCT((Модель!S5:S44<>"Пауза")*Модель!AK5:AK44) -> 6348 | G10: Физически обработанный поток | I10: Отправления, шт./мес. | J10: =SUM(Модель!BA5:BA44) -> 6935 | K10: Физически обработанный поток | M10: Отправления, шт./мес. | N10: =SUM(Модель!BA5:BA44) -> 6935 | O10: Физически обработанный поток
A11: Выкупы, шт./мес. | B11: =SUMPRODUCT((Модель!S5:S44<>"Пауза")*Модель!G5:G44) -> 6471 | C11: Остались у покупателя | E11: Выкупы, шт./мес. | F11: =SUMPRODUCT((Модель!S5:S44<>"Пауза")*Модель!AM5:AM44) -> 5801 | G11: Остались у покупателя | I11: Выкупы, шт./мес. | J11: =SUM(Модель!AZ5:AZ44) -> 6338 | K11: Остались у покупателя | M11: Выкупы, шт./мес. | N11: =SUM(Модель!AZ5:AZ44) -> 6338 | O11: Остались у покупателя
A12: Возвраты, шт./мес. | B12: =SUMPRODUCT((Модель!S5:S44<>"Пауза")*Модель!Y5:Y44) -> 606 | C12: Вернулись / не выкуплены | E12: Возвраты, шт./мес. | F12: =SUMPRODUCT((Модель!S5:S44<>"Пауза")*Модель!AL5:AL44) -> 547 | G12: Вернулись / не выкуплены | I12: Возвраты, шт./мес. | J12: =SUMPRODUCT((Модель!S5:S44="FBO")*Модель!Y5:Y44)+SUMPRODUCT((Модель!S5:S44="FBS")*Модель!AL5:AL44) -> 597 | K12: Вернулись / не выкуплены | M12: Возвраты, шт./мес. | N12: =SUMPRODUCT((Модель!S5:S44="FBO")*Модель!Y5:Y44)+SUMPRODUCT((Модель!S5:S44="FBS")*Модель!AL5:AL44) -> 597 | O12: Вернулись / не выкуплены
A13: Отмены по SLA, шт./мес. | B13: =0 -> 0 | C13: Нарушение SLA ≤24 ч → seller cancellation | E13: Отмены по SLA, шт./мес. | F13: =SUMPRODUCT((Модель!S5:S44<>"Пауза")*Модель!AJ5:AJ44) -> 729 | G13: Нарушение SLA ≤24 ч → seller cancellation | I13: Отмены по SLA, шт./мес. | J13: =SUMPRODUCT((Модель!S5:S44="FBS")*Модель!AJ5:AJ44) -> 142 | K13: Нарушение SLA ≤24 ч → seller cancellation | M13: Отмены по SLA, шт./мес. | N13: =SUMPRODUCT((Модель!S5:S44="FBS")*Модель!AJ5:AJ44) -> 142 | O13: Нарушение SLA ≤24 ч → seller cancellation
A14: Нормативный запас, шт. | B14: =SUMPRODUCT((Модель!S5:S44<>"Пауза")*Модель!BO5:BO44) -> 17296 | C14: Связка оборачиваемость → запас → хранение | E14: Нормативный запас, шт. | F14: =SUMPRODUCT((Модель!S5:S44<>"Пауза")*Модель!BP5:BP44) -> 17296 | G14: Связка оборачиваемость → запас → хранение | I14: Нормативный запас, шт. | J14: =SUM(Модель!BQ5:BQ44) -> 17296 | K14: Связка оборачиваемость → запас → хранение | M14: Нормативный запас, шт. | N14: =SUM(Модель!BQ5:BQ44) -> 17296 | O14: Связка оборачиваемость → запас → хранение
A15: Рейсы собственного FBS → Ozon, раз/мес. | B15: =0 -> 0 | C15: По лимиту 250 отправлений / 6 м³ | E15: Рейсы собственного FBS → Ozon, раз/мес. | F15: =Итоги!D16 -> 0.9 | G15: По лимиту 250 отправлений / 6 м³ | I15: Рейсы собственного FBS → Ozon, раз/мес. | J15: =Итоги!E16 -> 0.9 | K15: По лимиту 250 отправлений / 6 м³ | M15: Рейсы собственного FBS → Ozon, раз/мес. | N15: =0 -> 0 | O15: По лимиту 250 отправлений / 6 м³
A16: SLA FBS: передано ≤24 ч, % | B16: =0 -> 0 | C16: Рабочее допущение; уточняется пилотом / SLA партнёра | E16: SLA FBS: передано ≤24 ч, % | F16: =Итоги!D18 -> 0 | G16: Рабочее допущение; уточняется пилотом / SLA партнёра | I16: SLA FBS: передано ≤24 ч, % | J16: =Итоги!E18 -> 0 | K16: Рабочее допущение; уточняется пилотом / SLA партнёра | M16: SLA FBS: передано ≤24 ч, % | N16: =Итоги!F18 -> 0 | O16: Рабочее допущение; уточняется пилотом / SLA партнёра
A18: P&L | B18: Значение | C18: Источник | E18: P&L | F18: Значение | G18: Источник | I18: P&L | J18: Значение | K18: Источник | M18: P&L | N18: Значение | O18: Источник
A19: Выручка, ₽/мес. | B19: =Итоги!C22 -> 14530290 | C19: Итоги | E19: Выручка, ₽/мес. | F19: =Итоги!D22 -> 12876790 | G19: Итоги | I19: Выручка, ₽/мес. | J19: =Итоги!E22 -> 13668020 | K19: Итоги | M19: Выручка, ₽/мес. | N19: =Итоги!F22 -> 13668020 | O19: Итоги
A20: Себестоимость выкупов, ₽/мес. | B20: =Итоги!C23 -> 6332650 | C20: Итоги | E20: Себестоимость выкупов, ₽/мес. | F20: =Итоги!D23 -> 5594240 | G20: Итоги | I20: Себестоимость выкупов, ₽/мес. | J20: =Итоги!E23 -> 5902340 | K20: Итоги | M20: Себестоимость выкупов, ₽/мес. | N20: =Итоги!F23 -> 5902340 | O20: Итоги
A21: Валовая прибыль, ₽/мес. | B21: =Итоги!C24 -> 8197640 | C21: Итоги | E21: Валовая прибыль, ₽/мес. | F21: =Итоги!D24 -> 7282550 | G21: Итоги | I21: Валовая прибыль, ₽/мес. | J21: =Итоги!E24 -> 7765680 | K21: Итоги | M21: Валовая прибыль, ₽/мес. | N21: =Итоги!F24 -> 7765680 | O21: Итоги
A22: Комиссия Ozon, ₽/мес. | B22: =Итоги!C27 -> 2246020.2 | C22: Итоги | E22: Комиссия Ozon, ₽/мес. | F22: =Итоги!D27 -> 1865684 | G22: Итоги | I22: Комиссия Ozon, ₽/мес. | J22: =Итоги!E27 -> 2064528.4 | K22: Итоги | M22: Комиссия Ozon, ₽/мес. | N22: =Итоги!F27 -> 2064528.4 | O22: Итоги
A23: Эквайринг, ₽/мес. | B23: =Итоги!C28 -> 217954.35 | C23: Итоги | E23: Эквайринг, ₽/мес. | F23: =Итоги!D28 -> 193151.85 | G23: Итоги | I23: Эквайринг, ₽/мес. | J23: =Итоги!E28 -> 205020.3 | K23: Итоги | M23: Эквайринг, ₽/мес. | N23: =Итоги!F28 -> 205020.3 | O23: Итоги
A24: Первая миля, ₽/мес. | B24: =Итоги!C29 -> 151335.48 | C24: Итоги | E24: Первая миля, ₽/мес. | F24: =Итоги!D29 -> 75000 | G24: Итоги | I24: Первая миля, ₽/мес. | J24: =Итоги!E29 -> 119332.49 | K24: Итоги | M24: Первая миля, ₽/мес. | N24: =Итоги!F29 -> 138580.02 | O24: Итоги
A25: Хранение, ₽/мес. | B25: =Итоги!C30 -> 2097850.1 | C25: Итоги | E25: Хранение, ₽/мес. | F25: =Итоги!D30 -> 674342.55 | G25: Итоги | I25: Хранение, ₽/мес. | J25: =Итоги!E30 -> 1044600.1 | K25: Итоги | M25: Хранение, ₽/мес. | N25: =Итоги!F30 -> 918219.83 | O25: Итоги
A26: Сборка / подбор, ₽/мес. | B26: =Итоги!C31 -> 0 | C26: Итоги | E26: Сборка / подбор, ₽/мес. | F26: =Итоги!D31 -> 380880 | G26: Итоги | I26: Сборка / подбор, ₽/мес. | J26: =Итоги!E31 -> 70500 | K26: Итоги | M26: Сборка / подбор, ₽/мес. | N26: =Итоги!F31 -> 21150 | O26: Итоги
A27: Упаковка, ₽/мес. | B27: =Итоги!C32 -> 0 | C27: Итоги | E27: Упаковка, ₽/мес. | F27: =Итоги!D32 -> 63480 | G27: Итоги | I27: Упаковка, ₽/мес. | J27: =Итоги!E32 -> 11750 | K27: Итоги | M27: Упаковка, ₽/мес. | N27: =Итоги!F32 -> 28410 | O27: Итоги
A28: Передача FBS в Ozon, ₽/мес. | B28: =Итоги!C33 -> 0 | C28: Итоги | E28: Передача FBS в Ozon, ₽/мес. | F28: =Итоги!D33 -> 63480 | G28: Итоги | I28: Передача FBS в Ozon, ₽/мес. | J28: =Итоги!E33 -> 11750 | K28: Итоги | M28: Передача FBS в Ozon, ₽/мес. | N28: =Итоги!F33 -> 29375 | O28: Итоги
A29: Прямая логистика Ozon, ₽/мес. | B29: =Итоги!C34 -> 962020.39 | C29: Итоги | E29: Прямая логистика Ozon, ₽/мес. | F29: =Итоги!D34 -> 856216.43 | G29: Итоги | I29: Прямая логистика Ozon, ₽/мес. | J29: =Итоги!E34 -> 906738.53 | K29: Итоги | M29: Прямая логистика Ozon, ₽/мес. | N29: =Итоги!F34 -> 906738.53 | O29: Итоги
A30: Последняя миля Ozon, ₽/мес. | B30: =Итоги!C35 -> 176925 | C30: Итоги | E30: Последняя миля Ozon, ₽/мес. | F30: =Итоги!D35 -> 158700 | G30: Итоги | I30: Последняя миля Ozon, ₽/мес. | J30: =Итоги!E35 -> 173375 | K30: Итоги | M30: Последняя миля Ozon, ₽/мес. | N30: =Итоги!F35 -> 173375 | O30: Итоги
A31: Возвратная логистика Ozon, ₽/мес. | B31: =Итоги!C36 -> 82202.78 | C31: Итоги | E31: Возвратная логистика Ozon, ₽/мес. | F31: =Итоги!D36 -> 76085.74 | G31: Итоги | I31: Возвратная логистика Ozon, ₽/мес. | J31: =Итоги!E36 -> 80483.08 | K31: Итоги | M31: Возвратная логистика Ozon, ₽/мес. | N31: =Итоги!F36 -> 80483.08 | O31: Итоги
A32: Обработка возвратов, ₽/мес. | B32: =Итоги!C37 -> 0 | C32: Итоги | E32: Обработка возвратов, ₽/мес. | F32: =Итоги!D37 -> 54700 | G32: Итоги | I32: Обработка возвратов, ₽/мес. | J32: =Итоги!E37 -> 8700 | K32: Итоги | M32: Обработка возвратов, ₽/мес. | N32: =Итоги!F37 -> 5046 | O32: Итоги
A33: Штрафы / списания, ₽/мес. | B33: =Итоги!C38 -> 111684 | C33: Итоги | E33: Штрафы / списания, ₽/мес. | F33: =Итоги!D38 -> 212339.25 | G33: Итоги | I33: Штрафы / списания, ₽/мес. | J33: =Итоги!E38 -> 130107 | K33: Итоги | M33: Штрафы / списания, ₽/мес. | N33: =Итоги!F38 -> 130107 | O33: Итоги
A34: Операционные расходы (без COGS), ₽/мес. | B34: =Итоги!C39 -> 6045992.3 | C34: Итоги | E34: Операционные расходы (без COGS), ₽/мес. | F34: =Итоги!D39 -> 4674059.8 | G34: Итоги | I34: Операционные расходы (без COGS), ₽/мес. | J34: =Итоги!E39 -> 4826884.9 | K34: Итоги | M34: Операционные расходы (без COGS), ₽/мес. | N34: =Итоги!F39 -> 4701033.2 | O34: Итоги
A35: Операционная прибыль, ₽/мес. | B35: =Итоги!C42 -> 2151647.7 | C35: Итоги | E35: Операционная прибыль, ₽/мес. | F35: =Итоги!D42 -> 2608490.2 | G35: Итоги | I35: Операционная прибыль, ₽/мес. | J35: =Итоги!E42 -> 2938795.1 | K35: Итоги | M35: Операционная прибыль, ₽/мес. | N35: =Итоги!F42 -> 3064646.8 | O35: Итоги
A36: Операционная маржа | B36: =Итоги!C43 -> 0.14808016 | C36: Итоги | E36: Операционная маржа | F36: =Итоги!D43 -> 0.20257302 | G36: Итоги | I36: Операционная маржа | J36: =Итоги!E43 -> 0.2150125 | K36: Итоги | M36: Операционная маржа | N36: =Итоги!F43 -> 0.22422025 | O36: Итоги
A37: Разница к FBO, ₽/мес. | B37: =Итоги!C44 -> 0 | C37: Итоги | E37: Разница к FBO, ₽/мес. | F37: =Итоги!D44 -> 456842.47 | G37: Итоги | I37: Разница к FBO, ₽/мес. | J37: =Итоги!E44 -> 787147.43 | K37: Итоги | M37: Разница к FBO, ₽/мес. | N37: =Итоги!F44 -> 912999.13 | O37: Итоги
